Workbook

Sheet Assumptions
A1: OpenBench — Assumptions Register (Team Inferno, Tech Zephyr Finale)
A2: Legend: blue = input you can change · black = formula · green = link to another sheet · yellow = key assumption. Change any blue cell; every sheet recalculates.
A4: ID | B4: Parameter | C4: Base | D4: Downside | E4: Upside | F4: Downside + response | G4: Unit | H4: Source / rationale
A5: A1 | B5: Capture of Exhibit 2 mature volume | C5: 0.85 | D5: 0.65 | E5: 1 | F5: =D5 -> 0.65 | G5: % | H5: Pilot runs at 17.5 vs 20 baseline bookings/host = 87.5% (Ex.1, Ex.3). Base 85%; downside 65%.
A6: A2 | B6: Ramp: share of mature volume, live month 1 | C6: 0.3 | D6: =C6 -> 0.3 | E6: =C6 -> 0.3 | F6: =D6 -> 0.3 | G6: % | H6: Team assumption: new host needs ~3 months to fill committed slots
A7: A3 | B7: Ramp: live month 2 | C7: 0.6 | D7: =C7 -> 0.6 | E7: =C7 -> 0.6 | F7: =D7 -> 0.6 | G7: % | H7: Team assumption
A8: A4 | B8: Ramp: live month 3 | C8: 0.85 | D8: =C8 -> 0.85 | E8: =C8 -> 0.85 | F8: =D8 -> 0.85 | G8: % | H8: Team assumption
A9: A5 | B9: Ramp: live month 4+ | C9: 1 | D9: =C9 -> 1 | E9: =C9 -> 1 | F9: =D9 -> 1 | G9: % | H9: Team assumption
A10: A6 | B10: Pilot host bookings/month today | C10: 17.5 | D10: =C10 -> 17.5 | E10: =C10 -> 17.5 | F10: =D10 -> 17.5 | G10: # | H10: Ex.1: 70 bookings / 4 hosts
A11: A7 | B11: Pilot host bookings/month after Assured conversion | C11: 20 | D11: =C11 -> 20 | E11: =C11 -> 20 | F11: =D11 -> 20 | G11: # | H11: Ex.3 comparison baseline (20/host)
A12: A8 | B12: Months for pilot hosts to reach target | C12: 3 | D12: =C12 -> 3 | E12: =C12 -> 3 | F12: =D12 -> 3 | G12: months | H12: Team assumption
A13: A9 | B13: Average booking value multiplier | C13: 1 | D13: 0.9 | E13: 1 | F13: =D13 -> 0.9 | G13: x | H13: Downside: 10% price pressure
A14: A10 | B14: Bookings lost to cancellation (beyond tier on-time) | C14: 0 | D14: 0.05 | E14: 0 | F14: =D14 -> 0.05 | G14: % | H14: Downside stress
A15: A11 | B15: Onboarding delay for new hosts | C15: 0 | D15: 2 | E15: 0 | F15: =D15 -> 2 | G15: months | H15: Downside: institutional approvals slip 2 months (Stanford/Science Exchange precedent [S6])
A16: A12 | B16: Fixed cost multiplier | C16: 1 | D16: 1.15 | E16: 1 | F16: =D16 -> 1.15 | G16: x | H16: Downside: 15% overrun
A17: A13 | B17: Current fixed operating cost / month | C17: 360000 | D17: =C17 -> 360000 | E17: =C17 -> 360000 | F17: =D17 -> 360000 | G17: ₹ | H17: Ex.1
A18: A14 | B18: Central trust & quality lead (from month below) | C18: 40000 | D18: =C18 -> 40000 | E18: =C18 -> 40000 | F18: =D18 -> 40000 | G18: ₹/month | H18: Team assumption: 1 hire runs SLA, custody, disputes
A19: A15 | B19: Month central hire starts | C19: 2 | D19: =C19 -> 2 | E19: =C19 -> 2 | F19: =D19 -> 2 | G19: month | H19: Team assumption
A20: A16 | B20: Fixed cost per new city (city partner manager + local ops) | C20: 50000 | D20: =C20 -> 50000 | E20: =C20 -> 50000 | F20: =D20 -> 50000 | G20: ₹/month | H20: Team assumption; added the month before first host goes live
A21: A17 | B21: City 2 (Cluster A) cost starts | C21: 2 | D21: =C21 -> 2 | E21: =C21 -> 2 | F21: =D21 -> 2 | G21: month | H21: Plan
A22: A18 | B22: City 3 (Cluster C) cost starts | C22: 5 | D22: =C22 -> 5 | E22: =C22 -> 5 | F22: =D22 -> 5 | G22: month | H22: Plan
A23: A19 | B23: City 4 (Cluster B) cost starts | C23: 8 | D23: =C23 -> 8 | E23: =C23 -> 8 | F23: =D23 -> 8 | G23: month | H23: Plan
A24: A20 | B24: Assured variable cost after learning | C24: 1200 | D24: =C24 -> 1200 | E24: =C24 -> 1200 | F24: =D24 -> 1200 | G24: ₹/booking | H24: Team assumption: batching, custody kits, scheduling tool cut ₹1,350 by 11%
A25: A21 | B25: Month learning applies from | C25: 10 | D25: =C25 -> 10 | E25: =C25 -> 10 | F25: =D25 -> 10 | G25: month | H25: Team assumption
A26: A22 | B26: Priority SLA: share of Assured bookings | C26: 0.15 | D26: =C26 -> 0.15 | E26: =C26 -> 0.15 | F26: =D26 -> 0.15 | G26: % | H26: Team assumption; 31% of customers cite turnaround (Ex.1)
A27: A23 | B27: Priority SLA: price uplift | C27: 0.5 | D27: =C27 -> 0.5 | E27: =C27 -> 0.5 | F27: =D27 -> 0.5 | G27: % | H27: Evidence: Auriga Research (NABL lab, India) charges a 50% surcharge for express testing [S9]
A28: A24 | B28: Priority SLA: share of uplift OpenBench keeps | C28: 0.5 | D28: =C28 -> 0.5 | E28: =C28 -> 0.5 | F28: =D28 -> 0.5 | G28: % | H28: Other 50% paid to lab/technician pool (host incentive)
... A38: A34 | B38: Onboarding funnel: contact → meeting | C38: 0.3 | D38: =C38 -> 0.3 | E38: =C38 -> 0.3 | F38: =D38 -> 0.3 | G38: % | H38: Team assumption
A39: A35 | B39: Skip Cluster B Verified labs (1 = yes) | C39: 0 | D39: =C39 -> 0 | E39: =C39 -> 0 | F39: 1 | G39: flag | H39: Slide 11 response to "demand below plan" trigger at M9
A40: A36 | B40: City-4 (Cluster B) cost removed from month | C40: 99 | D40: =C40 -> 99 | E40: =C40 -> 99 | F40: 9 | G40: month | H40: Slide 11 response: cut City-4 cost at M9 (99 = never)
A42: Operating tiers (Exhibit 3)
A43: Tier | B43: Take rate | C43: Lab subscription ₹/month | D43: Variable cost ₹/booking | E43: Onboarding ₹/host | F43: On-time target | G43: Exhibit 3 model
A44: Assured | B44: 0.28 | C44: 0 | D44: 1350 | E44: 120000 | F44: 0.94 | G44: B. Managed fulfilment
A45: Connect | B45: 0.08 | C45: 12000 | D45: 400 | E45: 70000 | F45: 0.86 | G45: C. Lab SaaS + booking fee
A46: Verified | B46: 0.18 | C46: 0 | D46: 600 | E46: 45000 | F46: 0.82 | G46: A. Marketplace
A48: Clusters (Exhibit 1 & 2)
A49: Cluster | B49: Potential hosts | C49: Avg booking value ₹ | D49: Mature bookings/host/month | E49: Key issue
A50: Pilot | B50: 4 | C50: 8500 | D50: 20 | E50: Reliability; repeat
A51: A | B51: 5 | C51: 12000 | D51: 24 | E51: IP protection; custom protocols
A52: B | B52: 7 | C52: 6500 | D52: 30 | E52: Price sensitivity; predictable turnaround
A53: C | B53: 4 | C53: 8000 | D53: 26 | E53: Seasonal demand; small batches
A55: Host onboarding plan (planned go-live month, before any delay)
A56: Host # | B56: Cluster | C56: Tier | D56: Avg booking value ₹ | E56: Mature bookings/month | F56: Planned go-live month | G56: Pilot host?
A57: 1 | B57: Pilot | C57: Assured | D57: =INDEX($C$50:$C$53,MATCH(B57,$A$50:$A$53,0)) -> 8500 | E57: =INDEX($D$50:$D$53,MATCH(B57,$A$50:$A$53,0)) -> 20 | F57: 1 | G57: =IF(B57="Pilot",1,0) -> 1
A58: 2 | B58: Pilot | C58: Assured | D58: =INDEX($C$50:$C$53,MATCH(B58,$A$50:$A$53,0)) -> 8500 | E58: =INDEX($D$50:$D$53,MATCH(B58,$A$50:$A$53,0)) -> 20 | F58: 1 | G58: =IF(B58="Pilot",1,0) -> 1
A59: 3 | B59: Pilot | C59: Assured | D59: =INDEX($C$50:$C$53,MATCH(B59,$A$50:$A$53,0)) -> 8500 | E59: =INDEX($D$50:$D$53,MATCH(B59,$A$50:$A$53,0)) -> 20 | F59: 1 | G59: =IF(B59="Pilot",1,0) -> 1
A60: 4 | B60: Pilot | C60: Assured | D60: =INDEX($C$50:$C$53,MATCH(B60,$A$50:$A$53,0)) -> 8500 | E60: =INDEX($D$50:$D$53,MATCH(B60,$A$50:$A$53,0)) -> 20 | F60: 1 | G60: =IF(B60="Pilot",1,0) -> 1
A61: 5 | B61: A | C61: Assured | D61: =INDEX($C$50:$C$53,MATCH(B61,$A$50:$A$53,0)) -> 12000 | E61: =INDEX($D$50:$D$53,MATCH(B61,$A$50:$A$53,0)) -> 24 | F61: 3 | G61: =IF(B61="Pilot",1,0) -> 0
A62: 6 | B62: A | C62: Assured | D62: =INDEX($C$50:$C$53,MATCH(B62,$A$50:$A$53,0)) -> 12000 | E62: =INDEX($D$50:$D$53,MATCH(B62,$A$50:$A$53,0)) -> 24 | F62: 3 | G62: =IF(B62="Pilot",1,0) -> 0
A63: 7 | B63: A | C63: Assured | D63: =INDEX($C$50:$C$53,MATCH(B63,$A$50:$A$53,0)) -> 12000 | E63: =INDEX($D$50:$D$53,MATCH(B63,$A$50:$A$53,0)) -> 24 | F63: 4 | G63: =IF(B63="Pilot",1,0) -> 0
A64: 8 | B64: A | C64: Assured | D64: =INDEX($C$50:$C$53,MATCH(B64,$A$50:$A$53,0)) -> 12000 | E64: =INDEX($D$50:$D$53,MATCH(B64,$A$50:$A$53,0)) -> 24 | F64: 4 | G64: =IF(B64="Pilot",1,0) -> 0
A65: 9 | B65: A | C65: Assured | D65: =INDEX($C$50:$C$53,MATCH(B65,$A$50:$A$53,0)) -> 12000 | E65: =INDEX($D$50:$D$53,MATCH(B65,$A$50:$A$53,0)) -> 24 | F65: 5 | G65: =IF(B65="Pilot",1,0) -> 0
A66: 10 | B66: C | C66: Assured | D66: =INDEX($C$50:$C$53,MATCH(B66,$A$50:$A$53,0)) -> 8000 | E66: =INDEX($D$50:$D$53,MATCH(B66,$A$50:$A$53,0)) -> 26 | F66: 6 | G66: =IF(B66="Pilot",1,0) -> 0
A67: 11 | B67: C | C67: Assured | D67: =INDEX($C$50:$C$53,MATCH(B67,$A$50:$A$53,0)) -> 8000 | E67: =INDEX($D$50:$D$53,MATCH(B67,$A$50:$A$53,0)) -> 26 | F67: 7 | G67: =IF(B67="Pilot",1,0) -> 0
A68: 12 | B68: C | C68: Assured | D68: =INDEX($C$50:$C$53,MATCH(B68,$A$50:$A$53,0)) -> 8000 | E68: =INDEX($D$50:$D$53,MATCH(B68,$A$50:$A$53,0)) -> 26 | F68: 7 | G68: =IF(B68="Pilot",1,0) -> 0
... A76: 20 | B76: B | C76: Verified | D76: =INDEX($C$50:$C$53,MATCH(B76,$A$50:$A$53,0)) -> 6500 | E76: =INDEX($D$50:$D$53,MATCH(B76,$A$50:$A$53,0)) -> 30 | F76: 14 | G76: =IF(B76="Pilot",1,0) -> 0

Sheet Unit Economics
A1: Unit economics by operating model (Exhibit 3) and cluster (Exhibit 2)
A3: Baseline booking value ₹ | C3: 8500 | D3: Ex.3 comparison baseline
A4: Baseline bookings/host/month | C4: 20 | D4: Ex.3 comparison baseline
A6: Model (tier) | B6: Revenue/booking ₹ | C6: Variable cost ₹ | D6: Contribution/booking ₹ | E6: Subscription ₹/host/month | F6: Contribution/host/month ₹ | G6: Onboarding ₹/host | H6: Payback (months)
A7: B. Managed fulfilment (Assured) | B7: =$C$3*Assumptions!B44 -> 2380 | C7: =Assumptions!D44 -> 1350 | D7: =B7-C7 -> 1030 | E7: =Assumptions!C44 -> 0 | F7: =D7*$C$4+E7 -> 20600 | G7: =Assumptions!E44 -> 120000 | H7: =G7/F7 -> 5.8252427
A8: C. Lab SaaS + booking fee (Connect) | B8: =$C$3*Assumptions!B45 -> 680 | C8: =Assumptions!D45 -> 400 | D8: =B8-C8 -> 280 | E8: =Assumptions!C45 -> 12000 | F8: =D8*$C$4+E8 -> 17600 | G8: =Assumptions!E45 -> 70000 | H8: =G8/F8 -> 3.9772727
A9: A. Marketplace (Verified) | B9: =$C$3*Assumptions!B46 -> 1530 | C9: =Assumptions!D46 -> 600 | D9: =B9-C9 -> 930 | E9: =Assumptions!C46 -> 0 | F9: =D9*$C$4+E9 -> 18600 | G9: =Assumptions!E46 -> 45000 | H9: =G9/F9 -> 2.4193548
A11: Pilot today (Marketplace, 18%)
A12: Revenue per booking ₹ | B12: =Assumptions!C50*Assumptions!B46 -> 1530
A13: Contribution per booking ₹ | B13: =B12-Assumptions!D46 -> 930
A14: Bookings per month | B14: =70 -> 70 | C14: Ex.1: 420 bookings / 6 months
A15: Monthly contribution ₹ | B15: =B13*B14 -> 65100
A16: Fixed cost ₹ | B16: =Assumptions!C17 -> 360000
A17: Monthly operating loss ₹ | B17: =B15-B16 -> -294900
A18: Break-even bookings/month at today's fixed cost | B18: =B16/B13 -> 387.09677
A19: Multiple of today's volume | B19: =B18/B14 -> 5.5299539
A22: Cluster × tier (contribution per host per month at mature Exhibit 2 volume, ₹) | B22: Booking value | C22: Bookings/host | D22: Verified (18%) | E22: Assured (28%) | F22: Connect (₹12k + 8%) | G22: Best tier
A23: Cluster A | B23: =Assumptions!C51 -> 12000 | C23: =Assumptions!D51 -> 24 | D23: =C23*(B23*Assumptions!B46-Assumptions!D46) -> 37440 | E23: =C23*(B23*Assumptions!B44-Assumptions!D44) -> 48240 | F23: =C23*(B23*Assumptions!B45-Assumptions!D45)+Assumptions!C45 -> 25440 | G23: =INDEX($D$22:$F$22,MATCH(MAX(D23:F23),D23:F23,0)) -> Assured (28%)
A24: Cluster B | B24: =Assumptions!C52 -> 6500 | C24: =Assumptions!D52 -> 30 | D24: =C24*(B24*Assumptions!B46-Assumptions!D46) -> 17100 | E24: =C24*(B24*Assumptions!B44-Assumptions!D44) -> 14100 | F24: =C24*(B24*Assumptions!B45-Assumptions!D45)+Assumptions!C45 -> 15600 | G24: =INDEX($D$22:$F$22,MATCH(MAX(D24:F24),D24:F24,0)) -> Verified (18%)
A25: Cluster C | B25: =Assumptions!C53 -> 8000 | C25: =Assumptions!D53 -> 26 | D25: =C25*(B25*Assumptions!B46-Assumptions!D46) -> 21840 | E25: =C25*(B25*Assumptions!B44-Assumptions!D44) -> 23140 | F25: =C25*(B25*Assumptions!B45-Assumptions!D45)+Assumptions!C45 -> 18240 | G25: =INDEX($D$22:$F$22,MATCH(MAX(D25:F25),D25:F25,0)) -> Assured (28%)
A27: Reading: Assured wins where booking value and IP sensitivity are high (A, C). In price-sensitive B, Connect charges customers 8% instead of 28% and still earns a subscription floor.
A29: Cluster B break-even point: Connect beats Verified below this many bookings/host/month | B29: =Assumptions!C45/((B24*Assumptions!B46-Assumptions!D46)-(B24*Assumptions!B45-Assumptions!D45)) -> 26.666667 | C29: =B29/C24 -> 0.88888889 | D29: of Exhibit 2 volume → Connect is the safer default for B; labs that refuse a subscription (6 of 10, Ex.3) go on Verified
A31: Why labs join: pilot lab revenue per host per month
A32: Today: marketplace, 17.5 bookings × ₹8,500 × (1 − 18%) | B32: =Assumptions!C10*Assumptions!C50*(1-Assumptions!B46) -> 121975
A33: Assured: 20 bookings × ₹8,500 × (1 − 28% + Priority share to lab) | B33: =Assumptions!C11*Assumptions!C50*(1-Assumptions!B44+Assumptions!C26*Assumptions!C27*(1-Assumptions!C28)) -> 128775
A34: Change for the lab (and OpenBench now does the admin) | B34: =B33/B32-1 -> 0.055749129

Sheet Monthly_Base
A1: Monthly engine — Base scenario (M1–M18)
A2: All values flow from the Assumptions tab. Green = linked input.
A4: ID | B4: Parameter | C4: Value
A5: A1 | B5: =Assumptions!B5 -> Capture of Exhibit 2 mature volume | C5: =Assumptions!C5 -> 0.85
A6: A2 | B6: =Assumptions!B6 -> Ramp: share of mature volume, live month 1 | C6: =Assumptions!C6 -> 0.3
A7: A3 | B7: =Assumptions!B7 -> Ramp: live month 2 | C7: =Assumptions!C7 -> 0.6
A8: A4 | B8: =Assumptions!B8 -> Ramp: live month 3 | C8: =Assumptions!C8 -> 0.85
A9: A5 | B9: =Assumptions!B9 -> Ramp: live month 4+ | C9: =Assumptions!C9 -> 1
A10: A6 | B10: =Assumptions!B10 -> Pilot host bookings/month today | C10: =Assumptions!C10 -> 17.5
A11: A7 | B11: =Assumptions!B11 -> Pilot host bookings/month after Assured conversion | C11: =Assumptions!C11 -> 20
A12: A8 | B12: =Assumptions!B12 -> Months for pilot hosts to reach target | C12: =Assumptions!C12 -> 3
A13: A9 | B13: =Assumptions!B13 -> Average booking value multiplier | C13: =Assumptions!C13 -> 1
A14: A10 | B14: =Assumptions!B14 -> Bookings lost to cancellation (beyond tier on-time) | C14: =Assumptions!C14 -> 0
A15: A11 | B15: =Assumptions!B15 -> Onboarding delay for new hosts | C15: =Assumptions!C15 -> 0
A16: A12 | B16: =Assumptions!B16 -> Fixed cost multiplier | C16: =Assumptions!C16 -> 1
... A40: A36 | B40: =Assumptions!B40 -> City-4 (Cluster B) cost removed from month | C40: =Assumptions!C40 -> 99
A45: Month → | H45: 1 | I45: 2 | J45: 3 | K45: 4 | L45: 5 | M45: 6 | N45: 7 | O45: 8 | P45: 9 | Q45: 10 | R45: 11 | S45: 12 | T45: 13 | U45: 14 | V45: 15 | W45: 16 | X45: 17 | Y45: 18
A47: Bookings per host | B47: Cluster | C47: Tier | D47: Booking value ₹ | E47: Mature/month | F47: Pilot? | G47: Live from month
A48: =Assumptions!A57 -> 1 | B48: =Assumptions!B57 -> Pilot | C48: =Assumptions!C57 -> Assured | D48: =Assumptions!D57 -> 8500 | E48: =Assumptions!E57 -> 20 | F48: =Assumptions!G57 -> 1 | G48: =Assumptions!F57+IF(F48=1,0,$C$15) -> 1 | H48: =IF(H$45<$G48,0,IF($F48=1,$C$10+($C$11-$C$10)*MIN(H$45-$G48,$C$12)/$C$12,$E48*$C$5*INDEX($C$6:$C$9,MIN(H$45-$G48,3)+1)))*(1-$C$14)*IF(AND($C48="Verified",$C$39=1),0,1) -> 17.5 | I48: =IF(I$45<$G48,0,IF($F48=1,$C$10+($C$11-$C$10)*MIN(I$45-$G48,$C$12)/$C$12,$E48*$C$5*INDEX($C$6:$C$9,MIN(I$45-$G48,3)+1)))*(1-$C$14)*IF(AND($C48="Verified",$C$39=1),0,1) -> 18.333333 | J48: =IF(J$45<$G48,0,IF($F48=1,$C$10+($C$11-$C$10)*MIN(J$45-$G48,$C$12)/$C$12,$E48*$C$5*INDEX($C$6:$C$9,MIN(J$45-$G48,3)+1)))*(1-$C$14)*IF(AND($C48="Verified",$C$39=1),0,1) -> 19.166667 | K48: =IF(K$45<$G48,0,IF($F48=1,$C$10+($C$11-$C$10)*MIN(K$45-$G48,$C$12)/$C$12,$E48*$C$5*INDEX($C$6:$C$9,MIN(K$45-$G48,3)+1)))*(1-$C$14)*IF(AND($C48="Verified",$C$39=1),0,1) -> 20 | L48: =IF(L$45<$G48,0,IF($F48=1,$C$10+($C$11-$C$10)*MIN(L$45-$G48,$C$12)/$C$12,$E48*$C$5*INDEX($C$6:$C$9,MIN(L$45-$G48,3)+1)))*(1-$C$14)*IF(AND($C48="Verified",$C$39=1),0,1) -> 20 | M48: =IF(M$45<$G48,0,IF($F48=1,$C$10+($C$11-$C$10)*MIN(M$45-$G48,$C$12)/$C$12,$E48*$C$5*INDEX($C$6:$C$9,MIN(M$45-$G48,3)+1)))*(1-$C$14)*IF(AND($C48="Verified",$C$39=1),0,1) -> 20 | N48: =IF(N$45<$G48,0,IF($F48=1,$C$10+($C$11-$C$10)*MIN(N$45-$G48,$C$12)/$C$12,$E48*$C$5*INDEX($C$6:$C$9,MIN(N$45-$G48,3)+1)))*(1-$C$14)*IF(AND($C48="Verified",$C$39=1),0,1) -> 20 | O48: =IF(O$45<$G48,0,IF($F48=1,$C$10+($C$11-$C$10)*MIN(O$45-$G48,$C$12)/$C$12,$E48*$C$5*INDEX($C$6:$C$9,MIN(O$45-$G48,3)+1)))*(1-$C$14)*IF(AND($C48="Verified",$C$39=1),0,1) -> 20 | ... Y48: =IF(Y$45<$G48,0,IF($F48=1,$C$10+($C$11-$C$10)*MIN(Y$45-$G48,$C$12)/$C$12,$E48*$C$5*INDEX($C$6:$C$9,MIN(Y$45-$G48,3)+1)))*(1-$C$14)*IF(AND($C48="Verified",$C$39=1),0,1) -> 20
A49: =Assumptions!A58 -> 2 | B49: =Assumptions!B58 -> Pilot | C49: =Assumptions!C58 -> Assured | D49: =Assumptions!D58 -> 8500 | E49: =Assumptions!E58 -> 20 | F49: =Assumptions!G58 -> 1 | G49: =Assumptions!F58+IF(F49=1,0,$C$15) -> 1 | H49: =IF(H$45<$G49,0,IF($F49=1,$C$10+($C$11-$C$10)*MIN(H$45-$G49,$C$12)/$C$12,$E49*$C$5*INDEX($C$6:$C$9,MIN(H$45-$G49,3)+1)))*(1-$C$14)*IF(AND($C49="Verified",$C$39=1),0,1) -> 17.5 | I49: =IF(I$45<$G49,0,IF($F49=1,$C$10+($C$11-$C$10)*MIN(I$45-$G49,$C$12)/$C$12,$E49*$C$5*INDEX($C$6:$C$9,MIN(I$45-$G49,3)+1)))*(1-$C$14)*IF(AND($C49="Verified",$C$39=1),0,1) -> 18.333333 | J49: =IF(J$45<$G49,0,IF($F49=1,$C$10+($C$11-$C$10)*MIN(J$45-$G49,$C$12)/$C$12,$E49*$C$5*INDEX($C$6:$C$9,MIN(J$45-$G49,3)+1)))*(1-$C$14)*IF(AND($C49="Verified",$C$39=1),0,1) -> 19.166667 | K49: =IF(K$45<$G49,0,IF($F49=1,$C$10+($C$11-$C$10)*MIN(K$45-$G49,$C$12)/$C$12,$E49*$C$5*INDEX($C$6:$C$9,MIN(K$45-$G49,3)+1)))*(1-$C$14)*IF(AND($C49="Verified",$C$39=1),0,1) -> 20 | L49: =IF(L$45<$G49,0,IF($F49=1,$C$10+($C$11-$C$10)*MIN(L$45-$G49,$C$12)/$C$12,$E49*$C$5*INDEX($C$6:$C$9,MIN(L$45-$G49,3)+1)))*(1-$C$14)*IF(AND($C49="Verified",$C$39=1),0,1) -> 20 | M49: =IF(M$45<$G49,0,IF($F49=1,$C$10+($C$11-$C$10)*MIN(M$45-$G49,$C$12)/$C$12,$E49*$C$5*INDEX($C$6:$C$9,MIN(M$45-$G49,3)+1)))*(1-$C$14)*IF(AND($C49="Verified",$C$39=1),0,1) -> 20 | N49: =IF(N$45<$G49,0,IF($F49=1,$C$10+($C$11-$C$10)*MIN(N$45-$G49,$C$12)/$C$12,$E49*$C$5*INDEX($C$6:$C$9,MIN(N$45-$G49,3)+1)))*(1-$C$14)*IF(AND($C49="Verified",$C$39=1),0,1) -> 20 | O49: =IF(O$45<$G49,0,IF($F49=1,$C$10+($C$11-$C$10)*MIN(O$45-$G49,$C$12)/$C$12,$E49*$C$5*INDEX($C$6:$C$9,MIN(O$45-$G49,3)+1)))*(1-$C$14)*IF(AND($C49="Verified",$C$39=1),0,1) -> 20 | ... Y49: =IF(Y$45<$G49,0,IF($F49=1,$C$10+($C$11-$C$10)*MIN(Y$45-$G49,$C$12)/$C$12,$E49*$C$5*INDEX($C$6:$C$9,MIN(Y$45-$G49,3)+1)))*(1-$C$14)*IF(AND($C49="Verified",$C$39=1),0,1) -> 20
A50: =Assumptions!A59 -> 3 | B50: =Assumptions!B59 -> Pilot | C50: =Assumptions!C59 -> Assured | D50: =Assumptions!D59 -> 8500 | E50: =Assumptions!E59 -> 20 | F50: =Assumptions!G59 -> 1 | G50: =Assumptions!F59+IF(F50=1,0,$C$15) -> 1 | H50: =IF(H$45<$G50,0,IF($F50=1,$C$10+($C$11-$C$10)*MIN(H$45-$G50,$C$12)/$C$12,$E50*$C$5*INDEX($C$6:$C$9,MIN(H$45-$G50,3)+1)))*(1-$C$14)*IF(AND($C50="Verified",$C$39=1),0,1) -> 17.5 | I50: =IF(I$45<$G50,0,IF($F50=1,$C$10+($C$11-$C$10)*MIN(I$45-$G50,$C$12)/$C$12,$E50*$C$5*INDEX($C$6:$C$9,MIN(I$45-$G50,3)+1)))*(1-$C$14)*IF(AND($C50="Verified",$C$39=1),0,1) -> 18.333333 | J50: =IF(J$45<$G50,0,IF($F50=1,$C$10+($C$11-$C$10)*MIN(J$45-$G50,$C$12)/$C$12,$E50*$C$5*INDEX($C$6:$C$9,MIN(J$45-$G50,3)+1)))*(1-$C$14)*IF(AND($C50="Verified",$C$39=1),0,1) -> 19.166667 | K50: =IF(K$45<$G50,0,IF($F50=1,$C$10+($C$11-$C$10)*MIN(K$45-$G50,$C$12)/$C$12,$E50*$C$5*INDEX($C$6:$C$9,MIN(K$45-$G50,3)+1)))*(1-$C$14)*IF(AND($C50="Verified",$C$39=1),0,1) -> 20 | L50: =IF(L$45<$G50,0,IF($F50=1,$C$10+($C$11-$C$10)*MIN(L$45-$G50,$C$12)/$C$12,$E50*$C$5*INDEX($C$6:$C$9,MIN(L$45-$G50,3)+1)))*(1-$C$14)*IF(AND($C50="Verified",$C$39=1),0,1) -> 20 | M50: =IF(M$45<$G50,0,IF($F50=1,$C$10+($C$11-$C$10)*MIN(M$45-$G50,$C$12)/$C$12,$E50*$C$5*INDEX($C$6:$C$9,MIN(M$45-$G50,3)+1)))*(1-$C$14)*IF(AND($C50="Verified",$C$39=1),0,1) -> 20 | N50: =IF(N$45<$G50,0,IF($F50=1,$C$10+($C$11-$C$10)*MIN(N$45-$G50,$C$12)/$C$12,$E50*$C$5*INDEX($C$6:$C$9,MIN(N$45-$G50,3)+1)))*(1-$C$14)*IF(AND($C50="Verified",$C$39=1),0,1) -> 20 | O50: =IF(O$45<$G50,0,IF($F50=1,$C$10+($C$11-$C$10)*MIN(O$45-$G50,$C$12)/$C$12,$E50*$C$5*INDEX($C$6:$C$9,MIN(O$45-$G50,3)+1)))*(1-$C$14)*IF(AND($C50="Verified",$C$39=1),0,1) -> 20 | ... Y50: =IF(Y$45<$G50,0,IF($F50=1,$C$10+($C$11-$C$10)*MIN(Y$45-$G50,$C$12)/$C$12,$E50*$C$5*INDEX($C$6:$C$9,MIN(Y$45-$G50,3)+1)))*(1-$C$14)*IF(AND($C50="Verified",$C$39=1),0,1) -> 20
A51: =Assumptions!A60 -> 4 | B51: =Assumptions!B60 -> Pilot | C51: =Assumptions!C60 -> Assured | D51: =Assumptions!D60 -> 8500 | E51: =Assumptions!E60 -> 20 | F51: =Assumptions!G60 -> 1 | G51: =Assumptions!F60+IF(F51=1,0,$C$15) -> 1 | H51: =IF(H$45<$G51,0,IF($F51=1,$C$10+($C$11-$C$10)*MIN(H$45-$G51,$C$12)/$C$12,$E51*$C$5*INDEX($C$6:$C$9,MIN(H$45-$G51,3)+1)))*(1-$C$14)*IF(AND($C51="Verified",$C$39=1),0,1) -> 17.5 | I51: =IF(I$45<$G51,0,IF($F51=1,$C$10+($C$11-$C$10)*MIN(I$45-$G51,$C$12)/$C$12,$E51*$C$5*INDEX($C$6:$C$9,MIN(I$45-$G51,3)+1)))*(1-$C$14)*IF(AND($C51="Verified",$C$39=1),0,1) -> 18.333333 | J51: =IF(J$45<$G51,0,IF($F51=1,$C$10+($C$11-$C$10)*MIN(J$45-$G51,$C$12)/$C$12,$E51*$C$5*INDEX($C$6:$C$9,MIN(J$45-$G51,3)+1)))*(1-$C$14)*IF(AND($C51="Verified",$C$39=1),0,1) -> 19.166667 | K51: =IF(K$45<$G51,0,IF($F51=1,$C$10+($C$11-$C$10)*MIN(K$45-$G51,$C$12)/$C$12,$E51*$C$5*INDEX($C$6:$C$9,MIN(K$45-$G51,3)+1)))*(1-$C$14)*IF(AND($C51="Verified",$C$39=1),0,1) -> 20 | L51: =IF(L$45<$G51,0,IF($F51=1,$C$10+($C$11-$C$10)*MIN(L$45-$G51,$C$12)/$C$12,$E51*$C$5*INDEX($C$6:$C$9,MIN(L$45-$G51,3)+1)))*(1-$C$14)*IF(AND($C51="Verified",$C$39=1),0,1) -> 20 | M51: =IF(M$45<$G51,0,IF($F51=1,$C$10+($C$11-$C$10)*MIN(M$45-$G51,$C$12)/$C$12,$E51*$C$5*INDEX($C$6:$C$9,MIN(M$45-$G51,3)+1)))*(1-$C$14)*IF(AND($C51="Verified",$C$39=1),0,1) -> 20 | N51: =IF(N$45<$G51,0,IF($F51=1,$C$10+($C$11-$C$10)*MIN(N$45-$G51,$C$12)/$C$12,$E51*$C$5*INDEX($C$6:$C$9,MIN(N$45-$G51,3)+1)))*(1-$C$14)*IF(AND($C51="Verified",$C$39=1),0,1) -> 20 | O51: =IF(O$45<$G51,0,IF($F51=1,$C$10+($C$11-$C$10)*MIN(O$45-$G51,$C$12)/$C$12,$E51*$C$5*INDEX($C$6:$C$9,MIN(O$45-$G51,3)+1)))*(1-$C$14)*IF(AND($C51="Verified",$C$39=1),0,1) -> 20 | ... Y51: =IF(Y$45<$G51,0,IF($F51=1,$C$10+($C$11-$C$10)*MIN(Y$45-$G51,$C$12)/$C$12,$E51*$C$5*INDEX($C$6:$C$9,MIN(Y$45-$G51,3)+1)))*(1-$C$14)*IF(AND($C51="Verified",$C$39=1),0,1) -> 20
A52: =Assumptions!A61 -> 5 | B52: =Assumptions!B61 -> A | C52: =Assumptions!C61 -> Assured | D52: =Assumptions!D61 -> 12000 | E52: =Assumptions!E61 -> 24 | F52: =Assumptions!G61 -> 0 | G52: =Assumptions!F61+IF(F52=1,0,$C$15) -> 3 | H52: =IF(H$45<$G52,0,IF($F52=1,$C$10+($C$11-$C$10)*MIN(H$45-$G52,$C$12)/$C$12,$E52*$C$5*INDEX($C$6:$C$9,MIN(H$45-$G52,3)+1)))*(1-$C$14)*IF(AND($C52="Verified",$C$39=1),0,1) -> 0 | I52: =IF(I$45<$G52,0,IF($F52=1,$C$10+($C$11-$C$10)*MIN(I$45-$G52,$C$12)/$C$12,$E52*$C$5*INDEX($C$6:$C$9,MIN(I$45-$G52,3)+1)))*(1-$C$14)*IF(AND($C52="Verified",$C$39=1),0,1) -> 0 | J52: =IF(J$45<$G52,0,IF($F52=1,$C$10+($C$11-$C$10)*MIN(J$45-$G52,$C$12)/$C$12,$E52*$C$5*INDEX($C$6:$C$9,MIN(J$45-$G52,3)+1)))*(1-$C$14)*IF(AND($C52="Verified",$C$39=1),0,1) -> 6.12 | K52: =IF(K$45<$G52,0,IF($F52=1,$C$10+($C$11-$C$10)*MIN(K$45-$G52,$C$12)/$C$12,$E52*$C$5*INDEX($C$6:$C$9,MIN(K$45-$G52,3)+1)))*(1-$C$14)*IF(AND($C52="Verified",$C$39=1),0,1) -> 12.24 | L52: =IF(L$45<$G52,0,IF($F52=1,$C$10+($C$11-$C$10)*MIN(L$45-$G52,$C$12)/$C$12,$E52*$C$5*INDEX($C$6:$C$9,MIN(L$45-$G52,3)+1)))*(1-$C$14)*IF(AND($C52="Verified",$C$39=1),0,1) -> 17.34 | M52: =IF(M$45<$G52,0,IF($F52=1,$C$10+($C$11-$C$10)*MIN(M$45-$G52,$C$12)/$C$12,$E52*$C$5*INDEX($C$6:$C$9,MIN(M$45-$G52,3)+1)))*(1-$C$14)*IF(AND($C52="Verified",$C$39=1),0,1) -> 20.4 | N52: =IF(N$45<$G52,0,IF($F52=1,$C$10+($C$11-$C$10)*MIN(N$45-$G52,$C$12)/$C$12,$E52*$C$5*INDEX($C$6:$C$9,MIN(N$45-$G52,3)+1)))*(1-$C$14)*IF(AND($C52="Verified",$C$39=1),0,1) -> 20.4 | O52: =IF(O$45<$G52,0,IF($F52=1,$C$10+($C$11-$C$10)*MIN(O$45-$G52,$C$12)/$C$12,$E52*$C$5*INDEX($C$6:$C$9,MIN(O$45-$G52,3)+1)))*(1-$C$14)*IF(AND($C52="Verified",$C$39=1),0,1) -> 20.4 | ... Y52: =IF(Y$45<$G52,0,IF($F52=1,$C$10+($C$11-$C$10)*MIN(Y$45-$G52,$C$12)/$C$12,$E52*$C$5*INDEX($C$6:$C$9,MIN(Y$45-$G52,3)+1)))*(1-$C$14)*IF(AND($C52="Verified",$C$39=1),0,1) -> 20.4
A53: =Assumptions!A62 -> 6 | B53: =Assumptions!B62 -> A | C53: =Assumptions!C62 -> Assured | D53: =Assumptions!D62 -> 12000 | E53: =Assumptions!E62 -> 24 | F53: =Assumptions!G62 -> 0 | G53: =Assumptions!F62+IF(F53=1,0,$C$15) -> 3 | H53: =IF(H$45<$G53,0,IF($F53=1,$C$10+($C$11-$C$10)*MIN(H$45-$G53,$C$12)/$C$12,$E53*$C$5*INDEX($C$6:$C$9,MIN(H$45-$G53,3)+1)))*(1-$C$14)*IF(AND($C53="Verified",$C$39=1),0,1) -> 0 | I53: =IF(I$45<$G53,0,IF($F53=1,$C$10+($C$11-$C$10)*MIN(I$45-$G53,$C$12)/$C$12,$E53*$C$5*INDEX($C$6:$C$9,MIN(I$45-$G53,3)+1)))*(1-$C$14)*IF(AND($C53="Verified",$C$39=1),0,1) -> 0 | J53: =IF(J$45<$G53,0,IF($F53=1,$C$10+($C$11-$C$10)*MIN(J$45-$G53,$C$12)/$C$12,$E53*$C$5*INDEX($C$6:$C$9,MIN(J$45-$G53,3)+1)))*(1-$C$14)*IF(AND($C53="Verified",$C$39=1),0,1) -> 6.12 | K53: =IF(K$45<$G53,0,IF($F53=1,$C$10+($C$11-$C$10)*MIN(K$45-$G53,$C$12)/$C$12,$E53*$C$5*INDEX($C$6:$C$9,MIN(K$45-$G53,3)+1)))*(1-$C$14)*IF(AND($C53="Verified",$C$39=1),0,1) -> 12.24 | L53: =IF(L$45<$G53,0,IF($F53=1,$C$10+($C$11-$C$10)*MIN(L$45-$G53,$C$12)/$C$12,$E53*$C$5*INDEX($C$6:$C$9,MIN(L$45-$G53,3)+1)))*(1-$C$14)*IF(AND($C53="Verified",$C$39=1),0,1) -> 17.34 | M53: =IF(M$45<$G53,0,IF($F53=1,$C$10+($C$11-$C$10)*MIN(M$45-$G53,$C$12)/$C$12,$E53*$C$5*INDEX($C$6:$C$9,MIN(M$45-$G53,3)+1)))*(1-$C$14)*IF(AND($C53="Verified",$C$39=1),0,1) -> 20.4 | N53: =IF(N$45<$G53,0,IF($F53=1,$C$10+($C$11-$C$10)*MIN(N$45-$G53,$C$12)/$C$12,$E53*$C$5*INDEX($C$6:$C$9,MIN(N$45-$G53,3)+1)))*(1-$C$14)*IF(AND($C53="Verified",$C$39=1),0,1) -> 20.4 | O53: =IF(O$45<$G53,0,IF($F53=1,$C$10+($C$11-$C$10)*MIN(O$45-$G53,$C$12)/$C$12,$E53*$C$5*INDEX($C$6:$C$9,MIN(O$45-$G53,3)+1)))*(1-$C$14)*IF(AND($C53="Verified",$C$39=1),0,1) -> 20.4 | ... Y53: =IF(Y$45<$G53,0,IF($F53=1,$C$10+($C$11-$C$10)*MIN(Y$45-$G53,$C$12)/$C$12,$E53*$C$5*INDEX($C$6:$C$9,MIN(Y$45-$G53,3)+1)))*(1-$C$14)*IF(AND($C53="Verified",$C$39=1),0,1) -> 20.4
A54: =Assumptions!A63 -> 7 | B54: =Assumptions!B63 -> A | C54: =Assumptions!C63 -> Assured | D54: =Assumptions!D63 -> 12000 | E54: =Assumptions!E63 -> 24 | F54: =Assumptions!G63 -> 0 | G54: =Assumptions!F63+IF(F54=1,0,$C$15) -> 4 | H54: =IF(H$45<$G54,0,IF($F54=1,$C$10+($C$11-$C$10)*MIN(H$45-$G54,$C$12)/$C$12,$E54*$C$5*INDEX($C$6:$C$9,MIN(H$45-$G54,3)+1)))*(1-$C$14)*IF(AND($C54="Verified",$C$39=1),0,1) -> 0 | I54: =IF(I$45<$G54,0,IF($F54=1,$C$10+($C$11-$C$10)*MIN(I$45-$G54,$C$12)/$C$12,$E54*$C$5*INDEX($C$6:$C$9,MIN(I$45-$G54,3)+1)))*(1-$C$14)*IF(AND($C54="Verified",$C$39=1),0,1) -> 0 | J54: =IF(J$45<$G54,0,IF($F54=1,$C$10+($C$11-$C$10)*MIN(J$45-$G54,$C$12)/$C$12,$E54*$C$5*INDEX($C$6:$C$9,MIN(J$45-$G54,3)+1)))*(1-$C$14)*IF(AND($C54="Verified",$C$39=1),0,1) -> 0 | K54: =IF(K$45<$G54,0,IF($F54=1,$C$10+($C$11-$C$10)*MIN(K$45-$G54,$C$12)/$C$12,$E54*$C$5*INDEX($C$6:$C$9,MIN(K$45-$G54,3)+1)))*(1-$C$14)*IF(AND($C54="Verified",$C$39=1),0,1) -> 6.12 | L54: =IF(L$45<$G54,0,IF($F54=1,$C$10+($C$11-$C$10)*MIN(L$45-$G54,$C$12)/$C$12,$E54*$C$5*INDEX($C$6:$C$9,MIN(L$45-$G54,3)+1)))*(1-$C$14)*IF(AND($C54="Verified",$C$39=1),0,1) -> 12.24 | M54: =IF(M$45<$G54,0,IF($F54=1,$C$10+($C$11-$C$10)*MIN(M$45-$G54,$C$12)/$C$12,$E54*$C$5*INDEX($C$6:$C$9,MIN(M$45-$G54,3)+1)))*(1-$C$14)*IF(AND($C54="Verified",$C$39=1),0,1) -> 17.34 | N54: =IF(N$45<$G54,0,IF($F54=1,$C$10+($C$11-$C$10)*MIN(N$45-$G54,$C$12)/$C$12,$E54*$C$5*INDEX($C$6:$C$9,MIN(N$45-$G54,3)+1)))*(1-$C$14)*IF(AND($C54="Verified",$C$39=1),0,1) -> 20.4 | O54: =IF(O$45<$G54,0,IF($F54=1,$C$10+($C$11-$C$10)*MIN(O$45-$G54,$C$12)/$C$12,$E54*$C$5*INDEX($C$6:$C$9,MIN(O$45-$G54,3)+1)))*(1-$C$14)*IF(AND($C54="Verified",$C$39=1),0,1) -> 20.4 | ... Y54: =IF(Y$45<$G54,0,IF($F54=1,$C$10+($C$11-$C$10)*MIN(Y$45-$G54,$C$12)/$C$12,$E54*$C$5*INDEX($C$6:$C$9,MIN(Y$45-$G54,3)+1)))*(1-$C$14)*IF(AND($C54="Verified",$C$39=1),0,1) -> 20.4
A55: =Assumptions!A64 -> 8 | B55: =Assumptions!B64 -> A | C55: =Assumptions!C64 -> Assured | D55: =Assumptions!D64 -> 12000 | E55: =Assumptions!E64 -> 24 | F55: =Assumptions!G64 -> 0 | G55: =Assumptions!F64+IF(F55=1,0,$C$15) -> 4 | H55: =IF(H$45<$G55,0,IF($F55=1,$C$10+($C$11-$C$10)*MIN(H$45-$G55,$C$12)/$C$12,$E55*$C$5*INDEX($C$6:$C$9,MIN(H$45-$G55,3)+1)))*(1-$C$14)*IF(AND($C55="Verified",$C$39=1),0,1) -> 0 | I55: =IF(I$45<$G55,0,IF($F55=1,$C$10+($C$11-$C$10)*MIN(I$45-$G55,$C$12)/$C$12,$E55*$C$5*INDEX($C$6:$C$9,MIN(I$45-$G55,3)+1)))*(1-$C$14)*IF(AND($C55="Verified",$C$39=1),0,1) -> 0 | J55: =IF(J$45<$G55,0,IF($F55=1,$C$10+($C$11-$C$10)*MIN(J$45-$G55,$C$12)/$C$12,$E55*$C$5*INDEX($C$6:$C$9,MIN(J$45-$G55,3)+1)))*(1-$C$14)*IF(AND($C55="Verified",$C$39=1),0,1) -> 0 | K55: =IF(K$45<$G55,0,IF($F55=1,$C$10+($C$11-$C$10)*MIN(K$45-$G55,$C$12)/$C$12,$E55*$C$5*INDEX($C$6:$C$9,MIN(K$45-$G55,3)+1)))*(1-$C$14)*IF(AND($C55="Verified",$C$39=1),0,1) -> 6.12 | L55: =IF(L$45<$G55,0,IF($F55=1,$C$10+($C$11-$C$10)*MIN(L$45-$G55,$C$12)/$C$12,$E55*$C$5*INDEX($C$6:$C$9,MIN(L$45-$G55,3)+1)))*(1-$C$14)*IF(AND($C55="Verified",$C$39=1),0,1) -> 12.24 | M55: =IF(M$45<$G55,0,IF($F55=1,$C$10+($C$11-$C$10)*MIN(M$45-$G55,$C$12)/$C$12,$E55*$C$5*INDEX($C$6:$C$9,MIN(M$45-$G55,3)+1)))*(1-$C$14)*IF(AND($C55="Verified",$C$39=1),0,1) -> 17.34 | N55: =IF(N$45<$G55,0,IF($F55=1,$C$10+($C$11-$C$10)*MIN(N$45-$G55,$C$12)/$C$12,$E55*$C$5*INDEX($C$6:$C$9,MIN(N$45-$G55,3)+1)))*(1-$C$14)*IF(AND($C55="Verified",$C$39=1),0,1) -> 20.4 | O55: =IF(O$45<$G55,0,IF($F55=1,$C$10+($C$11-$C$10)*MIN(O$45-$G55,$C$12)/$C$12,$E55*$C$5*INDEX($C$6:$C$9,MIN(O$45-$G55,3)+1)))*(1-$C$14)*IF(AND($C55="Verified",$C$39=1),0,1) -> 20.4 | ... Y55: =IF(Y$45<$G55,0,IF($F55=1,$C$10+($C$11-$C$10)*MIN(Y$45-$G55,$C$12)/$C$12,$E55*$C$5*INDEX($C$6:$C$9,MIN(Y$45-$G55,3)+1)))*(1-$C$14)*IF(AND($C55="Verified",$C$39=1),0,1) -> 20.4
A56: =Assumptions!A65 -> 9 | B56: =Assumptions!B65 -> A | C56: =Assumptions!C65 -> Assured | D56: =Assumptions!D65 -> 12000 | E56: =Assumptions!E65 -> 24 | F56: =Assumptions!G65 -> 0 | G56: =Assumptions!F65+IF(F56=1,0,$C$15) -> 5 | H56: =IF(H$45<$G56,0,IF($F56=1,$C$10+($C$11-$C$10)*MIN(H$45-$G56,$C$12)/$C$12,$E56*$C$5*INDEX($C$6:$C$9,MIN(H$45-$G56,3)+1)))*(1-$C$14)*IF(AND($C56="Verified",$C$39=1),0,1) -> 0 | I56: =IF(I$45<$G56,0,IF($F56=1,$C$10+($C$11-$C$10)*MIN(I$45-$G56,$C$12)/$C$12,$E56*$C$5*INDEX($C$6:$C$9,MIN(I$45-$G56,3)+1)))*(1-$C$14)*IF(AND($C56="Verified",$C$39=1),0,1) -> 0 | J56: =IF(J$45<$G56,0,IF($F56=1,$C$10+($C$11-$C$10)*MIN(J$45-$G56,$C$12)/$C$12,$E56*$C$5*INDEX($C$6:$C$9,MIN(J$45-$G56,3)+1)))*(1-$C$14)*IF(AND($C56="Verified",$C$39=1),0,1) -> 0 | K56: =IF(K$45<$G56,0,IF($F56=1,$C$10+($C$11-$C$10)*MIN(K$45-$G56,$C$12)/$C$12,$E56*$C$5*INDEX($C$6:$C$9,MIN(K$45-$G56,3)+1)))*(1-$C$14)*IF(AND($C56="Verified",$C$39=1),0,1) -> 0 | L56: =IF(L$45<$G56,0,IF($F56=1,$C$10+($C$11-$C$10)*MIN(L$45-$G56,$C$12)/$C$12,$E56*$C$5*INDEX($C$6:$C$9,MIN(L$45-$G56,3)+1)))*(1-$C$14)*IF(AND($C56="Verified",$C$39=1),0,1) -> 6.12 | M56: =IF(M$45<$G56,0,IF($F56=1,$C$10+($C$11-$C$10)*MIN(M$45-$G56,$C$12)/$C$12,$E56*$C$5*INDEX($C$6:$C$9,MIN(M$45-$G56,3)+1)))*(1-$C$14)*IF(AND($C56="Verified",$C$39=1),0,1) -> 12.24 | N56: =IF(N$45<$G56,0,IF($F56=1,$C$10+($C$11-$C$10)*MIN(N$45-$G56,$C$12)/$C$12,$E56*$C$5*INDEX($C$6:$C$9,MIN(N$45-$G56,3)+1)))*(1-$C$14)*IF(AND($C56="Verified",$C$39=1),0,1) -> 17.34 | O56: =IF(O$45<$G56,0,IF($F56=1,$C$10+($C$11-$C$10)*MIN(O$45-$G56,$C$12)/$C$12,$E56*$C$5*INDEX($C$6:$C$9,MIN(O$45-$G56,3)+1)))*(1-$C$14)*IF(AND($C56="Verified",$C$39=1),0,1) -> 20.4 | ... Y56: =IF(Y$45<$G56,0,IF($F56=1,$C$10+($C$11-$C$10)*MIN(Y$45-$G56,$C$12)/$C$12,$E56*$C$5*INDEX($C$6:$C$9,MIN(Y$45-$G56,3)+1)))*(1-$C$14)*IF(AND($C56="Verified",$C$39=1),0,1) -> 20.4
A57: =Assumptions!A66 -> 10 | B57: =Assumptions!B66 -> C | C57: =Assumptions!C66 -> Assured | D57: =Assumptions!D66 -> 8000 | E57: =Assumptions!E66 -> 26 | F57: =Assumptions!G66 -> 0 | G57: =Assumptions!F66+IF(F57=1,0,$C$15) -> 6 | H57: =IF(H$45<$G57,0,IF($F57=1,$C$10+($C$11-$C$10)*MIN(H$45-$G57,$C$12)/$C$12,$E57*$C$5*INDEX($C$6:$C$9,MIN(H$45-$G57,3)+1)))*(1-$C$14)*IF(AND($C57="Verified",$C$39=1),0,1) -> 0 | I57: =IF(I$45<$G57,0,IF($F57=1,$C$10+($C$11-$C$10)*MIN(I$45-$G57,$C$12)/$C$12,$E57*$C$5*INDEX($C$6:$C$9,MIN(I$45-$G57,3)+1)))*(1-$C$14)*IF(AND($C57="Verified",$C$39=1),0,1) -> 0 | J57: =IF(J$45<$G57,0,IF($F57=1,$C$10+($C$11-$C$10)*MIN(J$45-$G57,$C$12)/$C$12,$E57*$C$5*INDEX($C$6:$C$9,MIN(J$45-$G57,3)+1)))*(1-$C$14)*IF(AND($C57="Verified",$C$39=1),0,1) -> 0 | K57: =IF(K$45<$G57,0,IF($F57=1,$C$10+($C$11-$C$10)*MIN(K$45-$G57,$C$12)/$C$12,$E57*$C$5*INDEX($C$6:$C$9,MIN(K$45-$G57,3)+1)))*(1-$C$14)*IF(AND($C57="Verified",$C$39=1),0,1) -> 0 | L57: =IF(L$45<$G57,0,IF($F57=1,$C$10+($C$11-$C$10)*MIN(L$45-$G57,$C$12)/$C$12,$E57*$C$5*INDEX($C$6:$C$9,MIN(L$45-$G57,3)+1)))*(1-$C$14)*IF(AND($C57="Verified",$C$39=1),0,1) -> 0 | M57: =IF(M$45<$G57,0,IF($F57=1,$C$10+($C$11-$C$10)*MIN(M$45-$G57,$C$12)/$C$12,$E57*$C$5*INDEX($C$6:$C$9,MIN(M$45-$G57,3)+1)))*(1-$C$14)*IF(AND($C57="Verified",$C$39=1),0,1) -> 6.63 | N57: =IF(N$45<$G57,0,IF($F57=1,$C$10+($C$11-$C$10)*MIN(N$45-$G57,$C$12)/$C$12,$E57*$C$5*INDEX($C$6:$C$9,MIN(N$45-$G57,3)+1)))*(1-$C$14)*IF(AND($C57="Verified",$C$39=1),0,1) -> 13.26 | O57: =IF(O$45<$G57,0,IF($F57=1,$C$10+($C$11-$C$10)*MIN(O$45-$G57,$C$12)/$C$12,$E57*$C$5*INDEX($C$6:$C$9,MIN(O$45-$G57,3)+1)))*(1-$C$14)*IF(AND($C57="Verified",$C$39=1),0,1) -> 18.785 | ... Y57: =IF(Y$45<$G57,0,IF($F57=1,$C$10+($C$11-$C$10)*MIN(Y$45-$G57,$C$12)/$C$12,$E57*$C$5*INDEX($C$6:$C$9,MIN(Y$45-$G57,3)+1)))*(1-$C$14)*IF(AND($C57="Verified",$C$39=1),0,1) -> 22.1
A58: =Assumptions!A67 -> 11 | B58: =Assumptions!B67 -> C | C58: =Assumptions!C67 -> Assured | D58: =Assumptions!D67 -> 8000 | E58: =Assumptions!E67 -> 26 | F58: =Assumptions!G67 -> 0 | G58: =Assumptions!F67+IF(F58=1,0,$C$15) -> 7 | H58: =IF(H$45<$G58,0,IF($F58=1,$C$10+($C$11-$C$10)*MIN(H$45-$G58,$C$12)/$C$12,$E58*$C$5*INDEX($C$6:$C$9,MIN(H$45-$G58,3)+1)))*(1-$C$14)*IF(AND($C58="Verified",$C$39=1),0,1) -> 0 | I58: =IF(I$45<$G58,0,IF($F58=1,$C$10+($C$11-$C$10)*MIN(I$45-$G58,$C$12)/$C$12,$E58*$C$5*INDEX($C$6:$C$9,MIN(I$45-$G58,3)+1)))*(1-$C$14)*IF(AND($C58="Verified",$C$39=1),0,1) -> 0 | J58: =IF(J$45<$G58,0,IF($F58=1,$C$10+($C$11-$C$10)*MIN(J$45-$G58,$C$12)/$C$12,$E58*$C$5*INDEX($C$6:$C$9,MIN(J$45-$G58,3)+1)))*(1-$C$14)*IF(AND($C58="Verified",$C$39=1),0,1) -> 0 | K58: =IF(K$45<$G58,0,IF($F58=1,$C$10+($C$11-$C$10)*MIN(K$45-$G58,$C$12)/$C$12,$E58*$C$5*INDEX($C$6:$C$9,MIN(K$45-$G58,3)+1)))*(1-$C$14)*IF(AND($C58="Verified",$C$39=1),0,1) -> 0 | L58: =IF(L$45<$G58,0,IF($F58=1,$C$10+($C$11-$C$10)*MIN(L$45-$G58,$C$12)/$C$12,$E58*$C$5*INDEX($C$6:$C$9,MIN(L$45-$G58,3)+1)))*(1-$C$14)*IF(AND($C58="Verified",$C$39=1),0,1) -> 0 | M58: =IF(M$45<$G58,0,IF($F58=1,$C$10+($C$11-$C$10)*MIN(M$45-$G58,$C$12)/$C$12,$E58*$C$5*INDEX($C$6:$C$9,MIN(M$45-$G58,3)+1)))*(1-$C$14)*IF(AND($C58="Verified",$C$39=1),0,1) -> 0 | N58: =IF(N$45<$G58,0,IF($F58=1,$C$10+($C$11-$C$10)*MIN(N$45-$G58,$C$12)/$C$12,$E58*$C$5*INDEX($C$6:$C$9,MIN(N$45-$G58,3)+1)))*(1-$C$14)*IF(AND($C58="Verified",$C$39=1),0,1) -> 6.63 | O58: =IF(O$45<$G58,0,IF($F58=1,$C$10+($C$11-$C$10)*MIN(O$45-$G58,$C$12)/$C$12,$E58*$C$5*INDEX($C$6:$C$9,MIN(O$45-$G58,3)+1)))*(1-$C$14)*IF(AND($C58="Verified",$C$39=1),0,1) -> 13.26 | ... Y58: =IF(Y$45<$G58,0,IF($F58=1,$C$10+($C$11-$C$10)*MIN(Y$45-$G58,$C$12)/$C$12,$E58*$C$5*INDEX($C$6:$C$9,MIN(Y$45-$G58,3)+1)))*(1-$C$14)*IF(AND($C58="Verified",$C$39=1),0,1) -> 22.1
A59: =Assumptions!A68 -> 12 | B59: =Assumptions!B68 -> C | C59: =Assumptions!C68 -> Assured | D59: =Assumptions!D68 -> 8000 | E59: =Assumptions!E68 -> 26 | F59: =Assumptions!G68 -> 0 | G59: =Assumptions!F68+IF(F59=1,0,$C$15) -> 7 | H59: =IF(H$45<$G59,0,IF($F59=1,$C$10+($C$11-$C$10)*MIN(H$45-$G59,$C$12)/$C$12,$E59*$C$5*INDEX($C$6:$C$9,MIN(H$45-$G59,3)+1)))*(1-$C$14)*IF(AND($C59="Verified",$C$39=1),0,1) -> 0 | I59: =IF(I$45<$G59,0,IF($F59=1,$C$10+($C$11-$C$10)*MIN(I$45-$G59,$C$12)/$C$12,$E59*$C$5*INDEX($C$6:$C$9,MIN(I$45-$G59,3)+1)))*(1-$C$14)*IF(AND($C59="Verified",$C$39=1),0,1) -> 0 | J59: =IF(J$45<$G59,0,IF($F59=1,$C$10+($C$11-$C$10)*MIN(J$45-$G59,$C$12)/$C$12,$E59*$C$5*INDEX($C$6:$C$9,MIN(J$45-$G59,3)+1)))*(1-$C$14)*IF(AND($C59="Verified",$C$39=1),0,1) -> 0 | K59: =IF(K$45<$G59,0,IF($F59=1,$C$10+($C$11-$C$10)*MIN(K$45-$G59,$C$12)/$C$12,$E59*$C$5*INDEX($C$6:$C$9,MIN(K$45-$G59,3)+1)))*(1-$C$14)*IF(AND($C59="Verified",$C$39=1),0,1) -> 0 | L59: =IF(L$45<$G59,0,IF($F59=1,$C$10+($C$11-$C$10)*MIN(L$45-$G59,$C$12)/$C$12,$E59*$C$5*INDEX($C$6:$C$9,MIN(L$45-$G59,3)+1)))*(1-$C$14)*IF(AND($C59="Verified",$C$39=1),0,1) -> 0 | M59: =IF(M$45<$G59,0,IF($F59=1,$C$10+($C$11-$C$10)*MIN(M$45-$G59,$C$12)/$C$12,$E59*$C$5*INDEX($C$6:$C$9,MIN(M$45-$G59,3)+1)))*(1-$C$14)*IF(AND($C59="Verified",$C$39=1),0,1) -> 0 | N59: =IF(N$45<$G59,0,IF($F59=1,$C$10+($C$11-$C$10)*MIN(N$45-$G59,$C$12)/$C$12,$E59*$C$5*INDEX($C$6:$C$9,MIN(N$45-$G59,3)+1)))*(1-$C$14)*IF(AND($C59="Verified",$C$39=1),0,1) -> 6.63 | O59: =IF(O$45<$G59,0,IF($F59=1,$C$10+($C$11-$C$10)*MIN(O$45-$G59,$C$12)/$C$12,$E59*$C$5*INDEX($C$6:$C$9,MIN(O$45-$G59,3)+1)))*(1-$C$14)*IF(AND($C59="Verified",$C$39=1),0,1) -> 13.26 | ... Y59: =IF(Y$45<$G59,0,IF($F59=1,$C$10+($C$11-$C$10)*MIN(Y$45-$G59,$C$12)/$C$12,$E59*$C$5*INDEX($C$6:$C$9,MIN(Y$45-$G59,3)+1)))*(1-$C$14)*IF(AND($C59="Verified",$C$39=1),0,1) -> 22.1
... A67: =Assumptions!A76 -> 20 | B67: =Assumptions!B76 -> B | C67: =Assumptions!C76 -> Verified | D67: =Assumptions!D76 -> 6500 | E67: =Assumptions!E76 -> 30 | F67: =Assumptions!G76 -> 0 | G67: =Assumptions!F76+IF(F67=1,0,$C$15) -> 14 | H67: =IF(H$45<$G67,0,IF($F67=1,$C$10+($C$11-$C$10)*MIN(H$45-$G67,$C$12)/$C$12,$E67*$C$5*INDEX($C$6:$C$9,MIN(H$45-$G67,3)+1)))*(1-$C$14)*IF(AND($C67="Verified",$C$39=1),0,1) -> 0 | I67: =IF(I$45<$G67,0,IF($F67=1,$C$10+($C$11-$C$10)*MIN(I$45-$G67,$C$12)/$C$12,$E67*$C$5*INDEX($C$6:$C$9,MIN(I$45-$G67,3)+1)))*(1-$C$14)*IF(AND($C67="Verified",$C$39=1),0,1) -> 0 | J67: =IF(J$45<$G67,0,IF($F67=1,$C$10+($C$11-$C$10)*MIN(J$45-$G67,$C$12)/$C$12,$E67*$C$5*INDEX($C$6:$C$9,MIN(J$45-$G67,3)+1)))*(1-$C$14)*IF(AND($C67="Verified",$C$39=1),0,1) -> 0 | K67: =IF(K$45<$G67,0,IF($F67=1,$C$10+($C$11-$C$10)*MIN(K$45-$G67,$C$12)/$C$12,$E67*$C$5*INDEX($C$6:$C$9,MIN(K$45-$G67,3)+1)))*(1-$C$14)*IF(AND($C67="Verified",$C$39=1),0,1) -> 0 | L67: =IF(L$45<$G67,0,IF($F67=1,$C$10+($C$11-$C$10)*MIN(L$45-$G67,$C$12)/$C$12,$E67*$C$5*INDEX($C$6:$C$9,MIN(L$45-$G67,3)+1)))*(1-$C$14)*IF(AND($C67="Verified",$C$39=1),0,1) -> 0 | M67: =IF(M$45<$G67,0,IF($F67=1,$C$10+($C$11-$C$10)*MIN(M$45-$G67,$C$12)/$C$12,$E67*$C$5*INDEX($C$6:$C$9,MIN(M$45-$G67,3)+1)))*(1-$C$14)*IF(AND($C67="Verified",$C$39=1),0,1) -> 0 | N67: =IF(N$45<$G67,0,IF($F67=1,$C$10+($C$11-$C$10)*MIN(N$45-$G67,$C$12)/$C$12,$E67*$C$5*INDEX($C$6:$C$9,MIN(N$45-$G67,3)+1)))*(1-$C$14)*IF(AND($C67="Verified",$C$39=1),0,1) -> 0 | O67: =IF(O$45<$G67,0,IF($F67=1,$C$10+($C$11-$C$10)*MIN(O$45-$G67,$C$12)/$C$12,$E67*$C$5*INDEX($C$6:$C$9,MIN(O$45-$G67,3)+1)))*(1-$C$14)*IF(AND($C67="Verified",$C$39=1),0,1) -> 0 | ... Y67: =IF(Y$45<$G67,0,IF($F67=1,$C$10+($C$11-$C$10)*MIN(Y$45-$G67,$C$12)/$C$12,$E67*$C$5*INDEX($C$6:$C$9,MIN(Y$45-$G67,3)+1)))*(1-$C$14)*IF(AND($C67="Verified",$C$39=1),0,1) -> 25.5
A69: OpenBench revenue per host (₹)
A70: =A48 -> 1 | B70: =B48 -> Pilot | C70: =C48 -> Assured | H70: =H48*$D48*$C$13*INDEX(Assumptions!$B$44:$B$46,MATCH($C48,Assumptions!$A$44:$A$46,0))+IF(H$45>=$G48,INDEX(Assumptions!$C$44:$C$46,MATCH($C48,Assumptions!$A$44:$A$46,0)),0)+IF($C48="Assured",H48*$D48*$C$13*$C$26*$C$27*$C$28,0) -> 47228.125 | I70: =I48*$D48*$C$13*INDEX(Assumptions!$B$44:$B$46,MATCH($C48,Assumptions!$A$44:$A$46,0))+IF(I$45>=$G48,INDEX(Assumptions!$C$44:$C$46,MATCH($C48,Assumptions!$A$44:$A$46,0)),0)+IF($C48="Assured",I48*$D48*$C$13*$C$26*$C$27*$C$28,0) -> 49477.083 | J70: =J48*$D48*$C$13*INDEX(Assumptions!$B$44:$B$46,MATCH($C48,Assumptions!$A$44:$A$46,0))+IF(J$45>=$G48,INDEX(Assumptions!$C$44:$C$46,MATCH($C48,Assumptions!$A$44:$A$46,0)),0)+IF($C48="Assured",J48*$D48*$C$13*$C$26*$C$27*$C$28,0) -> 51726.042 | K70: =K48*$D48*$C$13*INDEX(Assumptions!$B$44:$B$46,MATCH($C48,Assumptions!$A$44:$A$46,0))+IF(K$45>=$G48,INDEX(Assumptions!$C$44:$C$46,MATCH($C48,Assumptions!$A$44:$A$46,0)),0)+IF($C48="Assured",K48*$D48*$C$13*$C$26*$C$27*$C$28,0) -> 53975 | L70: =L48*$D48*$C$13*INDEX(Assumptions!$B$44:$B$46,MATCH($C48,Assumptions!$A$44:$A$46,0))+IF(L$45>=$G48,INDEX(Assumptions!$C$44:$C$46,MATCH($C48,Assumptions!$A$44:$A$46,0)),0)+IF($C48="Assured",L48*$D48*$C$13*$C$26*$C$27*$C$28,0) -> 53975 | M70: =M48*$D48*$C$13*INDEX(Assumptions!$B$44:$B$46,MATCH($C48,Assumptions!$A$44:$A$46,0))+IF(M$45>=$G48,INDEX(Assumptions!$C$44:$C$46,MATCH($C48,Assumptions!$A$44:$A$46,0)),0)+IF($C48="Assured",M48*$D48*$C$13*$C$26*$C$27*$C$28,0) -> 53975 | N70: =N48*$D48*$C$13*INDEX(Assumptions!$B$44:$B$46,MATCH($C48,Assumptions!$A$44:$A$46,0))+IF(N$45>=$G48,INDEX(Assumptions!$C$44:$C$46,MATCH($C48,Assumptions!$A$44:$A$46,0)),0)+IF($C48="Assured",N48*$D48*$C$13*$C$26*$C$27*$C$28,0) -> 53975 | O70: =O48*$D48*$C$13*INDEX(Assumptions!$B$44:$B$46,MATCH($C48,Assumptions!$A$44:$A$46,0))+IF(O$45>=$G48,INDEX(Assumptions!$C$44:$C$46,MATCH($C48,Assumptions!$A$44:$A$46,0)),0)+IF($C48="Assured",O48*$D48*$C$13*$C$26*$C$27*$C$28,0) -> 53975 | ... Y70: =Y48*$D48*$C$13*INDEX(Assumptions!$B$44:$B$46,MATCH($C48,Assumptions!$A$44:$A$46,0))+IF(Y$45>=$G48,INDEX(Assumptions!$C$44:$C$46,MATCH($C48,Assumptions!$A$44:$A$46,0)),0)+IF($C48="Assured",Y48*$D48*$C$13*$C$26*$C$27*$C$28,0) -> 53975
A71: =A49 -> 2 | B71: =B49 -> Pilot | C71: =C49 -> Assured | H71: =H49*$D49*$C$13*INDEX(Assumptions!$B$44:$B$46,MATCH($C49,Assumptions!$A$44:$A$46,0))+IF(H$45>=$G49,INDEX(Assumptions!$C$44:$C$46,MATCH($C49,Assumptions!$A$44:$A$46,0)),0)+IF($C49="Assured",H49*$D49*$C$13*$C$26*$C$27*$C$28,0) -> 47228.125 | I71: =I49*$D49*$C$13*INDEX(Assumptions!$B$44:$B$46,MATCH($C49,Assumptions!$A$44:$A$46,0))+IF(I$45>=$G49,INDEX(Assumptions!$C$44:$C$46,MATCH($C49,Assumptions!$A$44:$A$46,0)),0)+IF($C49="Assured",I49*$D49*$C$13*$C$26*$C$27*$C$28,0) -> 49477.083 | J71: =J49*$D49*$C$13*INDEX(Assumptions!$B$44:$B$46,MATCH($C49,Assumptions!$A$44:$A$46,0))+IF(J$45>=$G49,INDEX(Assumptions!$C$44:$C$46,MATCH($C49,Assumptions!$A$44:$A$46,0)),0)+IF($C49="Assured",J49*$D49*$C$13*$C$26*$C$27*$C$28,0) -> 51726.042 | K71: =K49*$D49*$C$13*INDEX(Assumptions!$B$44:$B$46,MATCH($C49,Assumptions!$A$44:$A$46,0))+IF(K$45>=$G49,INDEX(Assumptions!$C$44:$C$46,MATCH($C49,Assumptions!$A$44:$A$46,0)),0)+IF($C49="Assured",K49*$D49*$C$13*$C$26*$C$27*$C$28,0) -> 53975 | L71: =L49*$D49*$C$13*INDEX(Assumptions!$B$44:$B$46,MATCH($C49,Assumptions!$A$44:$A$46,0))+IF(L$45>=$G49,INDEX(Assumptions!$C$44:$C$46,MATCH($C49,Assumptions!$A$44:$A$46,0)),0)+IF($C49="Assured",L49*$D49*$C$13*$C$26*$C$27*$C$28,0) -> 53975 | M71: =M49*$D49*$C$13*INDEX(Assumptions!$B$44:$B$46,MATCH($C49,Assumptions!$A$44:$A$46,0))+IF(M$45>=$G49,INDEX(Assumptions!$C$44:$C$46,MATCH($C49,Assumptions!$A$44:$A$46,0)),0)+IF($C49="Assured",M49*$D49*$C$13*$C$26*$C$27*$C$28,0) -> 53975 | N71: =N49*$D49*$C$13*INDEX(Assumptions!$B$44:$B$46,MATCH($C49,Assumptions!$A$44:$A$46,0))+IF(N$45>=$G49,INDEX(Assumptions!$C$44:$C$46,MATCH($C49,Assumptions!$A$44:$A$46,0)),0)+IF($C49="Assured",N49*$D49*$C$13*$C$26*$C$27*$C$28,0) -> 53975 | O71: =O49*$D49*$C$13*INDEX(Assumptions!$B$44:$B$46,MATCH($C49,Assumptions!$A$44:$A$46,0))+IF(O$45>=$G49,INDEX(Assumptions!$C$44:$C$46,MATCH($C49,Assumptions!$A$44:$A$46,0)),0)+IF($C49="Assured",O49*$D49*$C$13*$C$26*$C$27*$C$28,0) -> 53975 | ... Y71: =Y49*$D49*$C$13*INDEX(Assumptions!$B$44:$B$46,MATCH($C49,Assumptions!$A$44:$A$46,0))+IF(Y$45>=$G49,INDEX(Assumptions!$C$44:$C$46,MATCH($C49,Assumptions!$A$44:$A$46,0)),0)+IF($C49="Assured",Y49*$D49*$C$13*$C$26*$C$27*$C$28,0) -> 53975
A72: =A50 -> 3 | B72: =B50 -> Pilot | C72: =C50 -> Assured | H72: =H50*$D50*$C$13*INDEX(Assumptions!$B$44:$B$46,MATCH($C50,Assumptions!$A$44:$A$46,0))+IF(H$45>=$G50,INDEX(Assumptions!$C$44:$C$46,MATCH($C50,Assumptions!$A$44:$A$46,0)),0)+IF($C50="Assured",H50*$D50*$C$13*$C$26*$C$27*$C$28,0) -> 47228.125 | I72: =I50*$D50*$C$13*INDEX(Assumptions!$B$44:$B$46,MATCH($C50,Assumptions!$A$44:$A$46,0))+IF(I$45>=$G50,INDEX(Assumptions!$C$44:$C$46,MATCH($C50,Assumptions!$A$44:$A$46,0)),0)+IF($C50="Assured",I50*$D50*$C$13*$C$26*$C$27*$C$28,0) -> 49477.083 | J72: =J50*$D50*$C$13*INDEX(Assumptions!$B$44:$B$46,MATCH($C50,Assumptions!$A$44:$A$46,0))+IF(J$45>=$G50,INDEX(Assumptions!$C$44:$C$46,MATCH($C50,Assumptions!$A$44:$A$46,0)),0)+IF($C50="Assured",J50*$D50*$C$13*$C$26*$C$27*$C$28,0) -> 51726.042 | K72: =K50*$D50*$C$13*INDEX(Assumptions!$B$44:$B$46,MATCH($C50,Assumptions!$A$44:$A$46,0))+IF(K$45>=$G50,INDEX(Assumptions!$C$44:$C$46,MATCH($C50,Assumptions!$A$44:$A$46,0)),0)+IF($C50="Assured",K50*$D50*$C$13*$C$26*$C$27*$C$28,0) -> 53975 | L72: =L50*$D50*$C$13*INDEX(Assumptions!$B$44:$B$46,MATCH($C50,Assumptions!$A$44:$A$46,0))+IF(L$45>=$G50,INDEX(Assumptions!$C$44:$C$46,MATCH($C50,Assumptions!$A$44:$A$46,0)),0)+IF($C50="Assured",L50*$D50*$C$13*$C$26*$C$27*$C$28,0) -> 53975 | M72: =M50*$D50*$C$13*INDEX(Assumptions!$B$44:$B$46,MATCH($C50,Assumptions!$A$44:$A$46,0))+IF(M$45>=$G50,INDEX(Assumptions!$C$44:$C$46,MATCH($C50,Assumptions!$A$44:$A$46,0)),0)+IF($C50="Assured",M50*$D50*$C$13*$C$26*$C$27*$C$28,0) -> 53975 | N72: =N50*$D50*$C$13*INDEX(Assumptions!$B$44:$B$46,MATCH($C50,Assumptions!$A$44:$A$46,0))+IF(N$45>=$G50,INDEX(Assumptions!$C$44:$C$46,MATCH($C50,Assumptions!$A$44:$A$46,0)),0)+IF($C50="Assured",N50*$D50*$C$13*$C$26*$C$27*$C$28,0) -> 53975 | O72: =O50*$D50*$C$13*INDEX(Assumptions!$B$44:$B$46,MATCH($C50,Assumptions!$A$44:$A$46,0))+IF(O$45>=$G50,INDEX(Assumptions!$C$44:$C$46,MATCH($C50,Assumptions!$A$44:$A$46,0)),0)+IF($C50="Assured",O50*$D50*$C$13*$C$26*$C$27*$C$28,0) -> 53975 | ... Y72: =Y50*$D50*$C$13*INDEX(Assumptions!$B$44:$B$46,MATCH($C50,Assumptions!$A$44:$A$46,0))+IF(Y$45>=$G50,INDEX(Assumptions!$C$44:$C$46,MATCH($C50,Assumptions!$A$44:$A$46,0)),0)+IF($C50="Assured",Y50*$D50*$C$13*$C$26*$C$27*$C$28,0) -> 53975
A73: =A51 -> 4 | B73: =B51 -> Pilot | C73: =C51 -> Assured | H73: =H51*$D51*$C$13*INDEX(Assumptions!$B$44:$B$46,MATCH($C51,Assumptions!$A$44:$A$46,0))+IF(H$45>=$G51,INDEX(Assumptions!$C$44:$C$46,MATCH($C51,Assumptions!$A$44:$A$46,0)),0)+IF($C51="Assured",H51*$D51*$C$13*$C$26*$C$27*$C$28,0) -> 47228.125 | I73: =I51*$D51*$C$13*INDEX(Assumptions!$B$44:$B$46,MATCH($C51,Assumptions!$A$44:$A$46,0))+IF(I$45>=$G51,INDEX(Assumptions!$C$44:$C$46,MATCH($C51,Assumptions!$A$44:$A$46,0)),0)+IF($C51="Assured",I51*$D51*$C$13*$C$26*$C$27*$C$28,0) -> 49477.083 | J73: =J51*$D51*$C$13*INDEX(Assumptions!$B$44:$B$46,MATCH($C51,Assumptions!$A$44:$A$46,0))+IF(J$45>=$G51,INDEX(Assumptions!$C$44:$C$46,MATCH($C51,Assumptions!$A$44:$A$46,0)),0)+IF($C51="Assured",J51*$D51*$C$13*$C$26*$C$27*$C$28,0) -> 51726.042 | K73: =K51*$D51*$C$13*INDEX(Assumptions!$B$44:$B$46,MATCH($C51,Assumptions!$A$44:$A$46,0))+IF(K$45>=$G51,INDEX(Assumptions!$C$44:$C$46,MATCH($C51,Assumptions!$A$44:$A$46,0)),0)+IF($C51="Assured",K51*$D51*$C$13*$C$26*$C$27*$C$28,0) -> 53975 | L73: =L51*$D51*$C$13*INDEX(Assumptions!$B$44:$B$46,MATCH($C51,Assumptions!$A$44:$A$46,0))+IF(L$45>=$G51,INDEX(Assumptions!$C$44:$C$46,MATCH($C51,Assumptions!$A$44:$A$46,0)),0)+IF($C51="Assured",L51*$D51*$C$13*$C$26*$C$27*$C$28,0) -> 53975 | M73: =M51*$D51*$C$13*INDEX(Assumptions!$B$44:$B$46,MATCH($C51,Assumptions!$A$44:$A$46,0))+IF(M$45>=$G51,INDEX(Assumptions!$C$44:$C$46,MATCH($C51,Assumptions!$A$44:$A$46,0)),0)+IF($C51="Assured",M51*$D51*$C$13*$C$26*$C$27*$C$28,0) -> 53975 | N73: =N51*$D51*$C$13*INDEX(Assumptions!$B$44:$B$46,MATCH($C51,Assumptions!$A$44:$A$46,0))+IF(N$45>=$G51,INDEX(Assumptions!$C$44:$C$46,MATCH($C51,Assumptions!$A$44:$A$46,0)),0)+IF($C51="Assured",N51*$D51*$C$13*$C$26*$C$27*$C$28,0) -> 53975 | O73: =O51*$D51*$C$13*INDEX(Assumptions!$B$44:$B$46,MATCH($C51,Assumptions!$A$44:$A$46,0))+IF(O$45>=$G51,INDEX(Assumptions!$C$44:$C$46,MATCH($C51,Assumptions!$A$44:$A$46,0)),0)+IF($C51="Assured",O51*$D51*$C$13*$C$26*$C$27*$C$28,0) -> 53975 | ... Y73: =Y51*$D51*$C$13*INDEX(Assumptions!$B$44:$B$46,MATCH($C51,Assumptions!$A$44:$A$46,0))+IF(Y$45>=$G51,INDEX(Assumptions!$C$44:$C$46,MATCH($C51,Assumptions!$A$44:$A$46,0)),0)+IF($C51="Assured",Y51*$D51*$C$13*$C$26*$C$27*$C$28,0) -> 53975
A74: =A52 -> 5 | B74: =B52 -> A | C74: =C52 -> Assured | H74: =H52*$D52*$C$13*INDEX(Assumptions!$B$44:$B$46,MATCH($C52,Assumptions!$A$44:$A$46,0))+IF(H$45>=$G52,INDEX(Assumptions!$C$44:$C$46,MATCH($C52,Assumptions!$A$44:$A$46,0)),0)+IF($C52="Assured",H52*$D52*$C$13*$C$26*$C$27*$C$28,0) -> 0 | I74: =I52*$D52*$C$13*INDEX(Assumptions!$B$44:$B$46,MATCH($C52,Assumptions!$A$44:$A$46,0))+IF(I$45>=$G52,INDEX(Assumptions!$C$44:$C$46,MATCH($C52,Assumptions!$A$44:$A$46,0)),0)+IF($C52="Assured",I52*$D52*$C$13*$C$26*$C$27*$C$28,0) -> 0 | J74: =J52*$D52*$C$13*INDEX(Assumptions!$B$44:$B$46,MATCH($C52,Assumptions!$A$44:$A$46,0))+IF(J$45>=$G52,INDEX(Assumptions!$C$44:$C$46,MATCH($C52,Assumptions!$A$44:$A$46,0)),0)+IF($C52="Assured",J52*$D52*$C$13*$C$26*$C$27*$C$28,0) -> 23317.2 | K74: =K52*$D52*$C$13*INDEX(Assumptions!$B$44:$B$46,MATCH($C52,Assumptions!$A$44:$A$46,0))+IF(K$45>=$G52,INDEX(Assumptions!$C$44:$C$46,MATCH($C52,Assumptions!$A$44:$A$46,0)),0)+IF($C52="Assured",K52*$D52*$C$13*$C$26*$C$27*$C$28,0) -> 46634.4 | L74: =L52*$D52*$C$13*INDEX(Assumptions!$B$44:$B$46,MATCH($C52,Assumptions!$A$44:$A$46,0))+IF(L$45>=$G52,INDEX(Assumptions!$C$44:$C$46,MATCH($C52,Assumptions!$A$44:$A$46,0)),0)+IF($C52="Assured",L52*$D52*$C$13*$C$26*$C$27*$C$28,0) -> 66065.4 | M74: =M52*$D52*$C$13*INDEX(Assumptions!$B$44:$B$46,MATCH($C52,Assumptions!$A$44:$A$46,0))+IF(M$45>=$G52,INDEX(Assumptions!$C$44:$C$46,MATCH($C52,Assumptions!$A$44:$A$46,0)),0)+IF($C52="Assured",M52*$D52*$C$13*$C$26*$C$27*$C$28,0) -> 77724 | N74: =N52*$D52*$C$13*INDEX(Assumptions!$B$44:$B$46,MATCH($C52,Assumptions!$A$44:$A$46,0))+IF(N$45>=$G52,INDEX(Assumptions!$C$44:$C$46,MATCH($C52,Assumptions!$A$44:$A$46,0)),0)+IF($C52="Assured",N52*$D52*$C$13*$C$26*$C$27*$C$28,0) -> 77724 | O74: =O52*$D52*$C$13*INDEX(Assumptions!$B$44:$B$46,MATCH($C52,Assumptions!$A$44:$A$46,0))+IF(O$45>=$G52,INDEX(Assumptions!$C$44:$C$46,MATCH($C52,Assumptions!$A$44:$A$46,0)),0)+IF($C52="Assured",O52*$D52*$C$13*$C$26*$C$27*$C$28,0) -> 77724 | ... Y74: =Y52*$D52*$C$13*INDEX(Assumptions!$B$44:$B$46,MATCH($C52,Assumptions!$A$44:$A$46,0))+IF(Y$45>=$G52,INDEX(Assumptions!$C$44:$C$46,MATCH($C52,Assumptions!$A$44:$A$46,0)),0)+IF($C52="Assured",Y52*$D52*$C$13*$C$26*$C$27*$C$28,0) -> 77724
A75: =A53 -> 6 | B75: =B53 -> A | C75: =C53 -> Assured | H75: =H53*$D53*$C$13*INDEX(Assumptions!$B$44:$B$46,MATCH($C53,Assumptions!$A$44:$A$46,0))+IF(H$45>=$G53,INDEX(Assumptions!$C$44:$C$46,MATCH($C53,Assumptions!$A$44:$A$46,0)),0)+IF($C53="Assured",H53*$D53*$C$13*$C$26*$C$27*$C$28,0) -> 0 | I75: =I53*$D53*$C$13*INDEX(Assumptions!$B$44:$B$46,MATCH($C53,Assumptions!$A$44:$A$46,0))+IF(I$45>=$G53,INDEX(Assumptions!$C$44:$C$46,MATCH($C53,Assumptions!$A$44:$A$46,0)),0)+IF($C53="Assured",I53*$D53*$C$13*$C$26*$C$27*$C$28,0) -> 0 | J75: =J53*$D53*$C$13*INDEX(Assumptions!$B$44:$B$46,MATCH($C53,Assumptions!$A$44:$A$46,0))+IF(J$45>=$G53,INDEX(Assumptions!$C$44:$C$46,MATCH($C53,Assumptions!$A$44:$A$46,0)),0)+IF($C53="Assured",J53*$D53*$C$13*$C$26*$C$27*$C$28,0) -> 23317.2 | K75: =K53*$D53*$C$13*INDEX(Assumptions!$B$44:$B$46,MATCH($C53,Assumptions!$A$44:$A$46,0))+IF(K$45>=$G53,INDEX(Assumptions!$C$44:$C$46,MATCH($C53,Assumptions!$A$44:$A$46,0)),0)+IF($C53="Assured",K53*$D53*$C$13*$C$26*$C$27*$C$28,0) -> 46634.4 | L75: =L53*$D53*$C$13*INDEX(Assumptions!$B$44:$B$46,MATCH($C53,Assumptions!$A$44:$A$46,0))+IF(L$45>=$G53,INDEX(Assumptions!$C$44:$C$46,MATCH($C53,Assumptions!$A$44:$A$46,0)),0)+IF($C53="Assured",L53*$D53*$C$13*$C$26*$C$27*$C$28,0) -> 66065.4 | M75: =M53*$D53*$C$13*INDEX(Assumptions!$B$44:$B$46,MATCH($C53,Assumptions!$A$44:$A$46,0))+IF(M$45>=$G53,INDEX(Assumptions!$C$44:$C$46,MATCH($C53,Assumptions!$A$44:$A$46,0)),0)+IF($C53="Assured",M53*$D53*$C$13*$C$26*$C$27*$C$28,0) -> 77724 | N75: =N53*$D53*$C$13*INDEX(Assumptions!$B$44:$B$46,MATCH($C53,Assumptions!$A$44:$A$46,0))+IF(N$45>=$G53,INDEX(Assumptions!$C$44:$C$46,MATCH($C53,Assumptions!$A$44:$A$46,0)),0)+IF($C53="Assured",N53*$D53*$C$13*$C$26*$C$27*$C$28,0) -> 77724 | O75: =O53*$D53*$C$13*INDEX(Assumptions!$B$44:$B$46,MATCH($C53,Assumptions!$A$44:$A$46,0))+IF(O$45>=$G53,INDEX(Assumptions!$C$44:$C$46,MATCH($C53,Assumptions!$A$44:$A$46,0)),0)+IF($C53="Assured",O53*$D53*$C$13*$C$26*$C$27*$C$28,0) -> 77724 | ... Y75: =Y53*$D53*$C$13*INDEX(Assumptions!$B$44:$B$46,MATCH($C53,Assumptions!$A$44:$A$46,0))+IF(Y$45>=$G53,INDEX(Assumptions!$C$44:$C$46,MATCH($C53,Assumptions!$A$44:$A$46,0)),0)+IF($C53="Assured",Y53*$D53*$C$13*$C$26*$C$27*$C$28,0) -> 77724
A76: =A54 -> 7 | B76: =B54 -> A | C76: =C54 -> Assured | H76: =H54*$D54*$C$13*INDEX(Assumptions!$B$44:$B$46,MATCH($C54,Assumptions!$A$44:$A$46,0))+IF(H$45>=$G54,INDEX(Assumptions!$C$44:$C$46,MATCH($C54,Assumptions!$A$44:$A$46,0)),0)+IF($C54="Assured",H54*$D54*$C$13*$C$26*$C$27*$C$28,0) -> 0 | I76: =I54*$D54*$C$13*INDEX(Assumptions!$B$44:$B$46,MATCH($C54,Assumptions!$A$44:$A$46,0))+IF(I$45>=$G54,INDEX(Assumptions!$C$44:$C$46,MATCH($C54,Assumptions!$A$44:$A$46,0)),0)+IF($C54="Assured",I54*$D54*$C$13*$C$26*$C$27*$C$28,0) -> 0 | J76: =J54*$D54*$C$13*INDEX(Assumptions!$B$44:$B$46,MATCH($C54,Assumptions!$A$44:$A$46,0))+IF(J$45>=$G54,INDEX(Assumptions!$C$44:$C$46,MATCH($C54,Assumptions!$A$44:$A$46,0)),0)+IF($C54="Assured",J54*$D54*$C$13*$C$26*$C$27*$C$28,0) -> 0 | K76: =K54*$D54*$C$13*INDEX(Assumptions!$B$44:$B$46,MATCH($C54,Assumptions!$A$44:$A$46,0))+IF(K$45>=$G54,INDEX(Assumptions!$C$44:$C$46,MATCH($C54,Assumptions!$A$44:$A$46,0)),0)+IF($C54="Assured",K54*$D54*$C$13*$C$26*$C$27*$C$28,0) -> 23317.2 | L76: =L54*$D54*$C$13*INDEX(Assumptions!$B$44:$B$46,MATCH($C54,Assumptions!$A$44:$A$46,0))+IF(L$45>=$G54,INDEX(Assumptions!$C$44:$C$46,MATCH($C54,Assumptions!$A$44:$A$46,0)),0)+IF($C54="Assured",L54*$D54*$C$13*$C$26*$C$27*$C$28,0) -> 46634.4 | M76: =M54*$D54*$C$13*INDEX(Assumptions!$B$44:$B$46,MATCH($C54,Assumptions!$A$44:$A$46,0))+IF(M$45>=$G54,INDEX(Assumptions!$C$44:$C$46,MATCH($C54,Assumptions!$A$44:$A$46,0)),0)+IF($C54="Assured",M54*$D54*$C$13*$C$26*$C$27*$C$28,0) -> 66065.4 | N76: =N54*$D54*$C$13*INDEX(Assumptions!$B$44:$B$46,MATCH($C54,Assumptions!$A$44:$A$46,0))+IF(N$45>=$G54,INDEX(Assumptions!$C$44:$C$46,MATCH($C54,Assumptions!$A$44:$A$46,0)),0)+IF($C54="Assured",N54*$D54*$C$13*$C$26*$C$27*$C$28,0) -> 77724 | O76: =O54*$D54*$C$13*INDEX(Assumptions!$B$44:$B$46,MATCH($C54,Assumptions!$A$44:$A$46,0))+IF(O$45>=$G54,INDEX(Assumptions!$C$44:$C$46,MATCH($C54,Assumptions!$A$44:$A$46,0)),0)+IF($C54="Assured",O54*$D54*$C$13*$C$26*$C$27*$C$28,0) -> 77724 | ... Y76: =Y54*$D54*$C$13*INDEX(Assumptions!$B$44:$B$46,MATCH($C54,Assumptions!$A$44:$A$46,0))+IF(Y$45>=$G54,INDEX(Assumptions!$C$44:$C$46,MATCH($C54,Assumptions!$A$44:$A$46,0)),0)+IF($C54="Assured",Y54*$D54*$C$13*$C$26*$C$27*$C$28,0) -> 77724
A77: =A55 -> 8 | B77: =B55 -> A | C77: =C55 -> Assured | H77: =H55*$D55*$C$13*INDEX(Assumptions!$B$44:$B$46,MATCH($C55,Assumptions!$A$44:$A$46,0))+IF(H$45>=$G55,INDEX(Assumptions!$C$44:$C$46,MATCH($C55,Assumptions!$A$44:$A$46,0)),0)+IF($C55="Assured",H55*$D55*$C$13*$C$26*$C$27*$C$28,0) -> 0 | I77: =I55*$D55*$C$13*INDEX(Assumptions!$B$44:$B$46,MATCH($C55,Assumptions!$A$44:$A$46,0))+IF(I$45>=$G55,INDEX(Assumptions!$C$44:$C$46,MATCH($C55,Assumptions!$A$44:$A$46,0)),0)+IF($C55="Assured",I55*$D55*$C$13*$C$26*$C$27*$C$28,0) -> 0 | J77: =J55*$D55*$C$13*INDEX(Assumptions!$B$44:$B$46,MATCH($C55,Assumptions!$A$44:$A$46,0))+IF(J$45>=$G55,INDEX(Assumptions!$C$44:$C$46,MATCH($C55,Assumptions!$A$44:$A$46,0)),0)+IF($C55="Assured",J55*$D55*$C$13*$C$26*$C$27*$C$28,0) -> 0 | K77: =K55*$D55*$C$13*INDEX(Assumptions!$B$44:$B$46,MATCH($C55,Assumptions!$A$44:$A$46,0))+IF(K$45>=$G55,INDEX(Assumptions!$C$44:$C$46,MATCH($C55,Assumptions!$A$44:$A$46,0)),0)+IF($C55="Assured",K55*$D55*$C$13*$C$26*$C$27*$C$28,0) -> 23317.2 | L77: =L55*$D55*$C$13*INDEX(Assumptions!$B$44:$B$46,MATCH($C55,Assumptions!$A$44:$A$46,0))+IF(L$45>=$G55,INDEX(Assumptions!$C$44:$C$46,MATCH($C55,Assumptions!$A$44:$A$46,0)),0)+IF($C55="Assured",L55*$D55*$C$13*$C$26*$C$27*$C$28,0) -> 46634.4 | M77: =M55*$D55*$C$13*INDEX(Assumptions!$B$44:$B$46,MATCH($C55,Assumptions!$A$44:$A$46,0))+IF(M$45>=$G55,INDEX(Assumptions!$C$44:$C$46,MATCH($C55,Assumptions!$A$44:$A$46,0)),0)+IF($C55="Assured",M55*$D55*$C$13*$C$26*$C$27*$C$28,0) -> 66065.4 | N77: =N55*$D55*$C$13*INDEX(Assumptions!$B$44:$B$46,MATCH($C55,Assumptions!$A$44:$A$46,0))+IF(N$45>=$G55,INDEX(Assumptions!$C$44:$C$46,MATCH($C55,Assumptions!$A$44:$A$46,0)),0)+IF($C55="Assured",N55*$D55*$C$13*$C$26*$C$27*$C$28,0) -> 77724 | O77: =O55*$D55*$C$13*INDEX(Assumptions!$B$44:$B$46,MATCH($C55,Assumptions!$A$44:$A$46,0))+IF(O$45>=$G55,INDEX(Assumptions!$C$44:$C$46,MATCH($C55,Assumptions!$A$44:$A$46,0)),0)+IF($C55="Assured",O55*$D55*$C$13*$C$26*$C$27*$C$28,0) -> 77724 | ... Y77: =Y55*$D55*$C$13*INDEX(Assumptions!$B$44:$B$46,MATCH($C55,Assumptions!$A$44:$A$46,0))+IF(Y$45>=$G55,INDEX(Assumptions!$C$44:$C$46,MATCH($C55,Assumptions!$A$44:$A$46,0)),0)+IF($C55="Assured",Y55*$D55*$C$13*$C$26*$C$27*$C$28,0) -> 77724
A78: =A56 -> 9 | B78: =B56 -> A | C78: =C56 -> Assured | H78: =H56*$D56*$C$13*INDEX(Assumptions!$B$44:$B$46,MATCH($C56,Assumptions!$A$44:$A$46,0))+IF(H$45>=$G56,INDEX(Assumptions!$C$44:$C$46,MATCH($C56,Assumptions!$A$44:$A$46,0)),0)+IF($C56="Assured",H56*$D56*$C$13*$C$26*$C$27*$C$28,0) -> 0 | I78: =I56*$D56*$C$13*INDEX(Assumptions!$B$44:$B$46,MATCH($C56,Assumptions!$A$44:$A$46,0))+IF(I$45>=$G56,INDEX(Assumptions!$C$44:$C$46,MATCH($C56,Assumptions!$A$44:$A$46,0)),0)+IF($C56="Assured",I56*$D56*$C$13*$C$26*$C$27*$C$28,0) -> 0 | J78: =J56*$D56*$C$13*INDEX(Assumptions!$B$44:$B$46,MATCH($C56,Assumptions!$A$44:$A$46,0))+IF(J$45>=$G56,INDEX(Assumptions!$C$44:$C$46,MATCH($C56,Assumptions!$A$44:$A$46,0)),0)+IF($C56="Assured",J56*$D56*$C$13*$C$26*$C$27*$C$28,0) -> 0 | K78: =K56*$D56*$C$13*INDEX(Assumptions!$B$44:$B$46,MATCH($C56,Assumptions!$A$44:$A$46,0))+IF(K$45>=$G56,INDEX(Assumptions!$C$44:$C$46,MATCH($C56,Assumptions!$A$44:$A$46,0)),0)+IF($C56="Assured",K56*$D56*$C$13*$C$26*$C$27*$C$28,0) -> 0 | L78: =L56*$D56*$C$13*INDEX(Assumptions!$B$44:$B$46,MATCH($C56,Assumptions!$A$44:$A$46,0))+IF(L$45>=$G56,INDEX(Assumptions!$C$44:$C$46,MATCH($C56,Assumptions!$A$44:$A$46,0)),0)+IF($C56="Assured",L56*$D56*$C$13*$C$26*$C$27*$C$28,0) -> 23317.2 | M78: =M56*$D56*$C$13*INDEX(Assumptions!$B$44:$B$46,MATCH($C56,Assumptions!$A$44:$A$46,0))+IF(M$45>=$G56,INDEX(Assumptions!$C$44:$C$46,MATCH($C56,Assumptions!$A$44:$A$46,0)),0)+IF($C56="Assured",M56*$D56*$C$13*$C$26*$C$27*$C$28,0) -> 46634.4 | N78: =N56*$D56*$C$13*INDEX(Assumptions!$B$44:$B$46,MATCH($C56,Assumptions!$A$44:$A$46,0))+IF(N$45>=$G56,INDEX(Assumptions!$C$44:$C$46,MATCH($C56,Assumptions!$A$44:$A$46,0)),0)+IF($C56="Assured",N56*$D56*$C$13*$C$26*$C$27*$C$28,0) -> 66065.4 | O78: =O56*$D56*$C$13*INDEX(Assumptions!$B$44:$B$46,MATCH($C56,Assumptions!$A$44:$A$46,0))+IF(O$45>=$G56,INDEX(Assumptions!$C$44:$C$46,MATCH($C56,Assumptions!$A$44:$A$46,0)),0)+IF($C56="Assured",O56*$D56*$C$13*$C$26*$C$27*$C$28,0) -> 77724 | ... Y78: =Y56*$D56*$C$13*INDEX(Assumptions!$B$44:$B$46,MATCH($C56,Assumptions!$A$44:$A$46,0))+IF(Y$45>=$G56,INDEX(Assumptions!$C$44:$C$46,MATCH($C56,Assumptions!$A$44:$A$46,0)),0)+IF($C56="Assured",Y56*$D56*$C$13*$C$26*$C$27*$C$28,0) -> 77724
A79: =A57 -> 10 | B79: =B57 -> C | C79: =C57 -> Assured | H79: =H57*$D57*$C$13*INDEX(Assumptions!$B$44:$B$46,MATCH($C57,Assumptions!$A$44:$A$46,0))+IF(H$45>=$G57,INDEX(Assumptions!$C$44:$C$46,MATCH($C57,Assumptions!$A$44:$A$46,0)),0)+IF($C57="Assured",H57*$D57*$C$13*$C$26*$C$27*$C$28,0) -> 0 | I79: =I57*$D57*$C$13*INDEX(Assumptions!$B$44:$B$46,MATCH($C57,Assumptions!$A$44:$A$46,0))+IF(I$45>=$G57,INDEX(Assumptions!$C$44:$C$46,MATCH($C57,Assumptions!$A$44:$A$46,0)),0)+IF($C57="Assured",I57*$D57*$C$13*$C$26*$C$27*$C$28,0) -> 0 | J79: =J57*$D57*$C$13*INDEX(Assumptions!$B$44:$B$46,MATCH($C57,Assumptions!$A$44:$A$46,0))+IF(J$45>=$G57,INDEX(Assumptions!$C$44:$C$46,MATCH($C57,Assumptions!$A$44:$A$46,0)),0)+IF($C57="Assured",J57*$D57*$C$13*$C$26*$C$27*$C$28,0) -> 0 | K79: =K57*$D57*$C$13*INDEX(Assumptions!$B$44:$B$46,MATCH($C57,Assumptions!$A$44:$A$46,0))+IF(K$45>=$G57,INDEX(Assumptions!$C$44:$C$46,MATCH($C57,Assumptions!$A$44:$A$46,0)),0)+IF($C57="Assured",K57*$D57*$C$13*$C$26*$C$27*$C$28,0) -> 0 | L79: =L57*$D57*$C$13*INDEX(Assumptions!$B$44:$B$46,MATCH($C57,Assumptions!$A$44:$A$46,0))+IF(L$45>=$G57,INDEX(Assumptions!$C$44:$C$46,MATCH($C57,Assumptions!$A$44:$A$46,0)),0)+IF($C57="Assured",L57*$D57*$C$13*$C$26*$C$27*$C$28,0) -> 0 | M79: =M57*$D57*$C$13*INDEX(Assumptions!$B$44:$B$46,MATCH($C57,Assumptions!$A$44:$A$46,0))+IF(M$45>=$G57,INDEX(Assumptions!$C$44:$C$46,MATCH($C57,Assumptions!$A$44:$A$46,0)),0)+IF($C57="Assured",M57*$D57*$C$13*$C$26*$C$27*$C$28,0) -> 16840.2 | N79: =N57*$D57*$C$13*INDEX(Assumptions!$B$44:$B$46,MATCH($C57,Assumptions!$A$44:$A$46,0))+IF(N$45>=$G57,INDEX(Assumptions!$C$44:$C$46,MATCH($C57,Assumptions!$A$44:$A$46,0)),0)+IF($C57="Assured",N57*$D57*$C$13*$C$26*$C$27*$C$28,0) -> 33680.4 | O79: =O57*$D57*$C$13*INDEX(Assumptions!$B$44:$B$46,MATCH($C57,Assumptions!$A$44:$A$46,0))+IF(O$45>=$G57,INDEX(Assumptions!$C$44:$C$46,MATCH($C57,Assumptions!$A$44:$A$46,0)),0)+IF($C57="Assured",O57*$D57*$C$13*$C$26*$C$27*$C$28,0) -> 47713.9 | ... Y79: =Y57*$D57*$C$13*INDEX(Assumptions!$B$44:$B$46,MATCH($C57,Assumptions!$A$44:$A$46,0))+IF(Y$45>=$G57,INDEX(Assumptions!$C$44:$C$46,MATCH($C57,Assumptions!$A$44:$A$46,0)),0)+IF($C57="Assured",Y57*$D57*$C$13*$C$26*$C$27*$C$28,0) -> 56134
A80: =A58 -> 11 | B80: =B58 -> C | C80: =C58 -> Assured | H80: =H58*$D58*$C$13*INDEX(Assumptions!$B$44:$B$46,MATCH($C58,Assumptions!$A$44:$A$46,0))+IF(H$45>=$G58,INDEX(Assumptions!$C$44:$C$46,MATCH($C58,Assumptions!$A$44:$A$46,0)),0)+IF($C58="Assured",H58*$D58*$C$13*$C$26*$C$27*$C$28,0) -> 0 | I80: =I58*$D58*$C$13*INDEX(Assumptions!$B$44:$B$46,MATCH($C58,Assumptions!$A$44:$A$46,0))+IF(I$45>=$G58,INDEX(Assumptions!$C$44:$C$46,MATCH($C58,Assumptions!$A$44:$A$46,0)),0)+IF($C58="Assured",I58*$D58*$C$13*$C$26*$C$27*$C$28,0) -> 0 | J80: =J58*$D58*$C$13*INDEX(Assumptions!$B$44:$B$46,MATCH($C58,Assumptions!$A$44:$A$46,0))+IF(J$45>=$G58,INDEX(Assumptions!$C$44:$C$46,MATCH($C58,Assumptions!$A$44:$A$46,0)),0)+IF($C58="Assured",J58*$D58*$C$13*$C$26*$C$27*$C$28,0) -> 0 | K80: =K58*$D58*$C$13*INDEX(Assumptions!$B$44:$B$46,MATCH($C58,Assumptions!$A$44:$A$46,0))+IF(K$45>=$G58,INDEX(Assumptions!$C$44:$C$46,MATCH($C58,Assumptions!$A$44:$A$46,0)),0)+IF($C58="Assured",K58*$D58*$C$13*$C$26*$C$27*$C$28,0) -> 0 | L80: =L58*$D58*$C$13*INDEX(Assumptions!$B$44:$B$46,MATCH($C58,Assumptions!$A$44:$A$46,0))+IF(L$45>=$G58,INDEX(Assumptions!$C$44:$C$46,MATCH($C58,Assumptions!$A$44:$A$46,0)),0)+IF($C58="Assured",L58*$D58*$C$13*$C$26*$C$27*$C$28,0) -> 0 | M80: =M58*$D58*$C$13*INDEX(Assumptions!$B$44:$B$46,MATCH($C58,Assumptions!$A$44:$A$46,0))+IF(M$45>=$G58,INDEX(Assumptions!$C$44:$C$46,MATCH($C58,Assumptions!$A$44:$A$46,0)),0)+IF($C58="Assured",M58*$D58*$C$13*$C$26*$C$27*$C$28,0) -> 0 | N80: =N58*$D58*$C$13*INDEX(Assumptions!$B$44:$B$46,MATCH($C58,Assumptions!$A$44:$A$46,0))+IF(N$45>=$G58,INDEX(Assumptions!$C$44:$C$46,MATCH($C58,Assumptions!$A$44:$A$46,0)),0)+IF($C58="Assured",N58*$D58*$C$13*$C$26*$C$27*$C$28,0) -> 16840.2 | O80: =O58*$D58*$C$13*INDEX(Assumptions!$B$44:$B$46,MATCH($C58,Assumptions!$A$44:$A$46,0))+IF(O$45>=$G58,INDEX(Assumptions!$C$44:$C$46,MATCH($C58,Assumptions!$A$44:$A$46,0)),0)+IF($C58="Assured",O58*$D58*$C$13*$C$26*$C$27*$C$28,0) -> 33680.4 | ... Y80: =Y58*$D58*$C$13*INDEX(Assumptions!$B$44:$B$46,MATCH($C58,Assumptions!$A$44:$A$46,0))+IF(Y$45>=$G58,INDEX(Assumptions!$C$44:$C$46,MATCH($C58,Assumptions!$A$44:$A$46,0)),0)+IF($C58="Assured",Y58*$D58*$C$13*$C$26*$C$27*$C$28,0) -> 56134
A81: =A59 -> 12 | B81: =B59 -> C | C81: =C59 -> Assured | H81: =H59*$D59*$C$13*INDEX(Assumptions!$B$44:$B$46,MATCH($C59,Assumptions!$A$44:$A$46,0))+IF(H$45>=$G59,INDEX(Assumptions!$C$44:$C$46,MATCH($C59,Assumptions!$A$44:$A$46,0)),0)+IF($C59="Assured",H59*$D59*$C$13*$C$26*$C$27*$C$28,0) -> 0 | I81: =I59*$D59*$C$13*INDEX(Assumptions!$B$44:$B$46,MATCH($C59,Assumptions!$A$44:$A$46,0))+IF(I$45>=$G59,INDEX(Assumptions!$C$44:$C$46,MATCH($C59,Assumptions!$A$44:$A$46,0)),0)+IF($C59="Assured",I59*$D59*$C$13*$C$26*$C$27*$C$28,0) -> 0 | J81: =J59*$D59*$C$13*INDEX(Assumptions!$B$44:$B$46,MATCH($C59,Assumptions!$A$44:$A$46,0))+IF(J$45>=$G59,INDEX(Assumptions!$C$44:$C$46,MATCH($C59,Assumptions!$A$44:$A$46,0)),0)+IF($C59="Assured",J59*$D59*$C$13*$C$26*$C$27*$C$28,0) -> 0 | K81: =K59*$D59*$C$13*INDEX(Assumptions!$B$44:$B$46,MATCH($C59,Assumptions!$A$44:$A$46,0))+IF(K$45>=$G59,INDEX(Assumptions!$C$44:$C$46,MATCH($C59,Assumptions!$A$44:$A$46,0)),0)+IF($C59="Assured",K59*$D59*$C$13*$C$26*$C$27*$C$28,0) -> 0 | L81: =L59*$D59*$C$13*INDEX(Assumptions!$B$44:$B$46,MATCH($C59,Assumptions!$A$44:$A$46,0))+IF(L$45>=$G59,INDEX(Assumptions!$C$44:$C$46,MATCH($C59,Assumptions!$A$44:$A$46,0)),0)+IF($C59="Assured",L59*$D59*$C$13*$C$26*$C$27*$C$28,0) -> 0 | M81: =M59*$D59*$C$13*INDEX(Assumptions!$B$44:$B$46,MATCH($C59,Assumptions!$A$44:$A$46,0))+IF(M$45>=$G59,INDEX(Assumptions!$C$44:$C$46,MATCH($C59,Assumptions!$A$44:$A$46,0)),0)+IF($C59="Assured",M59*$D59*$C$13*$C$26*$C$27*$C$28,0) -> 0 | N81: =N59*$D59*$C$13*INDEX(Assumptions!$B$44:$B$46,MATCH($C59,Assumptions!$A$44:$A$46,0))+IF(N$45>=$G59,INDEX(Assumptions!$C$44:$C$46,MATCH($C59,Assumptions!$A$44:$A$46,0)),0)+IF($C59="Assured",N59*$D59*$C$13*$C$26*$C$27*$C$28,0) -> 16840.2 | O81: =O59*$D59*$C$13*INDEX(Assumptions!$B$44:$B$46,MATCH($C59,Assumptions!$A$44:$A$46,0))+IF(O$45>=$G59,INDEX(Assumptions!$C$44:$C$46,MATCH($C59,Assumptions!$A$44:$A$46,0)),0)+IF($C59="Assured",O59*$D59*$C$13*$C$26*$C$27*$C$28,0) -> 33680.4 | ... Y81: =Y59*$D59*$C$13*INDEX(Assumptions!$B$44:$B$46,MATCH($C59,Assumptions!$A$44:$A$46,0))+IF(Y$45>=$G59,INDEX(Assumptions!$C$44:$C$46,MATCH($C59,Assumptions!$A$44:$A$46,0)),0)+IF($C59="Assured",Y59*$D59*$C$13*$C$26*$C$27*$C$28,0) -> 56134
... A89: =A67 -> 20 | B89: =B67 -> B | C89: =C67 -> Verified | H89: =H67*$D67*$C$13*INDEX(Assumptions!$B$44:$B$46,MATCH($C67,Assumptions!$A$44:$A$46,0))+IF(H$45>=$G67,INDEX(Assumptions!$C$44:$C$46,MATCH($C67,Assumptions!$A$44:$A$46,0)),0)+IF($C67="Assured",H67*$D67*$C$13*$C$26*$C$27*$C$28,0) -> 0 | I89: =I67*$D67*$C$13*INDEX(Assumptions!$B$44:$B$46,MATCH($C67,Assumptions!$A$44:$A$46,0))+IF(I$45>=$G67,INDEX(Assumptions!$C$44:$C$46,MATCH($C67,Assumptions!$A$44:$A$46,0)),0)+IF($C67="Assured",I67*$D67*$C$13*$C$26*$C$27*$C$28,0) -> 0 | J89: =J67*$D67*$C$13*INDEX(Assumptions!$B$44:$B$46,MATCH($C67,Assumptions!$A$44:$A$46,0))+IF(J$45>=$G67,INDEX(Assumptions!$C$44:$C$46,MATCH($C67,Assumptions!$A$44:$A$46,0)),0)+IF($C67="Assured",J67*$D67*$C$13*$C$26*$C$27*$C$28,0) -> 0 | K89: =K67*$D67*$C$13*INDEX(Assumptions!$B$44:$B$46,MATCH($C67,Assumptions!$A$44:$A$46,0))+IF(K$45>=$G67,INDEX(Assumptions!$C$44:$C$46,MATCH($C67,Assumptions!$A$44:$A$46,0)),0)+IF($C67="Assured",K67*$D67*$C$13*$C$26*$C$27*$C$28,0) -> 0 | L89: =L67*$D67*$C$13*INDEX(Assumptions!$B$44:$B$46,MATCH($C67,Assumptions!$A$44:$A$46,0))+IF(L$45>=$G67,INDEX(Assumptions!$C$44:$C$46,MATCH($C67,Assumptions!$A$44:$A$46,0)),0)+IF($C67="Assured",L67*$D67*$C$13*$C$26*$C$27*$C$28,0) -> 0 | M89: =M67*$D67*$C$13*INDEX(Assumptions!$B$44:$B$46,MATCH($C67,Assumptions!$A$44:$A$46,0))+IF(M$45>=$G67,INDEX(Assumptions!$C$44:$C$46,MATCH($C67,Assumptions!$A$44:$A$46,0)),0)+IF($C67="Assured",M67*$D67*$C$13*$C$26*$C$27*$C$28,0) -> 0 | N89: =N67*$D67*$C$13*INDEX(Assumptions!$B$44:$B$46,MATCH($C67,Assumptions!$A$44:$A$46,0))+IF(N$45>=$G67,INDEX(Assumptions!$C$44:$C$46,MATCH($C67,Assumptions!$A$44:$A$46,0)),0)+IF($C67="Assured",N67*$D67*$C$13*$C$26*$C$27*$C$28,0) -> 0 | O89: =O67*$D67*$C$13*INDEX(Assumptions!$B$44:$B$46,MATCH($C67,Assumptions!$A$44:$A$46,0))+IF(O$45>=$G67,INDEX(Assumptions!$C$44:$C$46,MATCH($C67,Assumptions!$A$44:$A$46,0)),0)+IF($C67="Assured",O67*$D67*$C$13*$C$26*$C$27*$C$28,0) -> 0 | ... Y89: =Y67*$D67*$C$13*INDEX(Assumptions!$B$44:$B$46,MATCH($C67,Assumptions!$A$44:$A$46,0))+IF(Y$45>=$G67,INDEX(Assumptions!$C$44:$C$46,MATCH($C67,Assumptions!$A$44:$A$46,0)),0)+IF($C67="Assured",Y67*$D67*$C$13*$C$26*$C$27*$C$28,0) -> 29835
A91: Variable cost per host (₹)
A92: =A48 -> 1 | B92: =B48 -> Pilot | C92: =C48 -> Assured | H92: =H48*IF(AND($C48="Assured",H$45>=$C$25),$C$24,INDEX(Assumptions!$D$44:$D$46,MATCH($C48,Assumptions!$A$44:$A$46,0))) -> 23625 | I92: =I48*IF(AND($C48="Assured",I$45>=$C$25),$C$24,INDEX(Assumptions!$D$44:$D$46,MATCH($C48,Assumptions!$A$44:$A$46,0))) -> 24750 | J92: =J48*IF(AND($C48="Assured",J$45>=$C$25),$C$24,INDEX(Assumptions!$D$44:$D$46,MATCH($C48,Assumptions!$A$44:$A$46,0))) -> 25875 | K92: =K48*IF(AND($C48="Assured",K$45>=$C$25),$C$24,INDEX(Assumptions!$D$44:$D$46,MATCH($C48,Assumptions!$A$44:$A$46,0))) -> 27000 | L92: =L48*IF(AND($C48="Assured",L$45>=$C$25),$C$24,INDEX(Assumptions!$D$44:$D$46,MATCH($C48,Assumptions!$A$44:$A$46,0))) -> 27000 | M92: =M48*IF(AND($C48="Assured",M$45>=$C$25),$C$24,INDEX(Assumptions!$D$44:$D$46,MATCH($C48,Assumptions!$A$44:$A$46,0))) -> 27000 | N92: =N48*IF(AND($C48="Assured",N$45>=$C$25),$C$24,INDEX(Assumptions!$D$44:$D$46,MATCH($C48,Assumptions!$A$44:$A$46,0))) -> 27000 | O92: =O48*IF(AND($C48="Assured",O$45>=$C$25),$C$24,INDEX(Assumptions!$D$44:$D$46,MATCH($C48,Assumptions!$A$44:$A$46,0))) -> 27000 | ... Y92: =Y48*IF(AND($C48="Assured",Y$45>=$C$25),$C$24,INDEX(Assumptions!$D$44:$D$46,MATCH($C48,Assumptions!$A$44:$A$46,0))) -> 24000
A93: =A49 -> 2 | B93: =B49 -> Pilot | C93: =C49 -> Assured | H93: =H49*IF(AND($C49="Assured",H$45>=$C$25),$C$24,INDEX(Assumptions!$D$44:$D$46,MATCH($C49,Assumptions!$A$44:$A$46,0))) -> 23625 | I93: =I49*IF(AND($C49="Assured",I$45>=$C$25),$C$24,INDEX(Assumptions!$D$44:$D$46,MATCH($C49,Assumptions!$A$44:$A$46,0))) -> 24750 | J93: =J49*IF(AND($C49="Assured",J$45>=$C$25),$C$24,INDEX(Assumptions!$D$44:$D$46,MATCH($C49,Assumptions!$A$44:$A$46,0))) -> 25875 | K93: =K49*IF(AND($C49="Assured",K$45>=$C$25),$C$24,INDEX(Assumptions!$D$44:$D$46,MATCH($C49,Assumptions!$A$44:$A$46,0))) -> 27000 | L93: =L49*IF(AND($C49="Assured",L$45>=$C$25),$C$24,INDEX(Assumptions!$D$44:$D$46,MATCH($C49,Assumptions!$A$44:$A$46,0))) -> 27000 | M93: =M49*IF(AND($C49="Assured",M$45>=$C$25),$C$24,INDEX(Assumptions!$D$44:$D$46,MATCH($C49,Assumptions!$A$44:$A$46,0))) -> 27000 | N93: =N49*IF(AND($C49="Assured",N$45>=$C$25),$C$24,INDEX(Assumptions!$D$44:$D$46,MATCH($C49,Assumptions!$A$44:$A$46,0))) -> 27000 | O93: =O49*IF(AND($C49="Assured",O$45>=$C$25),$C$24,INDEX(Assumptions!$D$44:$D$46,MATCH($C49,Assumptions!$A$44:$A$46,0))) -> 27000 | ... Y93: =Y49*IF(AND($C49="Assured",Y$45>=$C$25),$C$24,INDEX(Assumptions!$D$44:$D$46,MATCH($C49,Assumptions!$A$44:$A$46,0))) -> 24000
A94: =A50 -> 3 | B94: =B50 -> Pilot | C94: =C50 -> Assured | H94: =H50*IF(AND($C50="Assured",H$45>=$C$25),$C$24,INDEX(Assumptions!$D$44:$D$46,MATCH($C50,Assumptions!$A$44:$A$46,0))) -> 23625 | I94: =I50*IF(AND($C50="Assured",I$45>=$C$25),$C$24,INDEX(Assumptions!$D$44:$D$46,MATCH($C50,Assumptions!$A$44:$A$46,0))) -> 24750 | J94: =J50*IF(AND($C50="Assured",J$45>=$C$25),$C$24,INDEX(Assumptions!$D$44:$D$46,MATCH($C50,Assumptions!$A$44:$A$46,0))) -> 25875 | K94: =K50*IF(AND($C50="Assured",K$45>=$C$25),$C$24,INDEX(Assumptions!$D$44:$D$46,MATCH($C50,Assumptions!$A$44:$A$46,0))) -> 27000 | L94: =L50*IF(AND($C50="Assured",L$45>=$C$25),$C$24,INDEX(Assumptions!$D$44:$D$46,MATCH($C50,Assumptions!$A$44:$A$46,0))) -> 27000 | M94: =M50*IF(AND($C50="Assured",M$45>=$C$25),$C$24,INDEX(Assumptions!$D$44:$D$46,MATCH($C50,Assumptions!$A$44:$A$46,0))) -> 27000 | N94: =N50*IF(AND($C50="Assured",N$45>=$C$25),$C$24,INDEX(Assumptions!$D$44:$D$46,MATCH($C50,Assumptions!$A$44:$A$46,0))) -> 27000 | O94: =O50*IF(AND($C50="Assured",O$45>=$C$25),$C$24,INDEX(Assumptions!$D$44:$D$46,MATCH($C50,Assumptions!$A$44:$A$46,0))) -> 27000 | ... Y94: =Y50*IF(AND($C50="Assured",Y$45>=$C$25),$C$24,INDEX(Assumptions!$D$44:$D$46,MATCH($C50,Assumptions!$A$44:$A$46,0))) -> 24000
A95: =A51 -> 4 | B95: =B51 -> Pilot | C95: =C51 -> Assured | H95: =H51*IF(AND($C51="Assured",H$45>=$C$25),$C$24,INDEX(Assumptions!$D$44:$D$46,MATCH($C51,Assumptions!$A$44:$A$46,0))) -> 23625 | I95: =I51*IF(AND($C51="Assured",I$45>=$C$25),$C$24,INDEX(Assumptions!$D$44:$D$46,MATCH($C51,Assumptions!$A$44:$A$46,0))) -> 24750 | J95: =J51*IF(AND($C51="Assured",J$45>=$C$25),$C$24,INDEX(Assumptions!$D$44:$D$46,MATCH($C51,Assumptions!$A$44:$A$46,0))) -> 25875 | K95: =K51*IF(AND($C51="Assured",K$45>=$C$25),$C$24,INDEX(Assumptions!$D$44:$D$46,MATCH($C51,Assumptions!$A$44:$A$46,0))) -> 27000 | L95: =L51*IF(AND($C51="Assured",L$45>=$C$25),$C$24,INDEX(Assumptions!$D$44:$D$46,MATCH($C51,Assumptions!$A$44:$A$46,0))) -> 27000 | M95: =M51*IF(AND($C51="Assured",M$45>=$C$25),$C$24,INDEX(Assumptions!$D$44:$D$46,MATCH($C51,Assumptions!$A$44:$A$46,0))) -> 27000 | N95: =N51*IF(AND($C51="Assured",N$45>=$C$25),$C$24,INDEX(Assumptions!$D$44:$D$46,MATCH($C51,Assumptions!$A$44:$A$46,0))) -> 27000 | O95: =O51*IF(AND($C51="Assured",O$45>=$C$25),$C$24,INDEX(Assumptions!$D$44:$D$46,MATCH($C51,Assumptions!$A$44:$A$46,0))) -> 27000 | ... Y95: =Y51*IF(AND($C51="Assured",Y$45>=$C$25),$C$24,INDEX(Assumptions!$D$44:$D$46,MATCH($C51,Assumptions!$A$44:$A$46,0))) -> 24000
A96: =A52 -> 5 | B96: =B52 -> A | C96: =C52 -> Assured | H96: =H52*IF(AND($C52="Assured",H$45>=$C$25),$C$24,INDEX(Assumptions!$D$44:$D$46,MATCH($C52,Assumptions!$A$44:$A$46,0))) -> 0 | I96: =I52*IF(AND($C52="Assured",I$45>=$C$25),$C$24,INDEX(Assumptions!$D$44:$D$46,MATCH($C52,Assumptions!$A$44:$A$46,0))) -> 0 | J96: =J52*IF(AND($C52="Assured",J$45>=$C$25),$C$24,INDEX(Assumptions!$D$44:$D$46,MATCH($C52,Assumptions!$A$44:$A$46,0))) -> 8262 | K96: =K52*IF(AND($C52="Assured",K$45>=$C$25),$C$24,INDEX(Assumptions!$D$44:$D$46,MATCH($C52,Assumptions!$A$44:$A$46,0))) -> 16524 | L96: =L52*IF(AND($C52="Assured",L$45>=$C$25),$C$24,INDEX(Assumptions!$D$44:$D$46,MATCH($C52,Assumptions!$A$44:$A$46,0))) -> 23409 | M96: =M52*IF(AND($C52="Assured",M$45>=$C$25),$C$24,INDEX(Assumptions!$D$44:$D$46,MATCH($C52,Assumptions!$A$44:$A$46,0))) -> 27540 | N96: =N52*IF(AND($C52="Assured",N$45>=$C$25),$C$24,INDEX(Assumptions!$D$44:$D$46,MATCH($C52,Assumptions!$A$44:$A$46,0))) -> 27540 | O96: =O52*IF(AND($C52="Assured",O$45>=$C$25),$C$24,INDEX(Assumptions!$D$44:$D$46,MATCH($C52,Assumptions!$A$44:$A$46,0))) -> 27540 | ... Y96: =Y52*IF(AND($C52="Assured",Y$45>=$C$25),$C$24,INDEX(Assumptions!$D$44:$D$46,MATCH($C52,Assumptions!$A$44:$A$46,0))) -> 24480
A97: =A53 -> 6 | B97: =B53 -> A | C97: =C53 -> Assured | H97: =H53*IF(AND($C53="Assured",H$45>=$C$25),$C$24,INDEX(Assumptions!$D$44:$D$46,MATCH($C53,Assumptions!$A$44:$A$46,0))) -> 0 | I97: =I53*IF(AND($C53="Assured",I$45>=$C$25),$C$24,INDEX(Assumptions!$D$44:$D$46,MATCH($C53,Assumptions!$A$44:$A$46,0))) -> 0 | J97: =J53*IF(AND($C53="Assured",J$45>=$C$25),$C$24,INDEX(Assumptions!$D$44:$D$46,MATCH($C53,Assumptions!$A$44:$A$46,0))) -> 8262 | K97: =K53*IF(AND($C53="Assured",K$45>=$C$25),$C$24,INDEX(Assumptions!$D$44:$D$46,MATCH($C53,Assumptions!$A$44:$A$46,0))) -> 16524 | L97: =L53*IF(AND($C53="Assured",L$45>=$C$25),$C$24,INDEX(Assumptions!$D$44:$D$46,MATCH($C53,Assumptions!$A$44:$A$46,0))) -> 23409 | M97: =M53*IF(AND($C53="Assured",M$45>=$C$25),$C$24,INDEX(Assumptions!$D$44:$D$46,MATCH($C53,Assumptions!$A$44:$A$46,0))) -> 27540 | N97: =N53*IF(AND($C53="Assured",N$45>=$C$25),$C$24,INDEX(Assumptions!$D$44:$D$46,MATCH($C53,Assumptions!$A$44:$A$46,0))) -> 27540 | O97: =O53*IF(AND($C53="Assured",O$45>=$C$25),$C$24,INDEX(Assumptions!$D$44:$D$46,MATCH($C53,Assumptions!$A$44:$A$46,0))) -> 27540 | ... Y97: =Y53*IF(AND($C53="Assured",Y$45>=$C$25),$C$24,INDEX(Assumptions!$D$44:$D$46,MATCH($C53,Assumptions!$A$44:$A$46,0))) -> 24480
A98: =A54 -> 7 | B98: =B54 -> A | C98: =C54 -> Assured | H98: =H54*IF(AND($C54="Assured",H$45>=$C$25),$C$24,INDEX(Assumptions!$D$44:$D$46,MATCH($C54,Assumptions!$A$44:$A$46,0))) -> 0 | I98: =I54*IF(AND($C54="Assured",I$45>=$C$25),$C$24,INDEX(Assumptions!$D$44:$D$46,MATCH($C54,Assumptions!$A$44:$A$46,0))) -> 0 | J98: =J54*IF(AND($C54="Assured",J$45>=$C$25),$C$24,INDEX(Assumptions!$D$44:$D$46,MATCH($C54,Assumptions!$A$44:$A$46,0))) -> 0 | K98: =K54*IF(AND($C54="Assured",K$45>=$C$25),$C$24,INDEX(Assumptions!$D$44:$D$46,MATCH($C54,Assumptions!$A$44:$A$46,0))) -> 8262 | L98: =L54*IF(AND($C54="Assured",L$45>=$C$25),$C$24,INDEX(Assumptions!$D$44:$D$46,MATCH($C54,Assumptions!$A$44:$A$46,0))) -> 16524 | M98: =M54*IF(AND($C54="Assured",M$45>=$C$25),$C$24,INDEX(Assumptions!$D$44:$D$46,MATCH($C54,Assumptions!$A$44:$A$46,0))) -> 23409 | N98: =N54*IF(AND($C54="Assured",N$45>=$C$25),$C$24,INDEX(Assumptions!$D$44:$D$46,MATCH($C54,Assumptions!$A$44:$A$46,0))) -> 27540 | O98: =O54*IF(AND($C54="Assured",O$45>=$C$25),$C$24,INDEX(Assumptions!$D$44:$D$46,MATCH($C54,Assumptions!$A$44:$A$46,0))) -> 27540 | ... Y98: =Y54*IF(AND($C54="Assured",Y$45>=$C$25),$C$24,INDEX(Assumptions!$D$44:$D$46,MATCH($C54,Assumptions!$A$44:$A$46,0))) -> 24480
A99: =A55 -> 8 | B99: =B55 -> A | C99: =C55 -> Assured | H99: =H55*IF(AND($C55="Assured",H$45>=$C$25),$C$24,INDEX(Assumptions!$D$44:$D$46,MATCH($C55,Assumptions!$A$44:$A$46,0))) -> 0 | I99: =I55*IF(AND($C55="Assured",I$45>=$C$25),$C$24,INDEX(Assumptions!$D$44:$D$46,MATCH($C55,Assumptions!$A$44:$A$46,0))) -> 0 | J99: =J55*IF(AND($C55="Assured",J$45>=$C$25),$C$24,INDEX(Assumptions!$D$44:$D$46,MATCH($C55,Assumptions!$A$44:$A$46,0))) -> 0 | K99: =K55*IF(AND($C55="Assured",K$45>=$C$25),$C$24,INDEX(Assumptions!$D$44:$D$46,MATCH($C55,Assumptions!$A$44:$A$46,0))) -> 8262 | L99: =L55*IF(AND($C55="Assured",L$45>=$C$25),$C$24,INDEX(Assumptions!$D$44:$D$46,MATCH($C55,Assumptions!$A$44:$A$46,0))) -> 16524 | M99: =M55*IF(AND($C55="Assured",M$45>=$C$25),$C$24,INDEX(Assumptions!$D$44:$D$46,MATCH($C55,Assumptions!$A$44:$A$46,0))) -> 23409 | N99: =N55*IF(AND($C55="Assured",N$45>=$C$25),$C$24,INDEX(Assumptions!$D$44:$D$46,MATCH($C55,Assumptions!$A$44:$A$46,0))) -> 27540 | O99: =O55*IF(AND($C55="Assured",O$45>=$C$25),$C$24,INDEX(Assumptions!$D$44:$D$46,MATCH($C55,Assumptions!$A$44:$A$46,0))) -> 27540 | ... Y99: =Y55*IF(AND($C55="Assured",Y$45>=$C$25),$C$24,INDEX(Assumptions!$D$44:$D$46,MATCH($C55,Assumptions!$A$44:$A$46,0))) -> 24480
A100: =A56 -> 9 | B100: =B56 -> A | C100: =C56 -> Assured | H100: =H56*IF(AND($C56="Assured",H$45>=$C$25),$C$24,INDEX(Assumptions!$D$44:$D$46,MATCH($C56,Assumptions!$A$44:$A$46,0))) -> 0 | I100: =I56*IF(AND($C56="Assured",I$45>=$C$25),$C$24,INDEX(Assumptions!$D$44:$D$46,MATCH($C56,Assumptions!$A$44:$A$46,0))) -> 0 | J100: =J56*IF(AND($C56="Assured",J$45>=$C$25),$C$24,INDEX(Assumptions!$D$44:$D$46,MATCH($C56,Assumptions!$A$44:$A$46,0))) -> 0 | K100: =K56*IF(AND($C56="Assured",K$45>=$C$25),$C$24,INDEX(Assumptions!$D$44:$D$46,MATCH($C56,Assumptions!$A$44:$A$46,0))) -> 0 | L100: =L56*IF(AND($C56="Assured",L$45>=$C$25),$C$24,INDEX(Assumptions!$D$44:$D$46,MATCH($C56,Assumptions!$A$44:$A$46,0))) -> 8262 | M100: =M56*IF(AND($C56="Assured",M$45>=$C$25),$C$24,INDEX(Assumptions!$D$44:$D$46,MATCH($C56,Assumptions!$A$44:$A$46,0))) -> 16524 | N100: =N56*IF(AND($C56="Assured",N$45>=$C$25),$C$24,INDEX(Assumptions!$D$44:$D$46,MATCH($C56,Assumptions!$A$44:$A$46,0))) -> 23409 | O100: =O56*IF(AND($C56="Assured",O$45>=$C$25),$C$24,INDEX(Assumptions!$D$44:$D$46,MATCH($C56,Assumptions!$A$44:$A$46,0))) -> 27540 | ... Y100: =Y56*IF(AND($C56="Assured",Y$45>=$C$25),$C$24,INDEX(Assumptions!$D$44:$D$46,MATCH($C56,Assumptions!$A$44:$A$46,0))) -> 24480
A101: =A57 -> 10 | B101: =B57 -> C | C101: =C57 -> Assured | H101: =H57*IF(AND($C57="Assured",H$45>=$C$25),$C$24,INDEX(Assumptions!$D$44:$D$46,MATCH($C57,Assumptions!$A$44:$A$46,0))) -> 0 | I101: =I57*IF(AND($C57="Assured",I$45>=$C$25),$C$24,INDEX(Assumptions!$D$44:$D$46,MATCH($C57,Assumptions!$A$44:$A$46,0))) -> 0 | J101: =J57*IF(AND($C57="Assured",J$45>=$C$25),$C$24,INDEX(Assumptions!$D$44:$D$46,MATCH($C57,Assumptions!$A$44:$A$46,0))) -> 0 | K101: =K57*IF(AND($C57="Assured",K$45>=$C$25),$C$24,INDEX(Assumptions!$D$44:$D$46,MATCH($C57,Assumptions!$A$44:$A$46,0))) -> 0 | L101: =L57*IF(AND($C57="Assured",L$45>=$C$25),$C$24,INDEX(Assumptions!$D$44:$D$46,MATCH($C57,Assumptions!$A$44:$A$46,0))) -> 0 | M101: =M57*IF(AND($C57="Assured",M$45>=$C$25),$C$24,INDEX(Assumptions!$D$44:$D$46,MATCH($C57,Assumptions!$A$44:$A$46,0))) -> 8950.5 | N101: =N57*IF(AND($C57="Assured",N$45>=$C$25),$C$24,INDEX(Assumptions!$D$44:$D$46,MATCH($C57,Assumptions!$A$44:$A$46,0))) -> 17901 | O101: =O57*IF(AND($C57="Assured",O$45>=$C$25),$C$24,INDEX(Assumptions!$D$44:$D$46,MATCH($C57,Assumptions!$A$44:$A$46,0))) -> 25359.75 | ... Y101: =Y57*IF(AND($C57="Assured",Y$45>=$C$25),$C$24,INDEX(Assumptions!$D$44:$D$46,MATCH($C57,Assumptions!$A$44:$A$46,0))) -> 26520
A102: =A58 -> 11 | B102: =B58 -> C | C102: =C58 -> Assured | H102: =H58*IF(AND($C58="Assured",H$45>=$C$25),$C$24,INDEX(Assumptions!$D$44:$D$46,MATCH($C58,Assumptions!$A$44:$A$46,0))) -> 0 | I102: =I58*IF(AND($C58="Assured",I$45>=$C$25),$C$24,INDEX(Assumptions!$D$44:$D$46,MATCH($C58,Assumptions!$A$44:$A$46,0))) -> 0 | J102: =J58*IF(AND($C58="Assured",J$45>=$C$25),$C$24,INDEX(Assumptions!$D$44:$D$46,MATCH($C58,Assumptions!$A$44:$A$46,0))) -> 0 | K102: =K58*IF(AND($C58="Assured",K$45>=$C$25),$C$24,INDEX(Assumptions!$D$44:$D$46,MATCH($C58,Assumptions!$A$44:$A$46,0))) -> 0 | L102: =L58*IF(AND($C58="Assured",L$45>=$C$25),$C$24,INDEX(Assumptions!$D$44:$D$46,MATCH($C58,Assumptions!$A$44:$A$46,0))) -> 0 | M102: =M58*IF(AND($C58="Assured",M$45>=$C$25),$C$24,INDEX(Assumptions!$D$44:$D$46,MATCH($C58,Assumptions!$A$44:$A$46,0))) -> 0 | N102: =N58*IF(AND($C58="Assured",N$45>=$C$25),$C$24,INDEX(Assumptions!$D$44:$D$46,MATCH($C58,Assumptions!$A$44:$A$46,0))) -> 8950.5 | O102: =O58*IF(AND($C58="Assured",O$45>=$C$25),$C$24,INDEX(Assumptions!$D$44:$D$46,MATCH($C58,Assumptions!$A$44:$A$46,0))) -> 17901 | ... Y102: =Y58*IF(AND($C58="Assured",Y$45>=$C$25),$C$24,INDEX(Assumptions!$D$44:$D$46,MATCH($C58,Assumptions!$A$44:$A$46,0))) -> 26520
A103: =A59 -> 12 | B103: =B59 -> C | C103: =C59 -> Assured | H103: =H59*IF(AND($C59="Assured",H$45>=$C$25),$C$24,INDEX(Assumptions!$D$44:$D$46,MATCH($C59,Assumptions!$A$44:$A$46,0))) -> 0 | I103: =I59*IF(AND($C59="Assured",I$45>=$C$25),$C$24,INDEX(Assumptions!$D$44:$D$46,MATCH($C59,Assumptions!$A$44:$A$46,0))) -> 0 | J103: =J59*IF(AND($C59="Assured",J$45>=$C$25),$C$24,INDEX(Assumptions!$D$44:$D$46,MATCH($C59,Assumptions!$A$44:$A$46,0))) -> 0 | K103: =K59*IF(AND($C59="Assured",K$45>=$C$25),$C$24,INDEX(Assumptions!$D$44:$D$46,MATCH($C59,Assumptions!$A$44:$A$46,0))) -> 0 | L103: =L59*IF(AND($C59="Assured",L$45>=$C$25),$C$24,INDEX(Assumptions!$D$44:$D$46,MATCH($C59,Assumptions!$A$44:$A$46,0))) -> 0 | M103: =M59*IF(AND($C59="Assured",M$45>=$C$25),$C$24,INDEX(Assumptions!$D$44:$D$46,MATCH($C59,Assumptions!$A$44:$A$46,0))) -> 0 | N103: =N59*IF(AND($C59="Assured",N$45>=$C$25),$C$24,INDEX(Assumptions!$D$44:$D$46,MATCH($C59,Assumptions!$A$44:$A$46,0))) -> 8950.5 | O103: =O59*IF(AND($C59="Assured",O$45>=$C$25),$C$24,INDEX(Assumptions!$D$44:$D$46,MATCH($C59,Assumptions!$A$44:$A$46,0))) -> 17901 | ... Y103: =Y59*IF(AND($C59="Assured",Y$45>=$C$25),$C$24,INDEX(Assumptions!$D$44:$D$46,MATCH($C59,Assumptions!$A$44:$A$46,0))) -> 26520
... A111: =A67 -> 20 | B111: =B67 -> B | C111: =C67 -> Verified | H111: =H67*IF(AND($C67="Assured",H$45>=$C$25),$C$24,INDEX(Assumptions!$D$44:$D$46,MATCH($C67,Assumptions!$A$44:$A$46,0))) -> 0 | I111: =I67*IF(AND($C67="Assured",I$45>=$C$25),$C$24,INDEX(Assumptions!$D$44:$D$46,MATCH($C67,Assumptions!$A$44:$A$46,0))) -> 0 | J111: =J67*IF(AND($C67="Assured",J$45>=$C$25),$C$24,INDEX(Assumptions!$D$44:$D$46,MATCH($C67,Assumptions!$A$44:$A$46,0))) -> 0 | K111: =K67*IF(AND($C67="Assured",K$45>=$C$25),$C$24,INDEX(Assumptions!$D$44:$D$46,MATCH($C67,Assumptions!$A$44:$A$46,0))) -> 0 | L111: =L67*IF(AND($C67="Assured",L$45>=$C$25),$C$24,INDEX(Assumptions!$D$44:$D$46,MATCH($C67,Assumptions!$A$44:$A$46,0))) -> 0 | M111: =M67*IF(AND($C67="Assured",M$45>=$C$25),$C$24,INDEX(Assumptions!$D$44:$D$46,MATCH($C67,Assumptions!$A$44:$A$46,0))) -> 0 | N111: =N67*IF(AND($C67="Assured",N$45>=$C$25),$C$24,INDEX(Assumptions!$D$44:$D$46,MATCH($C67,Assumptions!$A$44:$A$46,0))) -> 0 | O111: =O67*IF(AND($C67="Assured",O$45>=$C$25),$C$24,INDEX(Assumptions!$D$44:$D$46,MATCH($C67,Assumptions!$A$44:$A$46,0))) -> 0 | ... Y111: =Y67*IF(AND($C67="Assured",Y$45>=$C$25),$C$24,INDEX(Assumptions!$D$44:$D$46,MATCH($C67,Assumptions!$A$44:$A$46,0))) -> 15300
A113: Onboarding spend per host (₹)
A114: =A48 -> 1 | B114: =B48 -> Pilot | C114: =C48 -> Assured | H114: =IF($F48=1,IF(H$45=1,INDEX(Assumptions!$E$44:$E$46,MATCH($C48,Assumptions!$A$44:$A$46,0))*$C$34,0),IF(H$45=MAX($G48-1,1),INDEX(Assumptions!$E$44:$E$46,MATCH($C48,Assumptions!$A$44:$A$46,0)),0))*IF(AND($C48="Verified",$C$39=1),0,1) -> 60000 | I114: =IF($F48=1,IF(I$45=1,INDEX(Assumptions!$E$44:$E$46,MATCH($C48,Assumptions!$A$44:$A$46,0))*$C$34,0),IF(I$45=MAX($G48-1,1),INDEX(Assumptions!$E$44:$E$46,MATCH($C48,Assumptions!$A$44:$A$46,0)),0))*IF(AND($C48="Verified",$C$39=1),0,1) -> 0 | J114: =IF($F48=1,IF(J$45=1,INDEX(Assumptions!$E$44:$E$46,MATCH($C48,Assumptions!$A$44:$A$46,0))*$C$34,0),IF(J$45=MAX($G48-1,1),INDEX(Assumptions!$E$44:$E$46,MATCH($C48,Assumptions!$A$44:$A$46,0)),0))*IF(AND($C48="Verified",$C$39=1),0,1) -> 0 | K114: =IF($F48=1,IF(K$45=1,INDEX(Assumptions!$E$44:$E$46,MATCH($C48,Assumptions!$A$44:$A$46,0))*$C$34,0),IF(K$45=MAX($G48-1,1),INDEX(Assumptions!$E$44:$E$46,MATCH($C48,Assumptions!$A$44:$A$46,0)),0))*IF(AND($C48="Verified",$C$39=1),0,1) -> 0 | L114: =IF($F48=1,IF(L$45=1,INDEX(Assumptions!$E$44:$E$46,MATCH($C48,Assumptions!$A$44:$A$46,0))*$C$34,0),IF(L$45=MAX($G48-1,1),INDEX(Assumptions!$E$44:$E$46,MATCH($C48,Assumptions!$A$44:$A$46,0)),0))*IF(AND($C48="Verified",$C$39=1),0,1) -> 0 | M114: =IF($F48=1,IF(M$45=1,INDEX(Assumptions!$E$44:$E$46,MATCH($C48,Assumptions!$A$44:$A$46,0))*$C$34,0),IF(M$45=MAX($G48-1,1),INDEX(Assumptions!$E$44:$E$46,MATCH($C48,Assumptions!$A$44:$A$46,0)),0))*IF(AND($C48="Verified",$C$39=1),0,1) -> 0 | N114: =IF($F48=1,IF(N$45=1,INDEX(Assumptions!$E$44:$E$46,MATCH($C48,Assumptions!$A$44:$A$46,0))*$C$34,0),IF(N$45=MAX($G48-1,1),INDEX(Assumptions!$E$44:$E$46,MATCH($C48,Assumptions!$A$44:$A$46,0)),0))*IF(AND($C48="Verified",$C$39=1),0,1) -> 0 | O114: =IF($F48=1,IF(O$45=1,INDEX(Assumptions!$E$44:$E$46,MATCH($C48,Assumptions!$A$44:$A$46,0))*$C$34,0),IF(O$45=MAX($G48-1,1),INDEX(Assumptions!$E$44:$E$46,MATCH($C48,Assumptions!$A$44:$A$46,0)),0))*IF(AND($C48="Verified",$C$39=1),0,1) -> 0 | ... Y114: =IF($F48=1,IF(Y$45=1,INDEX(Assumptions!$E$44:$E$46,MATCH($C48,Assumptions!$A$44:$A$46,0))*$C$34,0),IF(Y$45=MAX($G48-1,1),INDEX(Assumptions!$E$44:$E$46,MATCH($C48,Assumptions!$A$44:$A$46,0)),0))*IF(AND($C48="Verified",$C$39=1),0,1) -> 0
A115: =A49 -> 2 | B115: =B49 -> Pilot | C115: =C49 -> Assured | H115: =IF($F49=1,IF(H$45=1,INDEX(Assumptions!$E$44:$E$46,MATCH($C49,Assumptions!$A$44:$A$46,0))*$C$34,0),IF(H$45=MAX($G49-1,1),INDEX(Assumptions!$E$44:$E$46,MATCH($C49,Assumptions!$A$44:$A$46,0)),0))*IF(AND($C49="Verified",$C$39=1),0,1) -> 60000 | I115: =IF($F49=1,IF(I$45=1,INDEX(Assumptions!$E$44:$E$46,MATCH($C49,Assumptions!$A$44:$A$46,0))*$C$34,0),IF(I$45=MAX($G49-1,1),INDEX(Assumptions!$E$44:$E$46,MATCH($C49,Assumptions!$A$44:$A$46,0)),0))*IF(AND($C49="Verified",$C$39=1),0,1) -> 0 | J115: =IF($F49=1,IF(J$45=1,INDEX(Assumptions!$E$44:$E$46,MATCH($C49,Assumptions!$A$44:$A$46,0))*$C$34,0),IF(J$45=MAX($G49-1,1),INDEX(Assumptions!$E$44:$E$46,MATCH($C49,Assumptions!$A$44:$A$46,0)),0))*IF(AND($C49="Verified",$C$39=1),0,1) -> 0 | K115: =IF($F49=1,IF(K$45=1,INDEX(Assumptions!$E$44:$E$46,MATCH($C49,Assumptions!$A$44:$A$46,0))*$C$34,0),IF(K$45=MAX($G49-1,1),INDEX(Assumptions!$E$44:$E$46,MATCH($C49,Assumptions!$A$44:$A$46,0)),0))*IF(AND($C49="Verified",$C$39=1),0,1) -> 0 | L115: =IF($F49=1,IF(L$45=1,INDEX(Assumptions!$E$44:$E$46,MATCH($C49,Assumptions!$A$44:$A$46,0))*$C$34,0),IF(L$45=MAX($G49-1,1),INDEX(Assumptions!$E$44:$E$46,MATCH($C49,Assumptions!$A$44:$A$46,0)),0))*IF(AND($C49="Verified",$C$39=1),0,1) -> 0 | M115: =IF($F49=1,IF(M$45=1,INDEX(Assumptions!$E$44:$E$46,MATCH($C49,Assumptions!$A$44:$A$46,0))*$C$34,0),IF(M$45=MAX($G49-1,1),INDEX(Assumptions!$E$44:$E$46,MATCH($C49,Assumptions!$A$44:$A$46,0)),0))*IF(AND($C49="Verified",$C$39=1),0,1) -> 0 | N115: =IF($F49=1,IF(N$45=1,INDEX(Assumptions!$E$44:$E$46,MATCH($C49,Assumptions!$A$44:$A$46,0))*$C$34,0),IF(N$45=MAX($G49-1,1),INDEX(Assumptions!$E$44:$E$46,MATCH($C49,Assumptions!$A$44:$A$46,0)),0))*IF(AND($C49="Verified",$C$39=1),0,1) -> 0 | O115: =IF($F49=1,IF(O$45=1,INDEX(Assumptions!$E$44:$E$46,MATCH($C49,Assumptions!$A$44:$A$46,0))*$C$34,0),IF(O$45=MAX($G49-1,1),INDEX(Assumptions!$E$44:$E$46,MATCH($C49,Assumptions!$A$44:$A$46,0)),0))*IF(AND($C49="Verified",$C$39=1),0,1) -> 0 | ... Y115: =IF($F49=1,IF(Y$45=1,INDEX(Assumptions!$E$44:$E$46,MATCH($C49,Assumptions!$A$44:$A$46,0))*$C$34,0),IF(Y$45=MAX($G49-1,1),INDEX(Assumptions!$E$44:$E$46,MATCH($C49,Assumptions!$A$44:$A$46,0)),0))*IF(AND($C49="Verified",$C$39=1),0,1) -> 0
A116: =A50 -> 3 | B116: =B50 -> Pilot | C116: =C50 -> Assured | H116: =IF($F50=1,IF(H$45=1,INDEX(Assumptions!$E$44:$E$46,MATCH($C50,Assumptions!$A$44:$A$46,0))*$C$34,0),IF(H$45=MAX($G50-1,1),INDEX(Assumptions!$E$44:$E$46,MATCH($C50,Assumptions!$A$44:$A$46,0)),0))*IF(AND($C50="Verified",$C$39=1),0,1) -> 60000 | I116: =IF($F50=1,IF(I$45=1,INDEX(Assumptions!$E$44:$E$46,MATCH($C50,Assumptions!$A$44:$A$46,0))*$C$34,0),IF(I$45=MAX($G50-1,1),INDEX(Assumptions!$E$44:$E$46,MATCH($C50,Assumptions!$A$44:$A$46,0)),0))*IF(AND($C50="Verified",$C$39=1),0,1) -> 0 | J116: =IF($F50=1,IF(J$45=1,INDEX(Assumptions!$E$44:$E$46,MATCH($C50,Assumptions!$A$44:$A$46,0))*$C$34,0),IF(J$45=MAX($G50-1,1),INDEX(Assumptions!$E$44:$E$46,MATCH($C50,Assumptions!$A$44:$A$46,0)),0))*IF(AND($C50="Verified",$C$39=1),0,1) -> 0 | K116: =IF($F50=1,IF(K$45=1,INDEX(Assumptions!$E$44:$E$46,MATCH($C50,Assumptions!$A$44:$A$46,0))*$C$34,0),IF(K$45=MAX($G50-1,1),INDEX(Assumptions!$E$44:$E$46,MATCH($C50,Assumptions!$A$44:$A$46,0)),0))*IF(AND($C50="Verified",$C$39=1),0,1) -> 0 | L116: =IF($F50=1,IF(L$45=1,INDEX(Assumptions!$E$44:$E$46,MATCH($C50,Assumptions!$A$44:$A$46,0))*$C$34,0),IF(L$45=MAX($G50-1,1),INDEX(Assumptions!$E$44:$E$46,MATCH($C50,Assumptions!$A$44:$A$46,0)),0))*IF(AND($C50="Verified",$C$39=1),0,1) -> 0 | M116: =IF($F50=1,IF(M$45=1,INDEX(Assumptions!$E$44:$E$46,MATCH($C50,Assumptions!$A$44:$A$46,0))*$C$34,0),IF(M$45=MAX($G50-1,1),INDEX(Assumptions!$E$44:$E$46,MATCH($C50,Assumptions!$A$44:$A$46,0)),0))*IF(AND($C50="Verified",$C$39=1),0,1) -> 0 | N116: =IF($F50=1,IF(N$45=1,INDEX(Assumptions!$E$44:$E$46,MATCH($C50,Assumptions!$A$44:$A$46,0))*$C$34,0),IF(N$45=MAX($G50-1,1),INDEX(Assumptions!$E$44:$E$46,MATCH($C50,Assumptions!$A$44:$A$46,0)),0))*IF(AND($C50="Verified",$C$39=1),0,1) -> 0 | O116: =IF($F50=1,IF(O$45=1,INDEX(Assumptions!$E$44:$E$46,MATCH($C50,Assumptions!$A$44:$A$46,0))*$C$34,0),IF(O$45=MAX($G50-1,1),INDEX(Assumptions!$E$44:$E$46,MATCH($C50,Assumptions!$A$44:$A$46,0)),0))*IF(AND($C50="Verified",$C$39=1),0,1) -> 0 | ... Y116: =IF($F50=1,IF(Y$45=1,INDEX(Assumptions!$E$44:$E$46,MATCH($C50,Assumptions!$A$44:$A$46,0))*$C$34,0),IF(Y$45=MAX($G50-1,1),INDEX(Assumptions!$E$44:$E$46,MATCH($C50,Assumptions!$A$44:$A$46,0)),0))*IF(AND($C50="Verified",$C$39=1),0,1) -> 0
A117: =A51 -> 4 | B117: =B51 -> Pilot | C117: =C51 -> Assured | H117: =IF($F51=1,IF(H$45=1,INDEX(Assumptions!$E$44:$E$46,MATCH($C51,Assumptions!$A$44:$A$46,0))*$C$34,0),IF(H$45=MAX($G51-1,1),INDEX(Assumptions!$E$44:$E$46,MATCH($C51,Assumptions!$A$44:$A$46,0)),0))*IF(AND($C51="Verified",$C$39=1),0,1) -> 60000 | I117: =IF($F51=1,IF(I$45=1,INDEX(Assumptions!$E$44:$E$46,MATCH($C51,Assumptions!$A$44:$A$46,0))*$C$34,0),IF(I$45=MAX($G51-1,1),INDEX(Assumptions!$E$44:$E$46,MATCH($C51,Assumptions!$A$44:$A$46,0)),0))*IF(AND($C51="Verified",$C$39=1),0,1) -> 0 | J117: =IF($F51=1,IF(J$45=1,INDEX(Assumptions!$E$44:$E$46,MATCH($C51,Assumptions!$A$44:$A$46,0))*$C$34,0),IF(J$45=MAX($G51-1,1),INDEX(Assumptions!$E$44:$E$46,MATCH($C51,Assumptions!$A$44:$A$46,0)),0))*IF(AND($C51="Verified",$C$39=1),0,1) -> 0 | K117: =IF($F51=1,IF(K$45=1,INDEX(Assumptions!$E$44:$E$46,MATCH($C51,Assumptions!$A$44:$A$46,0))*$C$34,0),IF(K$45=MAX($G51-1,1),INDEX(Assumptions!$E$44:$E$46,MATCH($C51,Assumptions!$A$44:$A$46,0)),0))*IF(AND($C51="Verified",$C$39=1),0,1) -> 0 | L117: =IF($F51=1,IF(L$45=1,INDEX(Assumptions!$E$44:$E$46,MATCH($C51,Assumptions!$A$44:$A$46,0))*$C$34,0),IF(L$45=MAX($G51-1,1),INDEX(Assumptions!$E$44:$E$46,MATCH($C51,Assumptions!$A$44:$A$46,0)),0))*IF(AND($C51="Verified",$C$39=1),0,1) -> 0 | M117: =IF($F51=1,IF(M$45=1,INDEX(Assumptions!$E$44:$E$46,MATCH($C51,Assumptions!$A$44:$A$46,0))*$C$34,0),IF(M$45=MAX($G51-1,1),INDEX(Assumptions!$E$44:$E$46,MATCH($C51,Assumptions!$A$44:$A$46,0)),0))*IF(AND($C51="Verified",$C$39=1),0,1) -> 0 | N117: =IF($F51=1,IF(N$45=1,INDEX(Assumptions!$E$44:$E$46,MATCH($C51,Assumptions!$A$44:$A$46,0))*$C$34,0),IF(N$45=MAX($G51-1,1),INDEX(Assumptions!$E$44:$E$46,MATCH($C51,Assumptions!$A$44:$A$46,0)),0))*IF(AND($C51="Verified",$C$39=1),0,1) -> 0 | O117: =IF($F51=1,IF(O$45=1,INDEX(Assumptions!$E$44:$E$46,MATCH($C51,Assumptions!$A$44:$A$46,0))*$C$34,0),IF(O$45=MAX($G51-1,1),INDEX(Assumptions!$E$44:$E$46,MATCH($C51,Assumptions!$A$44:$A$46,0)),0))*IF(AND($C51="Verified",$C$39=1),0,1) -> 0 | ... Y117: =IF($F51=1,IF(Y$45=1,INDEX(Assumptions!$E$44:$E$46,MATCH($C51,Assumptions!$A$44:$A$46,0))*$C$34,0),IF(Y$45=MAX($G51-1,1),INDEX(Assumptions!$E$44:$E$46,MATCH($C51,Assumptions!$A$44:$A$46,0)),0))*IF(AND($C51="Verified",$C$39=1),0,1) -> 0
A118: =A52 -> 5 | B118: =B52 -> A | C118: =C52 -> Assured | H118: =IF($F52=1,IF(H$45=1,INDEX(Assumptions!$E$44:$E$46,MATCH($C52,Assumptions!$A$44:$A$46,0))*$C$34,0),IF(H$45=MAX($G52-1,1),INDEX(Assumptions!$E$44:$E$46,MATCH($C52,Assumptions!$A$44:$A$46,0)),0))*IF(AND($C52="Verified",$C$39=1),0,1) -> 0 | I118: =IF($F52=1,IF(I$45=1,INDEX(Assumptions!$E$44:$E$46,MATCH($C52,Assumptions!$A$44:$A$46,0))*$C$34,0),IF(I$45=MAX($G52-1,1),INDEX(Assumptions!$E$44:$E$46,MATCH($C52,Assumptions!$A$44:$A$46,0)),0))*IF(AND($C52="Verified",$C$39=1),0,1) -> 120000 | J118: =IF($F52=1,IF(J$45=1,INDEX(Assumptions!$E$44:$E$46,MATCH($C52,Assumptions!$A$44:$A$46,0))*$C$34,0),IF(J$45=MAX($G52-1,1),INDEX(Assumptions!$E$44:$E$46,MATCH($C52,Assumptions!$A$44:$A$46,0)),0))*IF(AND($C52="Verified",$C$39=1),0,1) -> 0 | K118: =IF($F52=1,IF(K$45=1,INDEX(Assumptions!$E$44:$E$46,MATCH($C52,Assumptions!$A$44:$A$46,0))*$C$34,0),IF(K$45=MAX($G52-1,1),INDEX(Assumptions!$E$44:$E$46,MATCH($C52,Assumptions!$A$44:$A$46,0)),0))*IF(AND($C52="Verified",$C$39=1),0,1) -> 0 | L118: =IF($F52=1,IF(L$45=1,INDEX(Assumptions!$E$44:$E$46,MATCH($C52,Assumptions!$A$44:$A$46,0))*$C$34,0),IF(L$45=MAX($G52-1,1),INDEX(Assumptions!$E$44:$E$46,MATCH($C52,Assumptions!$A$44:$A$46,0)),0))*IF(AND($C52="Verified",$C$39=1),0,1) -> 0 | M118: =IF($F52=1,IF(M$45=1,INDEX(Assumptions!$E$44:$E$46,MATCH($C52,Assumptions!$A$44:$A$46,0))*$C$34,0),IF(M$45=MAX($G52-1,1),INDEX(Assumptions!$E$44:$E$46,MATCH($C52,Assumptions!$A$44:$A$46,0)),0))*IF(AND($C52="Verified",$C$39=1),0,1) -> 0 | N118: =IF($F52=1,IF(N$45=1,INDEX(Assumptions!$E$44:$E$46,MATCH($C52,Assumptions!$A$44:$A$46,0))*$C$34,0),IF(N$45=MAX($G52-1,1),INDEX(Assumptions!$E$44:$E$46,MATCH($C52,Assumptions!$A$44:$A$46,0)),0))*IF(AND($C52="Verified",$C$39=1),0,1) -> 0 | O118: =IF($F52=1,IF(O$45=1,INDEX(Assumptions!$E$44:$E$46,MATCH($C52,Assumptions!$A$44:$A$46,0))*$C$34,0),IF(O$45=MAX($G52-1,1),INDEX(Assumptions!$E$44:$E$46,MATCH($C52,Assumptions!$A$44:$A$46,0)),0))*IF(AND($C52="Verified",$C$39=1),0,1) -> 0 | ... Y118: =IF($F52=1,IF(Y$45=1,INDEX(Assumptions!$E$44:$E$46,MATCH($C52,Assumptions!$A$44:$A$46,0))*$C$34,0),IF(Y$45=MAX($G52-1,1),INDEX(Assumptions!$E$44:$E$46,MATCH($C52,Assumptions!$A$44:$A$46,0)),0))*IF(AND($C52="Verified",$C$39=1),0,1) -> 0
A119: =A53 -> 6 | B119: =B53 -> A | C119: =C53 -> Assured | H119: =IF($F53=1,IF(H$45=1,INDEX(Assumptions!$E$44:$E$46,MATCH($C53,Assumptions!$A$44:$A$46,0))*$C$34,0),IF(H$45=MAX($G53-1,1),INDEX(Assumptions!$E$44:$E$46,MATCH($C53,Assumptions!$A$44:$A$46,0)),0))*IF(AND($C53="Verified",$C$39=1),0,1) -> 0 | I119: =IF($F53=1,IF(I$45=1,INDEX(Assumptions!$E$44:$E$46,MATCH($C53,Assumptions!$A$44:$A$46,0))*$C$34,0),IF(I$45=MAX($G53-1,1),INDEX(Assumptions!$E$44:$E$46,MATCH($C53,Assumptions!$A$44:$A$46,0)),0))*IF(AND($C53="Verified",$C$39=1),0,1) -> 120000 | J119: =IF($F53=1,IF(J$45=1,INDEX(Assumptions!$E$44:$E$46,MATCH($C53,Assumptions!$A$44:$A$46,0))*$C$34,0),IF(J$45=MAX($G53-1,1),INDEX(Assumptions!$E$44:$E$46,MATCH($C53,Assumptions!$A$44:$A$46,0)),0))*IF(AND($C53="Verified",$C$39=1),0,1) -> 0 | K119: =IF($F53=1,IF(K$45=1,INDEX(Assumptions!$E$44:$E$46,MATCH($C53,Assumptions!$A$44:$A$46,0))*$C$34,0),IF(K$45=MAX($G53-1,1),INDEX(Assumptions!$E$44:$E$46,MATCH($C53,Assumptions!$A$44:$A$46,0)),0))*IF(AND($C53="Verified",$C$39=1),0,1) -> 0 | L119: =IF($F53=1,IF(L$45=1,INDEX(Assumptions!$E$44:$E$46,MATCH($C53,Assumptions!$A$44:$A$46,0))*$C$34,0),IF(L$45=MAX($G53-1,1),INDEX(Assumptions!$E$44:$E$46,MATCH($C53,Assumptions!$A$44:$A$46,0)),0))*IF(AND($C53="Verified",$C$39=1),0,1) -> 0 | M119: =IF($F53=1,IF(M$45=1,INDEX(Assumptions!$E$44:$E$46,MATCH($C53,Assumptions!$A$44:$A$46,0))*$C$34,0),IF(M$45=MAX($G53-1,1),INDEX(Assumptions!$E$44:$E$46,MATCH($C53,Assumptions!$A$44:$A$46,0)),0))*IF(AND($C53="Verified",$C$39=1),0,1) -> 0 | N119: =IF($F53=1,IF(N$45=1,INDEX(Assumptions!$E$44:$E$46,MATCH($C53,Assumptions!$A$44:$A$46,0))*$C$34,0),IF(N$45=MAX($G53-1,1),INDEX(Assumptions!$E$44:$E$46,MATCH($C53,Assumptions!$A$44:$A$46,0)),0))*IF(AND($C53="Verified",$C$39=1),0,1) -> 0 | O119: =IF($F53=1,IF(O$45=1,INDEX(Assumptions!$E$44:$E$46,MATCH($C53,Assumptions!$A$44:$A$46,0))*$C$34,0),IF(O$45=MAX($G53-1,1),INDEX(Assumptions!$E$44:$E$46,MATCH($C53,Assumptions!$A$44:$A$46,0)),0))*IF(AND($C53="Verified",$C$39=1),0,1) -> 0 | ... Y119: =IF($F53=1,IF(Y$45=1,INDEX(Assumptions!$E$44:$E$46,MATCH($C53,Assumptions!$A$44:$A$46,0))*$C$34,0),IF(Y$45=MAX($G53-1,1),INDEX(Assumptions!$E$44:$E$46,MATCH($C53,Assumptions!$A$44:$A$46,0)),0))*IF(AND($C53="Verified",$C$39=1),0,1) -> 0
A120: =A54 -> 7 | B120: =B54 -> A | C120: =C54 -> Assured | H120: =IF($F54=1,IF(H$45=1,INDEX(Assumptions!$E$44:$E$46,MATCH($C54,Assumptions!$A$44:$A$46,0))*$C$34,0),IF(H$45=MAX($G54-1,1),INDEX(Assumptions!$E$44:$E$46,MATCH($C54,Assumptions!$A$44:$A$46,0)),0))*IF(AND($C54="Verified",$C$39=1),0,1) -> 0 | I120: =IF($F54=1,IF(I$45=1,INDEX(Assumptions!$E$44:$E$46,MATCH($C54,Assumptions!$A$44:$A$46,0))*$C$34,0),IF(I$45=MAX($G54-1,1),INDEX(Assumptions!$E$44:$E$46,MATCH($C54,Assumptions!$A$44:$A$46,0)),0))*IF(AND($C54="Verified",$C$39=1),0,1) -> 0 | J120: =IF($F54=1,IF(J$45=1,INDEX(Assumptions!$E$44:$E$46,MATCH($C54,Assumptions!$A$44:$A$46,0))*$C$34,0),IF(J$45=MAX($G54-1,1),INDEX(Assumptions!$E$44:$E$46,MATCH($C54,Assumptions!$A$44:$A$46,0)),0))*IF(AND($C54="Verified",$C$39=1),0,1) -> 120000 | K120: =IF($F54=1,IF(K$45=1,INDEX(Assumptions!$E$44:$E$46,MATCH($C54,Assumptions!$A$44:$A$46,0))*$C$34,0),IF(K$45=MAX($G54-1,1),INDEX(Assumptions!$E$44:$E$46,MATCH($C54,Assumptions!$A$44:$A$46,0)),0))*IF(AND($C54="Verified",$C$39=1),0,1) -> 0 | L120: =IF($F54=1,IF(L$45=1,INDEX(Assumptions!$E$44:$E$46,MATCH($C54,Assumptions!$A$44:$A$46,0))*$C$34,0),IF(L$45=MAX($G54-1,1),INDEX(Assumptions!$E$44:$E$46,MATCH($C54,Assumptions!$A$44:$A$46,0)),0))*IF(AND($C54="Verified",$C$39=1),0,1) -> 0 | M120: =IF($F54=1,IF(M$45=1,INDEX(Assumptions!$E$44:$E$46,MATCH($C54,Assumptions!$A$44:$A$46,0))*$C$34,0),IF(M$45=MAX($G54-1,1),INDEX(Assumptions!$E$44:$E$46,MATCH($C54,Assumptions!$A$44:$A$46,0)),0))*IF(AND($C54="Verified",$C$39=1),0,1) -> 0 | N120: =IF($F54=1,IF(N$45=1,INDEX(Assumptions!$E$44:$E$46,MATCH($C54,Assumptions!$A$44:$A$46,0))*$C$34,0),IF(N$45=MAX($G54-1,1),INDEX(Assumptions!$E$44:$E$46,MATCH($C54,Assumptions!$A$44:$A$46,0)),0))*IF(AND($C54="Verified",$C$39=1),0,1) -> 0 | O120: =IF($F54=1,IF(O$45=1,INDEX(Assumptions!$E$44:$E$46,MATCH($C54,Assumptions!$A$44:$A$46,0))*$C$34,0),IF(O$45=MAX($G54-1,1),INDEX(Assumptions!$E$44:$E$46,MATCH($C54,Assumptions!$A$44:$A$46,0)),0))*IF(AND($C54="Verified",$C$39=1),0,1) -> 0 | ... Y120: =IF($F54=1,IF(Y$45=1,INDEX(Assumptions!$E$44:$E$46,MATCH($C54,Assumptions!$A$44:$A$46,0))*$C$34,0),IF(Y$45=MAX($G54-1,1),INDEX(Assumptions!$E$44:$E$46,MATCH($C54,Assumptions!$A$44:$A$46,0)),0))*IF(AND($C54="Verified",$C$39=1),0,1) -> 0
A121: =A55 -> 8 | B121: =B55 -> A | C121: =C55 -> Assured | H121: =IF($F55=1,IF(H$45=1,INDEX(Assumptions!$E$44:$E$46,MATCH($C55,Assumptions!$A$44:$A$46,0))*$C$34,0),IF(H$45=MAX($G55-1,1),INDEX(Assumptions!$E$44:$E$46,MATCH($C55,Assumptions!$A$44:$A$46,0)),0))*IF(AND($C55="Verified",$C$39=1),0,1) -> 0 | I121: =IF($F55=1,IF(I$45=1,INDEX(Assumptions!$E$44:$E$46,MATCH($C55,Assumptions!$A$44:$A$46,0))*$C$34,0),IF(I$45=MAX($G55-1,1),INDEX(Assumptions!$E$44:$E$46,MATCH($C55,Assumptions!$A$44:$A$46,0)),0))*IF(AND($C55="Verified",$C$39=1),0,1) -> 0 | J121: =IF($F55=1,IF(J$45=1,INDEX(Assumptions!$E$44:$E$46,MATCH($C55,Assumptions!$A$44:$A$46,0))*$C$34,0),IF(J$45=MAX($G55-1,1),INDEX(Assumptions!$E$44:$E$46,MATCH($C55,Assumptions!$A$44:$A$46,0)),0))*IF(AND($C55="Verified",$C$39=1),0,1) -> 120000 | K121: =IF($F55=1,IF(K$45=1,INDEX(Assumptions!$E$44:$E$46,MATCH($C55,Assumptions!$A$44:$A$46,0))*$C$34,0),IF(K$45=MAX($G55-1,1),INDEX(Assumptions!$E$44:$E$46,MATCH($C55,Assumptions!$A$44:$A$46,0)),0))*IF(AND($C55="Verified",$C$39=1),0,1) -> 0 | L121: =IF($F55=1,IF(L$45=1,INDEX(Assumptions!$E$44:$E$46,MATCH($C55,Assumptions!$A$44:$A$46,0))*$C$34,0),IF(L$45=MAX($G55-1,1),INDEX(Assumptions!$E$44:$E$46,MATCH($C55,Assumptions!$A$44:$A$46,0)),0))*IF(AND($C55="Verified",$C$39=1),0,1) -> 0 | M121: =IF($F55=1,IF(M$45=1,INDEX(Assumptions!$E$44:$E$46,MATCH($C55,Assumptions!$A$44:$A$46,0))*$C$34,0),IF(M$45=MAX($G55-1,1),INDEX(Assumptions!$E$44:$E$46,MATCH($C55,Assumptions!$A$44:$A$46,0)),0))*IF(AND($C55="Verified",$C$39=1),0,1) -> 0 | N121: =IF($F55=1,IF(N$45=1,INDEX(Assumptions!$E$44:$E$46,MATCH($C55,Assumptions!$A$44:$A$46,0))*$C$34,0),IF(N$45=MAX($G55-1,1),INDEX(Assumptions!$E$44:$E$46,MATCH($C55,Assumptions!$A$44:$A$46,0)),0))*IF(AND($C55="Verified",$C$39=1),0,1) -> 0 | O121: =IF($F55=1,IF(O$45=1,INDEX(Assumptions!$E$44:$E$46,MATCH($C55,Assumptions!$A$44:$A$46,0))*$C$34,0),IF(O$45=MAX($G55-1,1),INDEX(Assumptions!$E$44:$E$46,MATCH($C55,Assumptions!$A$44:$A$46,0)),0))*IF(AND($C55="Verified",$C$39=1),0,1) -> 0 | ... Y121: =IF($F55=1,IF(Y$45=1,INDEX(Assumptions!$E$44:$E$46,MATCH($C55,Assumptions!$A$44:$A$46,0))*$C$34,0),IF(Y$45=MAX($G55-1,1),INDEX(Assumptions!$E$44:$E$46,MATCH($C55,Assumptions!$A$44:$A$46,0)),0))*IF(AND($C55="Verified",$C$39=1),0,1) -> 0
A122: =A56 -> 9 | B122: =B56 -> A | C122: =C56 -> Assured | H122: =IF($F56=1,IF(H$45=1,INDEX(Assumptions!$E$44:$E$46,MATCH($C56,Assumptions!$A$44:$A$46,0))*$C$34,0),IF(H$45=MAX($G56-1,1),INDEX(Assumptions!$E$44:$E$46,MATCH($C56,Assumptions!$A$44:$A$46,0)),0))*IF(AND($C56="Verified",$C$39=1),0,1) -> 0 | I122: =IF($F56=1,IF(I$45=1,INDEX(Assumptions!$E$44:$E$46,MATCH($C56,Assumptions!$A$44:$A$46,0))*$C$34,0),IF(I$45=MAX($G56-1,1),INDEX(Assumptions!$E$44:$E$46,MATCH($C56,Assumptions!$A$44:$A$46,0)),0))*IF(AND($C56="Verified",$C$39=1),0,1) -> 0 | J122: =IF($F56=1,IF(J$45=1,INDEX(Assumptions!$E$44:$E$46,MATCH($C56,Assumptions!$A$44:$A$46,0))*$C$34,0),IF(J$45=MAX($G56-1,1),INDEX(Assumptions!$E$44:$E$46,MATCH($C56,Assumptions!$A$44:$A$46,0)),0))*IF(AND($C56="Verified",$C$39=1),0,1) -> 0 | K122: =IF($F56=1,IF(K$45=1,INDEX(Assumptions!$E$44:$E$46,MATCH($C56,Assumptions!$A$44:$A$46,0))*$C$34,0),IF(K$45=MAX($G56-1,1),INDEX(Assumptions!$E$44:$E$46,MATCH($C56,Assumptions!$A$44:$A$46,0)),0))*IF(AND($C56="Verified",$C$39=1),0,1) -> 120000 | L122: =IF($F56=1,IF(L$45=1,INDEX(Assumptions!$E$44:$E$46,MATCH($C56,Assumptions!$A$44:$A$46,0))*$C$34,0),IF(L$45=MAX($G56-1,1),INDEX(Assumptions!$E$44:$E$46,MATCH($C56,Assumptions!$A$44:$A$46,0)),0))*IF(AND($C56="Verified",$C$39=1),0,1) -> 0 | M122: =IF($F56=1,IF(M$45=1,INDEX(Assumptions!$E$44:$E$46,MATCH($C56,Assumptions!$A$44:$A$46,0))*$C$34,0),IF(M$45=MAX($G56-1,1),INDEX(Assumptions!$E$44:$E$46,MATCH($C56,Assumptions!$A$44:$A$46,0)),0))*IF(AND($C56="Verified",$C$39=1),0,1) -> 0 | N122: =IF($F56=1,IF(N$45=1,INDEX(Assumptions!$E$44:$E$46,MATCH($C56,Assumptions!$A$44:$A$46,0))*$C$34,0),IF(N$45=MAX($G56-1,1),INDEX(Assumptions!$E$44:$E$46,MATCH($C56,Assumptions!$A$44:$A$46,0)),0))*IF(AND($C56="Verified",$C$39=1),0,1) -> 0 | O122: =IF($F56=1,IF(O$45=1,INDEX(Assumptions!$E$44:$E$46,MATCH($C56,Assumptions!$A$44:$A$46,0))*$C$34,0),IF(O$45=MAX($G56-1,1),INDEX(Assumptions!$E$44:$E$46,MATCH($C56,Assumptions!$A$44:$A$46,0)),0))*IF(AND($C56="Verified",$C$39=1),0,1) -> 0 | ... Y122: =IF($F56=1,IF(Y$45=1,INDEX(Assumptions!$E$44:$E$46,MATCH($C56,Assumptions!$A$44:$A$46,0))*$C$34,0),IF(Y$45=MAX($G56-1,1),INDEX(Assumptions!$E$44:$E$46,MATCH($C56,Assumptions!$A$44:$A$46,0)),0))*IF(AND($C56="Verified",$C$39=1),0,1) -> 0
A123: =A57 -> 10 | B123: =B57 -> C | C123: =C57 -> Assured | H123: =IF($F57=1,IF(H$45=1,INDEX(Assumptions!$E$44:$E$46,MATCH($C57,Assumptions!$A$44:$A$46,0))*$C$34,0),IF(H$45=MAX($G57-1,1),INDEX(Assumptions!$E$44:$E$46,MATCH($C57,Assumptions!$A$44:$A$46,0)),0))*IF(AND($C57="Verified",$C$39=1),0,1) -> 0 | I123: =IF($F57=1,IF(I$45=1,INDEX(Assumptions!$E$44:$E$46,MATCH($C57,Assumptions!$A$44:$A$46,0))*$C$34,0),IF(I$45=MAX($G57-1,1),INDEX(Assumptions!$E$44:$E$46,MATCH($C57,Assumptions!$A$44:$A$46,0)),0))*IF(AND($C57="Verified",$C$39=1),0,1) -> 0 | J123: =IF($F57=1,IF(J$45=1,INDEX(Assumptions!$E$44:$E$46,MATCH($C57,Assumptions!$A$44:$A$46,0))*$C$34,0),IF(J$45=MAX($G57-1,1),INDEX(Assumptions!$E$44:$E$46,MATCH($C57,Assumptions!$A$44:$A$46,0)),0))*IF(AND($C57="Verified",$C$39=1),0,1) -> 0 | K123: =IF($F57=1,IF(K$45=1,INDEX(Assumptions!$E$44:$E$46,MATCH($C57,Assumptions!$A$44:$A$46,0))*$C$34,0),IF(K$45=MAX($G57-1,1),INDEX(Assumptions!$E$44:$E$46,MATCH($C57,Assumptions!$A$44:$A$46,0)),0))*IF(AND($C57="Verified",$C$39=1),0,1) -> 0 | L123: =IF($F57=1,IF(L$45=1,INDEX(Assumptions!$E$44:$E$46,MATCH($C57,Assumptions!$A$44:$A$46,0))*$C$34,0),IF(L$45=MAX($G57-1,1),INDEX(Assumptions!$E$44:$E$46,MATCH($C57,Assumptions!$A$44:$A$46,0)),0))*IF(AND($C57="Verified",$C$39=1),0,1) -> 120000 | M123: =IF($F57=1,IF(M$45=1,INDEX(Assumptions!$E$44:$E$46,MATCH($C57,Assumptions!$A$44:$A$46,0))*$C$34,0),IF(M$45=MAX($G57-1,1),INDEX(Assumptions!$E$44:$E$46,MATCH($C57,Assumptions!$A$44:$A$46,0)),0))*IF(AND($C57="Verified",$C$39=1),0,1) -> 0 | N123: =IF($F57=1,IF(N$45=1,INDEX(Assumptions!$E$44:$E$46,MATCH($C57,Assumptions!$A$44:$A$46,0))*$C$34,0),IF(N$45=MAX($G57-1,1),INDEX(Assumptions!$E$44:$E$46,MATCH($C57,Assumptions!$A$44:$A$46,0)),0))*IF(AND($C57="Verified",$C$39=1),0,1) -> 0 | O123: =IF($F57=1,IF(O$45=1,INDEX(Assumptions!$E$44:$E$46,MATCH($C57,Assumptions!$A$44:$A$46,0))*$C$34,0),IF(O$45=MAX($G57-1,1),INDEX(Assumptions!$E$44:$E$46,MATCH($C57,Assumptions!$A$44:$A$46,0)),0))*IF(AND($C57="Verified",$C$39=1),0,1) -> 0 | ... Y123: =IF($F57=1,IF(Y$45=1,INDEX(Assumptions!$E$44:$E$46,MATCH($C57,Assumptions!$A$44:$A$46,0))*$C$34,0),IF(Y$45=MAX($G57-1,1),INDEX(Assumptions!$E$44:$E$46,MATCH($C57,Assumptions!$A$44:$A$46,0)),0))*IF(AND($C57="Verified",$C$39=1),0,1) -> 0
A124: =A58 -> 11 | B124: =B58 -> C | C124: =C58 -> Assured | H124: =IF($F58=1,IF(H$45=1,INDEX(Assumptions!$E$44:$E$46,MATCH($C58,Assumptions!$A$44:$A$46,0))*$C$34,0),IF(H$45=MAX($G58-1,1),INDEX(Assumptions!$E$44:$E$46,MATCH($C58,Assumptions!$A$44:$A$46,0)),0))*IF(AND($C58="Verified",$C$39=1),0,1) -> 0 | I124: =IF($F58=1,IF(I$45=1,INDEX(Assumptions!$E$44:$E$46,MATCH($C58,Assumptions!$A$44:$A$46,0))*$C$34,0),IF(I$45=MAX($G58-1,1),INDEX(Assumptions!$E$44:$E$46,MATCH($C58,Assumptions!$A$44:$A$46,0)),0))*IF(AND($C58="Verified",$C$39=1),0,1) -> 0 | J124: =IF($F58=1,IF(J$45=1,INDEX(Assumptions!$E$44:$E$46,MATCH($C58,Assumptions!$A$44:$A$46,0))*$C$34,0),IF(J$45=MAX($G58-1,1),INDEX(Assumptions!$E$44:$E$46,MATCH($C58,Assumptions!$A$44:$A$46,0)),0))*IF(AND($C58="Verified",$C$39=1),0,1) -> 0 | K124: =IF($F58=1,IF(K$45=1,INDEX(Assumptions!$E$44:$E$46,MATCH($C58,Assumptions!$A$44:$A$46,0))*$C$34,0),IF(K$45=MAX($G58-1,1),INDEX(Assumptions!$E$44:$E$46,MATCH($C58,Assumptions!$A$44:$A$46,0)),0))*IF(AND($C58="Verified",$C$39=1),0,1) -> 0 | L124: =IF($F58=1,IF(L$45=1,INDEX(Assumptions!$E$44:$E$46,MATCH($C58,Assumptions!$A$44:$A$46,0))*$C$34,0),IF(L$45=MAX($G58-1,1),INDEX(Assumptions!$E$44:$E$46,MATCH($C58,Assumptions!$A$44:$A$46,0)),0))*IF(AND($C58="Verified",$C$39=1),0,1) -> 0 | M124: =IF($F58=1,IF(M$45=1,INDEX(Assumptions!$E$44:$E$46,MATCH($C58,Assumptions!$A$44:$A$46,0))*$C$34,0),IF(M$45=MAX($G58-1,1),INDEX(Assumptions!$E$44:$E$46,MATCH($C58,Assumptions!$A$44:$A$46,0)),0))*IF(AND($C58="Verified",$C$39=1),0,1) -> 120000 | N124: =IF($F58=1,IF(N$45=1,INDEX(Assumptions!$E$44:$E$46,MATCH($C58,Assumptions!$A$44:$A$46,0))*$C$34,0),IF(N$45=MAX($G58-1,1),INDEX(Assumptions!$E$44:$E$46,MATCH($C58,Assumptions!$A$44:$A$46,0)),0))*IF(AND($C58="Verified",$C$39=1),0,1) -> 0 | O124: =IF($F58=1,IF(O$45=1,INDEX(Assumptions!$E$44:$E$46,MATCH($C58,Assumptions!$A$44:$A$46,0))*$C$34,0),IF(O$45=MAX($G58-1,1),INDEX(Assumptions!$E$44:$E$46,MATCH($C58,Assumptions!$A$44:$A$46,0)),0))*IF(AND($C58="Verified",$C$39=1),0,1) -> 0 | ... Y124: =IF($F58=1,IF(Y$45=1,INDEX(Assumptions!$E$44:$E$46,MATCH($C58,Assumptions!$A$44:$A$46,0))*$C$34,0),IF(Y$45=MAX($G58-1,1),INDEX(Assumptions!$E$44:$E$46,MATCH($C58,Assumptions!$A$44:$A$46,0)),0))*IF(AND($C58="Verified",$C$39=1),0,1) -> 0
A125: =A59 -> 12 | B125: =B59 -> C | C125: =C59 -> Assured | H125: =IF($F59=1,IF(H$45=1,INDEX(Assumptions!$E$44:$E$46,MATCH($C59,Assumptions!$A$44:$A$46,0))*$C$34,0),IF(H$45=MAX($G59-1,1),INDEX(Assumptions!$E$44:$E$46,MATCH($C59,Assumptions!$A$44:$A$46,0)),0))*IF(AND($C59="Verified",$C$39=1),0,1) -> 0 | I125: =IF($F59=1,IF(I$45=1,INDEX(Assumptions!$E$44:$E$46,MATCH($C59,Assumptions!$A$44:$A$46,0))*$C$34,0),IF(I$45=MAX($G59-1,1),INDEX(Assumptions!$E$44:$E$46,MATCH($C59,Assumptions!$A$44:$A$46,0)),0))*IF(AND($C59="Verified",$C$39=1),0,1) -> 0 | J125: =IF($F59=1,IF(J$45=1,INDEX(Assumptions!$E$44:$E$46,MATCH($C59,Assumptions!$A$44:$A$46,0))*$C$34,0),IF(J$45=MAX($G59-1,1),INDEX(Assumptions!$E$44:$E$46,MATCH($C59,Assumptions!$A$44:$A$46,0)),0))*IF(AND($C59="Verified",$C$39=1),0,1) -> 0 | K125: =IF($F59=1,IF(K$45=1,INDEX(Assumptions!$E$44:$E$46,MATCH($C59,Assumptions!$A$44:$A$46,0))*$C$34,0),IF(K$45=MAX($G59-1,1),INDEX(Assumptions!$E$44:$E$46,MATCH($C59,Assumptions!$A$44:$A$46,0)),0))*IF(AND($C59="Verified",$C$39=1),0,1) -> 0 | L125: =IF($F59=1,IF(L$45=1,INDEX(Assumptions!$E$44:$E$46,MATCH($C59,Assumptions!$A$44:$A$46,0))*$C$34,0),IF(L$45=MAX($G59-1,1),INDEX(Assumptions!$E$44:$E$46,MATCH($C59,Assumptions!$A$44:$A$46,0)),0))*IF(AND($C59="Verified",$C$39=1),0,1) -> 0 | M125: =IF($F59=1,IF(M$45=1,INDEX(Assumptions!$E$44:$E$46,MATCH($C59,Assumptions!$A$44:$A$46,0))*$C$34,0),IF(M$45=MAX($G59-1,1),INDEX(Assumptions!$E$44:$E$46,MATCH($C59,Assumptions!$A$44:$A$46,0)),0))*IF(AND($C59="Verified",$C$39=1),0,1) -> 120000 | N125: =IF($F59=1,IF(N$45=1,INDEX(Assumptions!$E$44:$E$46,MATCH($C59,Assumptions!$A$44:$A$46,0))*$C$34,0),IF(N$45=MAX($G59-1,1),INDEX(Assumptions!$E$44:$E$46,MATCH($C59,Assumptions!$A$44:$A$46,0)),0))*IF(AND($C59="Verified",$C$39=1),0,1) -> 0 | O125: =IF($F59=1,IF(O$45=1,INDEX(Assumptions!$E$44:$E$46,MATCH($C59,Assumptions!$A$44:$A$46,0))*$C$34,0),IF(O$45=MAX($G59-1,1),INDEX(Assumptions!$E$44:$E$46,MATCH($C59,Assumptions!$A$44:$A$46,0)),0))*IF(AND($C59="Verified",$C$39=1),0,1) -> 0 | ... Y125: =IF($F59=1,IF(Y$45=1,INDEX(Assumptions!$E$44:$E$46,MATCH($C59,Assumptions!$A$44:$A$46,0))*$C$34,0),IF(Y$45=MAX($G59-1,1),INDEX(Assumptions!$E$44:$E$46,MATCH($C59,Assumptions!$A$44:$A$46,0)),0))*IF(AND($C59="Verified",$C$39=1),0,1) -> 0
... A133: =A67 -> 20 | B133: =B67 -> B | C133: =C67 -> Verified | H133: =IF($F67=1,IF(H$45=1,INDEX(Assumptions!$E$44:$E$46,MATCH($C67,Assumptions!$A$44:$A$46,0))*$C$34,0),IF(H$45=MAX($G67-1,1),INDEX(Assumptions!$E$44:$E$46,MATCH($C67,Assumptions!$A$44:$A$46,0)),0))*IF(AND($C67="Verified",$C$39=1),0,1) -> 0 | I133: =IF($F67=1,IF(I$45=1,INDEX(Assumptions!$E$44:$E$46,MATCH($C67,Assumptions!$A$44:$A$46,0))*$C$34,0),IF(I$45=MAX($G67-1,1),INDEX(Assumptions!$E$44:$E$46,MATCH($C67,Assumptions!$A$44:$A$46,0)),0))*IF(AND($C67="Verified",$C$39=1),0,1) -> 0 | J133: =IF($F67=1,IF(J$45=1,INDEX(Assumptions!$E$44:$E$46,MATCH($C67,Assumptions!$A$44:$A$46,0))*$C$34,0),IF(J$45=MAX($G67-1,1),INDEX(Assumptions!$E$44:$E$46,MATCH($C67,Assumptions!$A$44:$A$46,0)),0))*IF(AND($C67="Verified",$C$39=1),0,1) -> 0 | K133: =IF($F67=1,IF(K$45=1,INDEX(Assumptions!$E$44:$E$46,MATCH($C67,Assumptions!$A$44:$A$46,0))*$C$34,0),IF(K$45=MAX($G67-1,1),INDEX(Assumptions!$E$44:$E$46,MATCH($C67,Assumptions!$A$44:$A$46,0)),0))*IF(AND($C67="Verified",$C$39=1),0,1) -> 0 | L133: =IF($F67=1,IF(L$45=1,INDEX(Assumptions!$E$44:$E$46,MATCH($C67,Assumptions!$A$44:$A$46,0))*$C$34,0),IF(L$45=MAX($G67-1,1),INDEX(Assumptions!$E$44:$E$46,MATCH($C67,Assumptions!$A$44:$A$46,0)),0))*IF(AND($C67="Verified",$C$39=1),0,1) -> 0 | M133: =IF($F67=1,IF(M$45=1,INDEX(Assumptions!$E$44:$E$46,MATCH($C67,Assumptions!$A$44:$A$46,0))*$C$34,0),IF(M$45=MAX($G67-1,1),INDEX(Assumptions!$E$44:$E$46,MATCH($C67,Assumptions!$A$44:$A$46,0)),0))*IF(AND($C67="Verified",$C$39=1),0,1) -> 0 | N133: =IF($F67=1,IF(N$45=1,INDEX(Assumptions!$E$44:$E$46,MATCH($C67,Assumptions!$A$44:$A$46,0))*$C$34,0),IF(N$45=MAX($G67-1,1),INDEX(Assumptions!$E$44:$E$46,MATCH($C67,Assumptions!$A$44:$A$46,0)),0))*IF(AND($C67="Verified",$C$39=1),0,1) -> 0 | O133: =IF($F67=1,IF(O$45=1,INDEX(Assumptions!$E$44:$E$46,MATCH($C67,Assumptions!$A$44:$A$46,0))*$C$34,0),IF(O$45=MAX($G67-1,1),INDEX(Assumptions!$E$44:$E$46,MATCH($C67,Assumptions!$A$44:$A$46,0)),0))*IF(AND($C67="Verified",$C$39=1),0,1) -> 0 | ... Y133: =IF($F67=1,IF(Y$45=1,INDEX(Assumptions!$E$44:$E$46,MATCH($C67,Assumptions!$A$44:$A$46,0))*$C$34,0),IF(Y$45=MAX($G67-1,1),INDEX(Assumptions!$E$44:$E$46,MATCH($C67,Assumptions!$A$44:$A$46,0)),0))*IF(AND($C67="Verified",$C$39=1),0,1) -> 0
A135: On-time-weighted bookings per host
A136: =A48 -> 1 | B136: =B48 -> Pilot | C136: =C48 -> Assured | H136: =H48*($C$30+(INDEX(Assumptions!$F$44:$F$46,MATCH($C48,Assumptions!$A$44:$A$46,0))-$C$30)*MIN(1,H$45/$C$29)) -> 14.116667 | I136: =I48*($C$30+(INDEX(Assumptions!$F$44:$F$46,MATCH($C48,Assumptions!$A$44:$A$46,0))-$C$30)*MIN(1,I$45/$C$29)) -> 15.277778 | J136: =J48*($C$30+(INDEX(Assumptions!$F$44:$F$46,MATCH($C48,Assumptions!$A$44:$A$46,0))-$C$30)*MIN(1,J$45/$C$29)) -> 16.483333 | K136: =K48*($C$30+(INDEX(Assumptions!$F$44:$F$46,MATCH($C48,Assumptions!$A$44:$A$46,0))-$C$30)*MIN(1,K$45/$C$29)) -> 17.733333 | L136: =L48*($C$30+(INDEX(Assumptions!$F$44:$F$46,MATCH($C48,Assumptions!$A$44:$A$46,0))-$C$30)*MIN(1,L$45/$C$29)) -> 18.266667 | M136: =M48*($C$30+(INDEX(Assumptions!$F$44:$F$46,MATCH($C48,Assumptions!$A$44:$A$46,0))-$C$30)*MIN(1,M$45/$C$29)) -> 18.8 | N136: =N48*($C$30+(INDEX(Assumptions!$F$44:$F$46,MATCH($C48,Assumptions!$A$44:$A$46,0))-$C$30)*MIN(1,N$45/$C$29)) -> 18.8 | O136: =O48*($C$30+(INDEX(Assumptions!$F$44:$F$46,MATCH($C48,Assumptions!$A$44:$A$46,0))-$C$30)*MIN(1,O$45/$C$29)) -> 18.8 | ... Y136: =Y48*($C$30+(INDEX(Assumptions!$F$44:$F$46,MATCH($C48,Assumptions!$A$44:$A$46,0))-$C$30)*MIN(1,Y$45/$C$29)) -> 18.8
A137: =A49 -> 2 | B137: =B49 -> Pilot | C137: =C49 -> Assured | H137: =H49*($C$30+(INDEX(Assumptions!$F$44:$F$46,MATCH($C49,Assumptions!$A$44:$A$46,0))-$C$30)*MIN(1,H$45/$C$29)) -> 14.116667 | I137: =I49*($C$30+(INDEX(Assumptions!$F$44:$F$46,MATCH($C49,Assumptions!$A$44:$A$46,0))-$C$30)*MIN(1,I$45/$C$29)) -> 15.277778 | J137: =J49*($C$30+(INDEX(Assumptions!$F$44:$F$46,MATCH($C49,Assumptions!$A$44:$A$46,0))-$C$30)*MIN(1,J$45/$C$29)) -> 16.483333 | K137: =K49*($C$30+(INDEX(Assumptions!$F$44:$F$46,MATCH($C49,Assumptions!$A$44:$A$46,0))-$C$30)*MIN(1,K$45/$C$29)) -> 17.733333 | L137: =L49*($C$30+(INDEX(Assumptions!$F$44:$F$46,MATCH($C49,Assumptions!$A$44:$A$46,0))-$C$30)*MIN(1,L$45/$C$29)) -> 18.266667 | M137: =M49*($C$30+(INDEX(Assumptions!$F$44:$F$46,MATCH($C49,Assumptions!$A$44:$A$46,0))-$C$30)*MIN(1,M$45/$C$29)) -> 18.8 | N137: =N49*($C$30+(INDEX(Assumptions!$F$44:$F$46,MATCH($C49,Assumptions!$A$44:$A$46,0))-$C$30)*MIN(1,N$45/$C$29)) -> 18.8 | O137: =O49*($C$30+(INDEX(Assumptions!$F$44:$F$46,MATCH($C49,Assumptions!$A$44:$A$46,0))-$C$30)*MIN(1,O$45/$C$29)) -> 18.8 | ... Y137: =Y49*($C$30+(INDEX(Assumptions!$F$44:$F$46,MATCH($C49,Assumptions!$A$44:$A$46,0))-$C$30)*MIN(1,Y$45/$C$29)) -> 18.8
A138: =A50 -> 3 | B138: =B50 -> Pilot | C138: =C50 -> Assured | H138: =H50*($C$30+(INDEX(Assumptions!$F$44:$F$46,MATCH($C50,Assumptions!$A$44:$A$46,0))-$C$30)*MIN(1,H$45/$C$29)) -> 14.116667 | I138: =I50*($C$30+(INDEX(Assumptions!$F$44:$F$46,MATCH($C50,Assumptions!$A$44:$A$46,0))-$C$30)*MIN(1,I$45/$C$29)) -> 15.277778 | J138: =J50*($C$30+(INDEX(Assumptions!$F$44:$F$46,MATCH($C50,Assumptions!$A$44:$A$46,0))-$C$30)*MIN(1,J$45/$C$29)) -> 16.483333 | K138: =K50*($C$30+(INDEX(Assumptions!$F$44:$F$46,MATCH($C50,Assumptions!$A$44:$A$46,0))-$C$30)*MIN(1,K$45/$C$29)) -> 17.733333 | L138: =L50*($C$30+(INDEX(Assumptions!$F$44:$F$46,MATCH($C50,Assumptions!$A$44:$A$46,0))-$C$30)*MIN(1,L$45/$C$29)) -> 18.266667 | M138: =M50*($C$30+(INDEX(Assumptions!$F$44:$F$46,MATCH($C50,Assumptions!$A$44:$A$46,0))-$C$30)*MIN(1,M$45/$C$29)) -> 18.8 | N138: =N50*($C$30+(INDEX(Assumptions!$F$44:$F$46,MATCH($C50,Assumptions!$A$44:$A$46,0))-$C$30)*MIN(1,N$45/$C$29)) -> 18.8 | O138: =O50*($C$30+(INDEX(Assumptions!$F$44:$F$46,MATCH($C50,Assumptions!$A$44:$A$46,0))-$C$30)*MIN(1,O$45/$C$29)) -> 18.8 | ... Y138: =Y50*($C$30+(INDEX(Assumptions!$F$44:$F$46,MATCH($C50,Assumptions!$A$44:$A$46,0))-$C$30)*MIN(1,Y$45/$C$29)) -> 18.8
A139: =A51 -> 4 | B139: =B51 -> Pilot | C139: =C51 -> Assured | H139: =H51*($C$30+(INDEX(Assumptions!$F$44:$F$46,MATCH($C51,Assumptions!$A$44:$A$46,0))-$C$30)*MIN(1,H$45/$C$29)) -> 14.116667 | I139: =I51*($C$30+(INDEX(Assumptions!$F$44:$F$46,MATCH($C51,Assumptions!$A$44:$A$46,0))-$C$30)*MIN(1,I$45/$C$29)) -> 15.277778 | J139: =J51*($C$30+(INDEX(Assumptions!$F$44:$F$46,MATCH($C51,Assumptions!$A$44:$A$46,0))-$C$30)*MIN(1,J$45/$C$29)) -> 16.483333 | K139: =K51*($C$30+(INDEX(Assumptions!$F$44:$F$46,MATCH($C51,Assumptions!$A$44:$A$46,0))-$C$30)*MIN(1,K$45/$C$29)) -> 17.733333 | L139: =L51*($C$30+(INDEX(Assumptions!$F$44:$F$46,MATCH($C51,Assumptions!$A$44:$A$46,0))-$C$30)*MIN(1,L$45/$C$29)) -> 18.266667 | M139: =M51*($C$30+(INDEX(Assumptions!$F$44:$F$46,MATCH($C51,Assumptions!$A$44:$A$46,0))-$C$30)*MIN(1,M$45/$C$29)) -> 18.8 | N139: =N51*($C$30+(INDEX(Assumptions!$F$44:$F$46,MATCH($C51,Assumptions!$A$44:$A$46,0))-$C$30)*MIN(1,N$45/$C$29)) -> 18.8 | O139: =O51*($C$30+(INDEX(Assumptions!$F$44:$F$46,MATCH($C51,Assumptions!$A$44:$A$46,0))-$C$30)*MIN(1,O$45/$C$29)) -> 18.8 | ... Y139: =Y51*($C$30+(INDEX(Assumptions!$F$44:$F$46,MATCH($C51,Assumptions!$A$44:$A$46,0))-$C$30)*MIN(1,Y$45/$C$29)) -> 18.8
A140: =A52 -> 5 | B140: =B52 -> A | C140: =C52 -> Assured | H140: =H52*($C$30+(INDEX(Assumptions!$F$44:$F$46,MATCH($C52,Assumptions!$A$44:$A$46,0))-$C$30)*MIN(1,H$45/$C$29)) -> 0 | I140: =I52*($C$30+(INDEX(Assumptions!$F$44:$F$46,MATCH($C52,Assumptions!$A$44:$A$46,0))-$C$30)*MIN(1,I$45/$C$29)) -> 0 | J140: =J52*($C$30+(INDEX(Assumptions!$F$44:$F$46,MATCH($C52,Assumptions!$A$44:$A$46,0))-$C$30)*MIN(1,J$45/$C$29)) -> 5.2632 | K140: =K52*($C$30+(INDEX(Assumptions!$F$44:$F$46,MATCH($C52,Assumptions!$A$44:$A$46,0))-$C$30)*MIN(1,K$45/$C$29)) -> 10.8528 | L140: =L52*($C$30+(INDEX(Assumptions!$F$44:$F$46,MATCH($C52,Assumptions!$A$44:$A$46,0))-$C$30)*MIN(1,L$45/$C$29)) -> 15.8372 | M140: =M52*($C$30+(INDEX(Assumptions!$F$44:$F$46,MATCH($C52,Assumptions!$A$44:$A$46,0))-$C$30)*MIN(1,M$45/$C$29)) -> 19.176 | N140: =N52*($C$30+(INDEX(Assumptions!$F$44:$F$46,MATCH($C52,Assumptions!$A$44:$A$46,0))-$C$30)*MIN(1,N$45/$C$29)) -> 19.176 | O140: =O52*($C$30+(INDEX(Assumptions!$F$44:$F$46,MATCH($C52,Assumptions!$A$44:$A$46,0))-$C$30)*MIN(1,O$45/$C$29)) -> 19.176 | ... Y140: =Y52*($C$30+(INDEX(Assumptions!$F$44:$F$46,MATCH($C52,Assumptions!$A$44:$A$46,0))-$C$30)*MIN(1,Y$45/$C$29)) -> 19.176
A141: =A53 -> 6 | B141: =B53 -> A | C141: =C53 -> Assured | H141: =H53*($C$30+(INDEX(Assumptions!$F$44:$F$46,MATCH($C53,Assumptions!$A$44:$A$46,0))-$C$30)*MIN(1,H$45/$C$29)) -> 0 | I141: =I53*($C$30+(INDEX(Assumptions!$F$44:$F$46,MATCH($C53,Assumptions!$A$44:$A$46,0))-$C$30)*MIN(1,I$45/$C$29)) -> 0 | J141: =J53*($C$30+(INDEX(Assumptions!$F$44:$F$46,MATCH($C53,Assumptions!$A$44:$A$46,0))-$C$30)*MIN(1,J$45/$C$29)) -> 5.2632 | K141: =K53*($C$30+(INDEX(Assumptions!$F$44:$F$46,MATCH($C53,Assumptions!$A$44:$A$46,0))-$C$30)*MIN(1,K$45/$C$29)) -> 10.8528 | L141: =L53*($C$30+(INDEX(Assumptions!$F$44:$F$46,MATCH($C53,Assumptions!$A$44:$A$46,0))-$C$30)*MIN(1,L$45/$C$29)) -> 15.8372 | M141: =M53*($C$30+(INDEX(Assumptions!$F$44:$F$46,MATCH($C53,Assumptions!$A$44:$A$46,0))-$C$30)*MIN(1,M$45/$C$29)) -> 19.176 | N141: =N53*($C$30+(INDEX(Assumptions!$F$44:$F$46,MATCH($C53,Assumptions!$A$44:$A$46,0))-$C$30)*MIN(1,N$45/$C$29)) -> 19.176 | O141: =O53*($C$30+(INDEX(Assumptions!$F$44:$F$46,MATCH($C53,Assumptions!$A$44:$A$46,0))-$C$30)*MIN(1,O$45/$C$29)) -> 19.176 | ... Y141: =Y53*($C$30+(INDEX(Assumptions!$F$44:$F$46,MATCH($C53,Assumptions!$A$44:$A$46,0))-$C$30)*MIN(1,Y$45/$C$29)) -> 19.176
A142: =A54 -> 7 | B142: =B54 -> A | C142: =C54 -> Assured | H142: =H54*($C$30+(INDEX(Assumptions!$F$44:$F$46,MATCH($C54,Assumptions!$A$44:$A$46,0))-$C$30)*MIN(1,H$45/$C$29)) -> 0 | I142: =I54*($C$30+(INDEX(Assumptions!$F$44:$F$46,MATCH($C54,Assumptions!$A$44:$A$46,0))-$C$30)*MIN(1,I$45/$C$29)) -> 0 | J142: =J54*($C$30+(INDEX(Assumptions!$F$44:$F$46,MATCH($C54,Assumptions!$A$44:$A$46,0))-$C$30)*MIN(1,J$45/$C$29)) -> 0 | K142: =K54*($C$30+(INDEX(Assumptions!$F$44:$F$46,MATCH($C54,Assumptions!$A$44:$A$46,0))-$C$30)*MIN(1,K$45/$C$29)) -> 5.4264 | L142: =L54*($C$30+(INDEX(Assumptions!$F$44:$F$46,MATCH($C54,Assumptions!$A$44:$A$46,0))-$C$30)*MIN(1,L$45/$C$29)) -> 11.1792 | M142: =M54*($C$30+(INDEX(Assumptions!$F$44:$F$46,MATCH($C54,Assumptions!$A$44:$A$46,0))-$C$30)*MIN(1,M$45/$C$29)) -> 16.2996 | N142: =N54*($C$30+(INDEX(Assumptions!$F$44:$F$46,MATCH($C54,Assumptions!$A$44:$A$46,0))-$C$30)*MIN(1,N$45/$C$29)) -> 19.176 | O142: =O54*($C$30+(INDEX(Assumptions!$F$44:$F$46,MATCH($C54,Assumptions!$A$44:$A$46,0))-$C$30)*MIN(1,O$45/$C$29)) -> 19.176 | ... Y142: =Y54*($C$30+(INDEX(Assumptions!$F$44:$F$46,MATCH($C54,Assumptions!$A$44:$A$46,0))-$C$30)*MIN(1,Y$45/$C$29)) -> 19.176
A143: =A55 -> 8 | B143: =B55 -> A | C143: =C55 -> Assured | H143: =H55*($C$30+(INDEX(Assumptions!$F$44:$F$46,MATCH($C55,Assumptions!$A$44:$A$46,0))-$C$30)*MIN(1,H$45/$C$29)) -> 0 | I143: =I55*($C$30+(INDEX(Assumptions!$F$44:$F$46,MATCH($C55,Assumptions!$A$44:$A$46,0))-$C$30)*MIN(1,I$45/$C$29)) -> 0 | J143: =J55*($C$30+(INDEX(Assumptions!$F$44:$F$46,MATCH($C55,Assumptions!$A$44:$A$46,0))-$C$30)*MIN(1,J$45/$C$29)) -> 0 | K143: =K55*($C$30+(INDEX(Assumptions!$F$44:$F$46,MATCH($C55,Assumptions!$A$44:$A$46,0))-$C$30)*MIN(1,K$45/$C$29)) -> 5.4264 | L143: =L55*($C$30+(INDEX(Assumptions!$F$44:$F$46,MATCH($C55,Assumptions!$A$44:$A$46,0))-$C$30)*MIN(1,L$45/$C$29)) -> 11.1792 | M143: =M55*($C$30+(INDEX(Assumptions!$F$44:$F$46,MATCH($C55,Assumptions!$A$44:$A$46,0))-$C$30)*MIN(1,M$45/$C$29)) -> 16.2996 | N143: =N55*($C$30+(INDEX(Assumptions!$F$44:$F$46,MATCH($C55,Assumptions!$A$44:$A$46,0))-$C$30)*MIN(1,N$45/$C$29)) -> 19.176 | O143: =O55*($C$30+(INDEX(Assumptions!$F$44:$F$46,MATCH($C55,Assumptions!$A$44:$A$46,0))-$C$30)*MIN(1,O$45/$C$29)) -> 19.176 | ... Y143: =Y55*($C$30+(INDEX(Assumptions!$F$44:$F$46,MATCH($C55,Assumptions!$A$44:$A$46,0))-$C$30)*MIN(1,Y$45/$C$29)) -> 19.176
A144: =A56 -> 9 | B144: =B56 -> A | C144: =C56 -> Assured | H144: =H56*($C$30+(INDEX(Assumptions!$F$44:$F$46,MATCH($C56,Assumptions!$A$44:$A$46,0))-$C$30)*MIN(1,H$45/$C$29)) -> 0 | I144: =I56*($C$30+(INDEX(Assumptions!$F$44:$F$46,MATCH($C56,Assumptions!$A$44:$A$46,0))-$C$30)*MIN(1,I$45/$C$29)) -> 0 | J144: =J56*($C$30+(INDEX(Assumptions!$F$44:$F$46,MATCH($C56,Assumptions!$A$44:$A$46,0))-$C$30)*MIN(1,J$45/$C$29)) -> 0 | K144: =K56*($C$30+(INDEX(Assumptions!$F$44:$F$46,MATCH($C56,Assumptions!$A$44:$A$46,0))-$C$30)*MIN(1,K$45/$C$29)) -> 0 | L144: =L56*($C$30+(INDEX(Assumptions!$F$44:$F$46,MATCH($C56,Assumptions!$A$44:$A$46,0))-$C$30)*MIN(1,L$45/$C$29)) -> 5.5896 | M144: =M56*($C$30+(INDEX(Assumptions!$F$44:$F$46,MATCH($C56,Assumptions!$A$44:$A$46,0))-$C$30)*MIN(1,M$45/$C$29)) -> 11.5056 | N144: =N56*($C$30+(INDEX(Assumptions!$F$44:$F$46,MATCH($C56,Assumptions!$A$44:$A$46,0))-$C$30)*MIN(1,N$45/$C$29)) -> 16.2996 | O144: =O56*($C$30+(INDEX(Assumptions!$F$44:$F$46,MATCH($C56,Assumptions!$A$44:$A$46,0))-$C$30)*MIN(1,O$45/$C$29)) -> 19.176 | ... Y144: =Y56*($C$30+(INDEX(Assumptions!$F$44:$F$46,MATCH($C56,Assumptions!$A$44:$A$46,0))-$C$30)*MIN(1,Y$45/$C$29)) -> 19.176
A145: =A57 -> 10 | B145: =B57 -> C | C145: =C57 -> Assured | H145: =H57*($C$30+(INDEX(Assumptions!$F$44:$F$46,MATCH($C57,Assumptions!$A$44:$A$46,0))-$C$30)*MIN(1,H$45/$C$29)) -> 0 | I145: =I57*($C$30+(INDEX(Assumptions!$F$44:$F$46,MATCH($C57,Assumptions!$A$44:$A$46,0))-$C$30)*MIN(1,I$45/$C$29)) -> 0 | J145: =J57*($C$30+(INDEX(Assumptions!$F$44:$F$46,MATCH($C57,Assumptions!$A$44:$A$46,0))-$C$30)*MIN(1,J$45/$C$29)) -> 0 | K145: =K57*($C$30+(INDEX(Assumptions!$F$44:$F$46,MATCH($C57,Assumptions!$A$44:$A$46,0))-$C$30)*MIN(1,K$45/$C$29)) -> 0 | L145: =L57*($C$30+(INDEX(Assumptions!$F$44:$F$46,MATCH($C57,Assumptions!$A$44:$A$46,0))-$C$30)*MIN(1,L$45/$C$29)) -> 0 | M145: =M57*($C$30+(INDEX(Assumptions!$F$44:$F$46,MATCH($C57,Assumptions!$A$44:$A$46,0))-$C$30)*MIN(1,M$45/$C$29)) -> 6.2322 | N145: =N57*($C$30+(INDEX(Assumptions!$F$44:$F$46,MATCH($C57,Assumptions!$A$44:$A$46,0))-$C$30)*MIN(1,N$45/$C$29)) -> 12.4644 | O145: =O57*($C$30+(INDEX(Assumptions!$F$44:$F$46,MATCH($C57,Assumptions!$A$44:$A$46,0))-$C$30)*MIN(1,O$45/$C$29)) -> 17.6579 | ... Y145: =Y57*($C$30+(INDEX(Assumptions!$F$44:$F$46,MATCH($C57,Assumptions!$A$44:$A$46,0))-$C$30)*MIN(1,Y$45/$C$29)) -> 20.774
A146: =A58 -> 11 | B146: =B58 -> C | C146: =C58 -> Assured | H146: =H58*($C$30+(INDEX(Assumptions!$F$44:$F$46,MATCH($C58,Assumptions!$A$44:$A$46,0))-$C$30)*MIN(1,H$45/$C$29)) -> 0 | I146: =I58*($C$30+(INDEX(Assumptions!$F$44:$F$46,MATCH($C58,Assumptions!$A$44:$A$46,0))-$C$30)*MIN(1,I$45/$C$29)) -> 0 | J146: =J58*($C$30+(INDEX(Assumptions!$F$44:$F$46,MATCH($C58,Assumptions!$A$44:$A$46,0))-$C$30)*MIN(1,J$45/$C$29)) -> 0 | K146: =K58*($C$30+(INDEX(Assumptions!$F$44:$F$46,MATCH($C58,Assumptions!$A$44:$A$46,0))-$C$30)*MIN(1,K$45/$C$29)) -> 0 | L146: =L58*($C$30+(INDEX(Assumptions!$F$44:$F$46,MATCH($C58,Assumptions!$A$44:$A$46,0))-$C$30)*MIN(1,L$45/$C$29)) -> 0 | M146: =M58*($C$30+(INDEX(Assumptions!$F$44:$F$46,MATCH($C58,Assumptions!$A$44:$A$46,0))-$C$30)*MIN(1,M$45/$C$29)) -> 0 | N146: =N58*($C$30+(INDEX(Assumptions!$F$44:$F$46,MATCH($C58,Assumptions!$A$44:$A$46,0))-$C$30)*MIN(1,N$45/$C$29)) -> 6.2322 | O146: =O58*($C$30+(INDEX(Assumptions!$F$44:$F$46,MATCH($C58,Assumptions!$A$44:$A$46,0))-$C$30)*MIN(1,O$45/$C$29)) -> 12.4644 | ... Y146: =Y58*($C$30+(INDEX(Assumptions!$F$44:$F$46,MATCH($C58,Assumptions!$A$44:$A$46,0))-$C$30)*MIN(1,Y$45/$C$29)) -> 20.774
A147: =A59 -> 12 | B147: =B59 -> C | C147: =C59 -> Assured | H147: =H59*($C$30+(INDEX(Assumptions!$F$44:$F$46,MATCH($C59,Assumptions!$A$44:$A$46,0))-$C$30)*MIN(1,H$45/$C$29)) -> 0 | I147: =I59*($C$30+(INDEX(Assumptions!$F$44:$F$46,MATCH($C59,Assumptions!$A$44:$A$46,0))-$C$30)*MIN(1,I$45/$C$29)) -> 0 | J147: =J59*($C$30+(INDEX(Assumptions!$F$44:$F$46,MATCH($C59,Assumptions!$A$44:$A$46,0))-$C$30)*MIN(1,J$45/$C$29)) -> 0 | K147: =K59*($C$30+(INDEX(Assumptions!$F$44:$F$46,MATCH($C59,Assumptions!$A$44:$A$46,0))-$C$30)*MIN(1,K$45/$C$29)) -> 0 | L147: =L59*($C$30+(INDEX(Assumptions!$F$44:$F$46,MATCH($C59,Assumptions!$A$44:$A$46,0))-$C$30)*MIN(1,L$45/$C$29)) -> 0 | M147: =M59*($C$30+(INDEX(Assumptions!$F$44:$F$46,MATCH($C59,Assumptions!$A$44:$A$46,0))-$C$30)*MIN(1,M$45/$C$29)) -> 0 | N147: =N59*($C$30+(INDEX(Assumptions!$F$44:$F$46,MATCH($C59,Assumptions!$A$44:$A$46,0))-$C$30)*MIN(1,N$45/$C$29)) -> 6.2322 | O147: =O59*($C$30+(INDEX(Assumptions!$F$44:$F$46,MATCH($C59,Assumptions!$A$44:$A$46,0))-$C$30)*MIN(1,O$45/$C$29)) -> 12.4644 | ... Y147: =Y59*($C$30+(INDEX(Assumptions!$F$44:$F$46,MATCH($C59,Assumptions!$A$44:$A$46,0))-$C$30)*MIN(1,Y$45/$C$29)) -> 20.774
... A155: =A67 -> 20 | B155: =B67 -> B | C155: =C67 -> Verified | H155: =H67*($C$30+(INDEX(Assumptions!$F$44:$F$46,MATCH($C67,Assumptions!$A$44:$A$46,0))-$C$30)*MIN(1,H$45/$C$29)) -> 0 | I155: =I67*($C$30+(INDEX(Assumptions!$F$44:$F$46,MATCH($C67,Assumptions!$A$44:$A$46,0))-$C$30)*MIN(1,I$45/$C$29)) -> 0 | J155: =J67*($C$30+(INDEX(Assumptions!$F$44:$F$46,MATCH($C67,Assumptions!$A$44:$A$46,0))-$C$30)*MIN(1,J$45/$C$29)) -> 0 | K155: =K67*($C$30+(INDEX(Assumptions!$F$44:$F$46,MATCH($C67,Assumptions!$A$44:$A$46,0))-$C$30)*MIN(1,K$45/$C$29)) -> 0 | L155: =L67*($C$30+(INDEX(Assumptions!$F$44:$F$46,MATCH($C67,Assumptions!$A$44:$A$46,0))-$C$30)*MIN(1,L$45/$C$29)) -> 0 | M155: =M67*($C$30+(INDEX(Assumptions!$F$44:$F$46,MATCH($C67,Assumptions!$A$44:$A$46,0))-$C$30)*MIN(1,M$45/$C$29)) -> 0 | N155: =N67*($C$30+(INDEX(Assumptions!$F$44:$F$46,MATCH($C67,Assumptions!$A$44:$A$46,0))-$C$30)*MIN(1,N$45/$C$29)) -> 0 | O155: =O67*($C$30+(INDEX(Assumptions!$F$44:$F$46,MATCH($C67,Assumptions!$A$44:$A$46,0))-$C$30)*MIN(1,O$45/$C$29)) -> 0 | ... Y155: =Y67*($C$30+(INDEX(Assumptions!$F$44:$F$46,MATCH($C67,Assumptions!$A$44:$A$46,0))-$C$30)*MIN(1,Y$45/$C$29)) -> 20.91
A157: Monthly summary
A158: Active hosts | H158: =COUNTIF($G$48:$G$67,"<="&H$45) -> 4 | I158: =COUNTIF($G$48:$G$67,"<="&I$45) -> 4 | J158: =COUNTIF($G$48:$G$67,"<="&J$45) -> 6 | K158: =COUNTIF($G$48:$G$67,"<="&K$45) -> 8 | L158: =COUNTIF($G$48:$G$67,"<="&L$45) -> 9 | M158: =COUNTIF($G$48:$G$67,"<="&M$45) -> 10 | N158: =COUNTIF($G$48:$G$67,"<="&N$45) -> 12 | O158: =COUNTIF($G$48:$G$67,"<="&O$45) -> 13 | ... Y158: =COUNTIF($G$48:$G$67,"<="&Y$45) -> 20
A159: Bookings | H159: =SUM(H48:H67) -> 70 | I159: =SUM(I48:I67) -> 73.333333 | J159: =SUM(J48:J67) -> 88.906667 | K159: =SUM(K48:K67) -> 116.72 | L159: =SUM(L48:L67) -> 145.28 | M159: =SUM(M48:M67) -> 174.35 | N159: =SUM(N48:N67) -> 205.46 | O159: =SUM(O48:O67) -> 233.935 | ... Y159: =SUM(Y48:Y67) -> 448.9
A160: Cumulative bookings | H160: =H159 -> 70 | I160: =H160+I159 -> 143.33333 | J160: =I160+J159 -> 232.24 | K160: =J160+K159 -> 348.96 | L160: =K160+L159 -> 494.24 | M160: =L160+M159 -> 668.59 | N160: =M160+N159 -> 874.05 | O160: =N160+O159 -> 1107.985 | P160: =O160+P159 -> 1370.565 | ... Y160: =X160+Y159 -> 4845.075
A161: GMV (₹) | H161: =SUMPRODUCT(H48:H67,$D$48:$D$67)*$C$13 -> 595000 | I161: =SUMPRODUCT(I48:I67,$D$48:$D$67)*$C$13 -> 623333.33 | J161: =SUMPRODUCT(J48:J67,$D$48:$D$67)*$C$13 -> 798546.67 | K161: =SUMPRODUCT(K48:K67,$D$48:$D$67)*$C$13 -> 1120640 | L161: =SUMPRODUCT(L48:L67,$D$48:$D$67)*$C$13 -> 1463360 | M161: =SUMPRODUCT(M48:M67,$D$48:$D$67)*$C$13 -> 1785680 | N161: =SUMPRODUCT(N48:N67,$D$48:$D$67)*$C$13 -> 2079440 | O161: =SUMPRODUCT(O48:O67,$D$48:$D$67)*$C$13 -> 2319480 | ... Y161: =SUMPRODUCT(Y48:Y67,$D$48:$D$67)*$C$13 -> 3771450
A162: OpenBench revenue (₹) | H162: =SUM(H70:H89) -> 188912.5 | I162: =SUM(I70:I89) -> 197908.33 | J162: =SUM(J70:J89) -> 253538.57 | K162: =SUM(K70:K89) -> 355803.2 | L162: =SUM(L70:L89) -> 464616.8 | M162: =SUM(M70:M89) -> 566953.4 | N162: =SUM(N70:N89) -> 660222.2 | O162: =SUM(O70:O89) -> 736434.9 | ... Y162: =SUM(Y70:Y89) -> 1024176
A163: Effective take rate | H163: =IF(H161=0,0,H162/H161) -> 0.3175 | I163: =IF(I161=0,0,I162/I161) -> 0.3175 | J163: =IF(J161=0,0,J162/J161) -> 0.3175 | K163: =IF(K161=0,0,K162/K161) -> 0.3175 | L163: =IF(L161=0,0,L162/L161) -> 0.3175 | M163: =IF(M161=0,0,M162/M161) -> 0.3175 | N163: =IF(N161=0,0,N162/N161) -> 0.3175 | O163: =IF(O161=0,0,O162/O161) -> 0.3175 | ... Y163: =IF(Y161=0,0,Y162/Y161) -> 0.27156028
A164: Variable cost (₹) | H164: =SUM(H92:H111) -> 94500 | I164: =SUM(I92:I111) -> 99000 | J164: =SUM(J92:J111) -> 120024 | K164: =SUM(K92:K111) -> 157572 | L164: =SUM(L92:L111) -> 196128 | M164: =SUM(M92:M111) -> 235372.5 | N164: =SUM(N92:N111) -> 277371 | O164: =SUM(O92:O111) -> 315812.25 | ... Y164: =SUM(Y92:Y111) -> 416280
A165: Contribution (₹) | H165: =H162-H164 -> 94412.5 | I165: =I162-I164 -> 98908.333 | J165: =J162-J164 -> 133514.57 | K165: =K162-K164 -> 198231.2 | L165: =L162-L164 -> 268488.8 | M165: =M162-M164 -> 331580.9 | N165: =N162-N164 -> 382851.2 | O165: =O162-O164 -> 420622.65 | ... Y165: =Y162-Y164 -> 607896
A166: Contribution per booking (₹) | H166: =IF(H159=0,0,H165/H159) -> 1348.75 | I166: =IF(I159=0,0,I165/I159) -> 1348.75 | J166: =IF(J159=0,0,J165/J159) -> 1501.7385 | K166: =IF(K159=0,0,K165/K159) -> 1698.3482 | L166: =IF(L159=0,0,L165/L159) -> 1848.0782 | M166: =IF(M159=0,0,M165/M159) -> 1901.8119 | N166: =IF(N159=0,0,N165/N159) -> 1863.3856 | O166: =IF(O159=0,0,O165/O159) -> 1798.0321 | ... Y166: =IF(Y159=0,0,Y165/Y159) -> 1354.1902
A167: Fixed cost (₹) | H167: =($C$17+IF(H$45>=$C$19,$C$18,0)+$C$20*((H$45>=$C$21+$C$15)+(H$45>=$C$22+$C$15)+(H$45>=$C$23+$C$15)*(H$45<$C$40)))*$C$16 -> 360000 | I167: =($C$17+IF(I$45>=$C$19,$C$18,0)+$C$20*((I$45>=$C$21+$C$15)+(I$45>=$C$22+$C$15)+(I$45>=$C$23+$C$15)*(I$45<$C$40)))*$C$16 -> 450000 | J167: =($C$17+IF(J$45>=$C$19,$C$18,0)+$C$20*((J$45>=$C$21+$C$15)+(J$45>=$C$22+$C$15)+(J$45>=$C$23+$C$15)*(J$45<$C$40)))*$C$16 -> 450000 | K167: =($C$17+IF(K$45>=$C$19,$C$18,0)+$C$20*((K$45>=$C$21+$C$15)+(K$45>=$C$22+$C$15)+(K$45>=$C$23+$C$15)*(K$45<$C$40)))*$C$16 -> 450000 | L167: =($C$17+IF(L$45>=$C$19,$C$18,0)+$C$20*((L$45>=$C$21+$C$15)+(L$45>=$C$22+$C$15)+(L$45>=$C$23+$C$15)*(L$45<$C$40)))*$C$16 -> 500000 | M167: =($C$17+IF(M$45>=$C$19,$C$18,0)+$C$20*((M$45>=$C$21+$C$15)+(M$45>=$C$22+$C$15)+(M$45>=$C$23+$C$15)*(M$45<$C$40)))*$C$16 -> 500000 | N167: =($C$17+IF(N$45>=$C$19,$C$18,0)+$C$20*((N$45>=$C$21+$C$15)+(N$45>=$C$22+$C$15)+(N$45>=$C$23+$C$15)*(N$45<$C$40)))*$C$16 -> 500000 | O167: =($C$17+IF(O$45>=$C$19,$C$18,0)+$C$20*((O$45>=$C$21+$C$15)+(O$45>=$C$22+$C$15)+(O$45>=$C$23+$C$15)*(O$45<$C$40)))*$C$16 -> 550000 | ... Y167: =($C$17+IF(Y$45>=$C$19,$C$18,0)+$C$20*((Y$45>=$C$21+$C$15)+(Y$45>=$C$22+$C$15)+(Y$45>=$C$23+$C$15)*(Y$45<$C$40)))*$C$16 -> 550000
A168: New customer organisations | H168: =H159*$C$36*(1-H175)/(1-$C$32) -> 28.35 | I168: =I159*$C$36*(1-I175)/(1-$C$32) -> 29.7 | J168: =J159*$C$36*(1-J175)/(1-$C$32) -> 36.0072 | K168: =K159*$C$36*(1-K175)/(1-$C$32) -> 45.098193 | L168: =L159*$C$36*(1-L175)/(1-$C$32) -> 53.427972 | M168: =M159*$C$36*(1-M175)/(1-$C$32) -> 60.872198 | N168: =N159*$C$36*(1-N175)/(1-$C$32) -> 67.908072 | O168: =O159*$C$36*(1-O175)/(1-$C$32) -> 72.96352 | ... Y168: =Y159*$C$36*(1-Y175)/(1-$C$32) -> 143.05752
A169: Customer acquisition cost (₹) | H169: =H168*$C$35*(1-$C$37) -> 8505 | I169: =I168*$C$35*(1-$C$37) -> 8910 | J169: =J168*$C$35*(1-$C$37) -> 10802.16 | K169: =K168*$C$35*(1-$C$37) -> 13529.458 | L169: =L168*$C$35*(1-$C$37) -> 16028.392 | M169: =M168*$C$35*(1-$C$37) -> 18261.659 | N169: =N168*$C$35*(1-$C$37) -> 20372.422 | O169: =O168*$C$35*(1-$C$37) -> 21889.056 | ... Y169: =Y168*$C$35*(1-$C$37) -> 42917.255
...

Sheet Monthly_Downside
A1: Monthly engine — Downside scenario (M1–M18)
A2: All values flow from the Assumptions tab. Green = linked input.
A4: ID | B4: Parameter | C4: Value
A5: A1 | B5: =Assumptions!B5 -> Capture of Exhibit 2 mature volume | C5: =Assumptions!D5 -> 0.65
A6: A2 | B6: =Assumptions!B6 -> Ramp: share of mature volume, live month 1 | C6: =Assumptions!D6 -> 0.3
A7: A3 | B7: =Assumptions!B7 -> Ramp: live month 2 | C7: =Assumptions!D7 -> 0.6
A8: A4 | B8: =Assumptions!B8 -> Ramp: live month 3 | C8: =Assumptions!D8 -> 0.85
A9: A5 | B9: =Assumptions!B9 -> Ramp: live month 4+ | C9: =Assumptions!D9 -> 1
A10: A6 | B10: =Assumptions!B10 -> Pilot host bookings/month today | C10: =Assumptions!D10 -> 17.5
A11: A7 | B11: =Assumptions!B11 -> Pilot host bookings/month after Assured conversion | C11: =Assumptions!D11 -> 20
A12: A8 | B12: =Assumptions!B12 -> Months for pilot hosts to reach target | C12: =Assumptions!D12 -> 3
A13: A9 | B13: =Assumptions!B13 -> Average booking value multiplier | C13: =Assumptions!D13 -> 0.9
A14: A10 | B14: =Assumptions!B14 -> Bookings lost to cancellation (beyond tier on-time) | C14: =Assumptions!D14 -> 0.05
A15: A11 | B15: =Assumptions!B15 -> Onboarding delay for new hosts | C15: =Assumptions!D15 -> 2
A16: A12 | B16: =Assumptions!B16 -> Fixed cost multiplier | C16: =Assumptions!D16 -> 1.15
... A40: A36 | B40: =Assumptions!B40 -> City-4 (Cluster B) cost removed from month | C40: =Assumptions!D40 -> 99
A45: Month → | H45: 1 | I45: 2 | J45: 3 | K45: 4 | L45: 5 | M45: 6 | N45: 7 | O45: 8 | P45: 9 | Q45: 10 | R45: 11 | S45: 12 | T45: 13 | U45: 14 | V45: 15 | W45: 16 | X45: 17 | Y45: 18
A47: Bookings per host | B47: Cluster | C47: Tier | D47: Booking value ₹ | E47: Mature/month | F47: Pilot? | G47: Live from month
A48: =Assumptions!A57 -> 1 | B48: =Assumptions!B57 -> Pilot | C48: =Assumptions!C57 -> Assured | D48: =Assumptions!D57 -> 8500 | E48: =Assumptions!E57 -> 20 | F48: =Assumptions!G57 -> 1 | G48: =Assumptions!F57+IF(F48=1,0,$C$15) -> 1 | H48: =IF(H$45<$G48,0,IF($F48=1,$C$10+($C$11-$C$10)*MIN(H$45-$G48,$C$12)/$C$12,$E48*$C$5*INDEX($C$6:$C$9,MIN(H$45-$G48,3)+1)))*(1-$C$14)*IF(AND($C48="Verified",$C$39=1),0,1) -> 16.625 | I48: =IF(I$45<$G48,0,IF($F48=1,$C$10+($C$11-$C$10)*MIN(I$45-$G48,$C$12)/$C$12,$E48*$C$5*INDEX($C$6:$C$9,MIN(I$45-$G48,3)+1)))*(1-$C$14)*IF(AND($C48="Verified",$C$39=1),0,1) -> 17.416667 | J48: =IF(J$45<$G48,0,IF($F48=1,$C$10+($C$11-$C$10)*MIN(J$45-$G48,$C$12)/$C$12,$E48*$C$5*INDEX($C$6:$C$9,MIN(J$45-$G48,3)+1)))*(1-$C$14)*IF(AND($C48="Verified",$C$39=1),0,1) -> 18.208333 | K48: =IF(K$45<$G48,0,IF($F48=1,$C$10+($C$11-$C$10)*MIN(K$45-$G48,$C$12)/$C$12,$E48*$C$5*INDEX($C$6:$C$9,MIN(K$45-$G48,3)+1)))*(1-$C$14)*IF(AND($C48="Verified",$C$39=1),0,1) -> 19 | L48: =IF(L$45<$G48,0,IF($F48=1,$C$10+($C$11-$C$10)*MIN(L$45-$G48,$C$12)/$C$12,$E48*$C$5*INDEX($C$6:$C$9,MIN(L$45-$G48,3)+1)))*(1-$C$14)*IF(AND($C48="Verified",$C$39=1),0,1) -> 19 | M48: =IF(M$45<$G48,0,IF($F48=1,$C$10+($C$11-$C$10)*MIN(M$45-$G48,$C$12)/$C$12,$E48*$C$5*INDEX($C$6:$C$9,MIN(M$45-$G48,3)+1)))*(1-$C$14)*IF(AND($C48="Verified",$C$39=1),0,1) -> 19 | N48: =IF(N$45<$G48,0,IF($F48=1,$C$10+($C$11-$C$10)*MIN(N$45-$G48,$C$12)/$C$12,$E48*$C$5*INDEX($C$6:$C$9,MIN(N$45-$G48,3)+1)))*(1-$C$14)*IF(AND($C48="Verified",$C$39=1),0,1) -> 19 | O48: =IF(O$45<$G48,0,IF($F48=1,$C$10+($C$11-$C$10)*MIN(O$45-$G48,$C$12)/$C$12,$E48*$C$5*INDEX($C$6:$C$9,MIN(O$45-$G48,3)+1)))*(1-$C$14)*IF(AND($C48="Verified",$C$39=1),0,1) -> 19 | ... Y48: =IF(Y$45<$G48,0,IF($F48=1,$C$10+($C$11-$C$10)*MIN(Y$45-$G48,$C$12)/$C$12,$E48*$C$5*INDEX($C$6:$C$9,MIN(Y$45-$G48,3)+1)))*(1-$C$14)*IF(AND($C48="Verified",$C$39=1),0,1) -> 19
A49: =Assumptions!A58 -> 2 | B49: =Assumptions!B58 -> Pilot | C49: =Assumptions!C58 -> Assured | D49: =Assumptions!D58 -> 8500 | E49: =Assumptions!E58 -> 20 | F49: =Assumptions!G58 -> 1 | G49: =Assumptions!F58+IF(F49=1,0,$C$15) -> 1 | H49: =IF(H$45<$G49,0,IF($F49=1,$C$10+($C$11-$C$10)*MIN(H$45-$G49,$C$12)/$C$12,$E49*$C$5*INDEX($C$6:$C$9,MIN(H$45-$G49,3)+1)))*(1-$C$14)*IF(AND($C49="Verified",$C$39=1),0,1) -> 16.625 | I49: =IF(I$45<$G49,0,IF($F49=1,$C$10+($C$11-$C$10)*MIN(I$45-$G49,$C$12)/$C$12,$E49*$C$5*INDEX($C$6:$C$9,MIN(I$45-$G49,3)+1)))*(1-$C$14)*IF(AND($C49="Verified",$C$39=1),0,1) -> 17.416667 | J49: =IF(J$45<$G49,0,IF($F49=1,$C$10+($C$11-$C$10)*MIN(J$45-$G49,$C$12)/$C$12,$E49*$C$5*INDEX($C$6:$C$9,MIN(J$45-$G49,3)+1)))*(1-$C$14)*IF(AND($C49="Verified",$C$39=1),0,1) -> 18.208333 | K49: =IF(K$45<$G49,0,IF($F49=1,$C$10+($C$11-$C$10)*MIN(K$45-$G49,$C$12)/$C$12,$E49*$C$5*INDEX($C$6:$C$9,MIN(K$45-$G49,3)+1)))*(1-$C$14)*IF(AND($C49="Verified",$C$39=1),0,1) -> 19 | L49: =IF(L$45<$G49,0,IF($F49=1,$C$10+($C$11-$C$10)*MIN(L$45-$G49,$C$12)/$C$12,$E49*$C$5*INDEX($C$6:$C$9,MIN(L$45-$G49,3)+1)))*(1-$C$14)*IF(AND($C49="Verified",$C$39=1),0,1) -> 19 | M49: =IF(M$45<$G49,0,IF($F49=1,$C$10+($C$11-$C$10)*MIN(M$45-$G49,$C$12)/$C$12,$E49*$C$5*INDEX($C$6:$C$9,MIN(M$45-$G49,3)+1)))*(1-$C$14)*IF(AND($C49="Verified",$C$39=1),0,1) -> 19 | N49: =IF(N$45<$G49,0,IF($F49=1,$C$10+($C$11-$C$10)*MIN(N$45-$G49,$C$12)/$C$12,$E49*$C$5*INDEX($C$6:$C$9,MIN(N$45-$G49,3)+1)))*(1-$C$14)*IF(AND($C49="Verified",$C$39=1),0,1) -> 19 | O49: =IF(O$45<$G49,0,IF($F49=1,$C$10+($C$11-$C$10)*MIN(O$45-$G49,$C$12)/$C$12,$E49*$C$5*INDEX($C$6:$C$9,MIN(O$45-$G49,3)+1)))*(1-$C$14)*IF(AND($C49="Verified",$C$39=1),0,1) -> 19 | ... Y49: =IF(Y$45<$G49,0,IF($F49=1,$C$10+($C$11-$C$10)*MIN(Y$45-$G49,$C$12)/$C$12,$E49*$C$5*INDEX($C$6:$C$9,MIN(Y$45-$G49,3)+1)))*(1-$C$14)*IF(AND($C49="Verified",$C$39=1),0,1) -> 19
A50: =Assumptions!A59 -> 3 | B50: =Assumptions!B59 -> Pilot | C50: =Assumptions!C59 -> Assured | D50: =Assumptions!D59 -> 8500 | E50: =Assumptions!E59 -> 20 | F50: =Assumptions!G59 -> 1 | G50: =Assumptions!F59+IF(F50=1,0,$C$15) -> 1 | H50: =IF(H$45<$G50,0,IF($F50=1,$C$10+($C$11-$C$10)*MIN(H$45-$G50,$C$12)/$C$12,$E50*$C$5*INDEX($C$6:$C$9,MIN(H$45-$G50,3)+1)))*(1-$C$14)*IF(AND($C50="Verified",$C$39=1),0,1) -> 16.625 | I50: =IF(I$45<$G50,0,IF($F50=1,$C$10+($C$11-$C$10)*MIN(I$45-$G50,$C$12)/$C$12,$E50*$C$5*INDEX($C$6:$C$9,MIN(I$45-$G50,3)+1)))*(1-$C$14)*IF(AND($C50="Verified",$C$39=1),0,1) -> 17.416667 | J50: =IF(J$45<$G50,0,IF($F50=1,$C$10+($C$11-$C$10)*MIN(J$45-$G50,$C$12)/$C$12,$E50*$C$5*INDEX($C$6:$C$9,MIN(J$45-$G50,3)+1)))*(1-$C$14)*IF(AND($C50="Verified",$C$39=1),0,1) -> 18.208333 | K50: =IF(K$45<$G50,0,IF($F50=1,$C$10+($C$11-$C$10)*MIN(K$45-$G50,$C$12)/$C$12,$E50*$C$5*INDEX($C$6:$C$9,MIN(K$45-$G50,3)+1)))*(1-$C$14)*IF(AND($C50="Verified",$C$39=1),0,1) -> 19 | L50: =IF(L$45<$G50,0,IF($F50=1,$C$10+($C$11-$C$10)*MIN(L$45-$G50,$C$12)/$C$12,$E50*$C$5*INDEX($C$6:$C$9,MIN(L$45-$G50,3)+1)))*(1-$C$14)*IF(AND($C50="Verified",$C$39=1),0,1) -> 19 | M50: =IF(M$45<$G50,0,IF($F50=1,$C$10+($C$11-$C$10)*MIN(M$45-$G50,$C$12)/$C$12,$E50*$C$5*INDEX($C$6:$C$9,MIN(M$45-$G50,3)+1)))*(1-$C$14)*IF(AND($C50="Verified",$C$39=1),0,1) -> 19 | N50: =IF(N$45<$G50,0,IF($F50=1,$C$10+($C$11-$C$10)*MIN(N$45-$G50,$C$12)/$C$12,$E50*$C$5*INDEX($C$6:$C$9,MIN(N$45-$G50,3)+1)))*(1-$C$14)*IF(AND($C50="Verified",$C$39=1),0,1) -> 19 | O50: =IF(O$45<$G50,0,IF($F50=1,$C$10+($C$11-$C$10)*MIN(O$45-$G50,$C$12)/$C$12,$E50*$C$5*INDEX($C$6:$C$9,MIN(O$45-$G50,3)+1)))*(1-$C$14)*IF(AND($C50="Verified",$C$39=1),0,1) -> 19 | ... Y50: =IF(Y$45<$G50,0,IF($F50=1,$C$10+($C$11-$C$10)*MIN(Y$45-$G50,$C$12)/$C$12,$E50*$C$5*INDEX($C$6:$C$9,MIN(Y$45-$G50,3)+1)))*(1-$C$14)*IF(AND($C50="Verified",$C$39=1),0,1) -> 19
A51: =Assumptions!A60 -> 4 | B51: =Assumptions!B60 -> Pilot | C51: =Assumptions!C60 -> Assured | D51: =Assumptions!D60 -> 8500 | E51: =Assumptions!E60 -> 20 | F51: =Assumptions!G60 -> 1 | G51: =Assumptions!F60+IF(F51=1,0,$C$15) -> 1 | H51: =IF(H$45<$G51,0,IF($F51=1,$C$10+($C$11-$C$10)*MIN(H$45-$G51,$C$12)/$C$12,$E51*$C$5*INDEX($C$6:$C$9,MIN(H$45-$G51,3)+1)))*(1-$C$14)*IF(AND($C51="Verified",$C$39=1),0,1) -> 16.625 | I51: =IF(I$45<$G51,0,IF($F51=1,$C$10+($C$11-$C$10)*MIN(I$45-$G51,$C$12)/$C$12,$E51*$C$5*INDEX($C$6:$C$9,MIN(I$45-$G51,3)+1)))*(1-$C$14)*IF(AND($C51="Verified",$C$39=1),0,1) -> 17.416667 | J51: =IF(J$45<$G51,0,IF($F51=1,$C$10+($C$11-$C$10)*MIN(J$45-$G51,$C$12)/$C$12,$E51*$C$5*INDEX($C$6:$C$9,MIN(J$45-$G51,3)+1)))*(1-$C$14)*IF(AND($C51="Verified",$C$39=1),0,1) -> 18.208333 | K51: =IF(K$45<$G51,0,IF($F51=1,$C$10+($C$11-$C$10)*MIN(K$45-$G51,$C$12)/$C$12,$E51*$C$5*INDEX($C$6:$C$9,MIN(K$45-$G51,3)+1)))*(1-$C$14)*IF(AND($C51="Verified",$C$39=1),0,1) -> 19 | L51: =IF(L$45<$G51,0,IF($F51=1,$C$10+($C$11-$C$10)*MIN(L$45-$G51,$C$12)/$C$12,$E51*$C$5*INDEX($C$6:$C$9,MIN(L$45-$G51,3)+1)))*(1-$C$14)*IF(AND($C51="Verified",$C$39=1),0,1) -> 19 | M51: =IF(M$45<$G51,0,IF($F51=1,$C$10+($C$11-$C$10)*MIN(M$45-$G51,$C$12)/$C$12,$E51*$C$5*INDEX($C$6:$C$9,MIN(M$45-$G51,3)+1)))*(1-$C$14)*IF(AND($C51="Verified",$C$39=1),0,1) -> 19 | N51: =IF(N$45<$G51,0,IF($F51=1,$C$10+($C$11-$C$10)*MIN(N$45-$G51,$C$12)/$C$12,$E51*$C$5*INDEX($C$6:$C$9,MIN(N$45-$G51,3)+1)))*(1-$C$14)*IF(AND($C51="Verified",$C$39=1),0,1) -> 19 | O51: =IF(O$45<$G51,0,IF($F51=1,$C$10+($C$11-$C$10)*MIN(O$45-$G51,$C$12)/$C$12,$E51*$C$5*INDEX($C$6:$C$9,MIN(O$45-$G51,3)+1)))*(1-$C$14)*IF(AND($C51="Verified",$C$39=1),0,1) -> 19 | ... Y51: =IF(Y$45<$G51,0,IF($F51=1,$C$10+($C$11-$C$10)*MIN(Y$45-$G51,$C$12)/$C$12,$E51*$C$5*INDEX($C$6:$C$9,MIN(Y$45-$G51,3)+1)))*(1-$C$14)*IF(AND($C51="Verified",$C$39=1),0,1) -> 19
A52: =Assumptions!A61 -> 5 | B52: =Assumptions!B61 -> A | C52: =Assumptions!C61 -> Assured | D52: =Assumptions!D61 -> 12000 | E52: =Assumptions!E61 -> 24 | F52: =Assumptions!G61 -> 0 | G52: =Assumptions!F61+IF(F52=1,0,$C$15) -> 5 | H52: =IF(H$45<$G52,0,IF($F52=1,$C$10+($C$11-$C$10)*MIN(H$45-$G52,$C$12)/$C$12,$E52*$C$5*INDEX($C$6:$C$9,MIN(H$45-$G52,3)+1)))*(1-$C$14)*IF(AND($C52="Verified",$C$39=1),0,1) -> 0 | I52: =IF(I$45<$G52,0,IF($F52=1,$C$10+($C$11-$C$10)*MIN(I$45-$G52,$C$12)/$C$12,$E52*$C$5*INDEX($C$6:$C$9,MIN(I$45-$G52,3)+1)))*(1-$C$14)*IF(AND($C52="Verified",$C$39=1),0,1) -> 0 | J52: =IF(J$45<$G52,0,IF($F52=1,$C$10+($C$11-$C$10)*MIN(J$45-$G52,$C$12)/$C$12,$E52*$C$5*INDEX($C$6:$C$9,MIN(J$45-$G52,3)+1)))*(1-$C$14)*IF(AND($C52="Verified",$C$39=1),0,1) -> 0 | K52: =IF(K$45<$G52,0,IF($F52=1,$C$10+($C$11-$C$10)*MIN(K$45-$G52,$C$12)/$C$12,$E52*$C$5*INDEX($C$6:$C$9,MIN(K$45-$G52,3)+1)))*(1-$C$14)*IF(AND($C52="Verified",$C$39=1),0,1) -> 0 | L52: =IF(L$45<$G52,0,IF($F52=1,$C$10+($C$11-$C$10)*MIN(L$45-$G52,$C$12)/$C$12,$E52*$C$5*INDEX($C$6:$C$9,MIN(L$45-$G52,3)+1)))*(1-$C$14)*IF(AND($C52="Verified",$C$39=1),0,1) -> 4.446 | M52: =IF(M$45<$G52,0,IF($F52=1,$C$10+($C$11-$C$10)*MIN(M$45-$G52,$C$12)/$C$12,$E52*$C$5*INDEX($C$6:$C$9,MIN(M$45-$G52,3)+1)))*(1-$C$14)*IF(AND($C52="Verified",$C$39=1),0,1) -> 8.892 | N52: =IF(N$45<$G52,0,IF($F52=1,$C$10+($C$11-$C$10)*MIN(N$45-$G52,$C$12)/$C$12,$E52*$C$5*INDEX($C$6:$C$9,MIN(N$45-$G52,3)+1)))*(1-$C$14)*IF(AND($C52="Verified",$C$39=1),0,1) -> 12.597 | O52: =IF(O$45<$G52,0,IF($F52=1,$C$10+($C$11-$C$10)*MIN(O$45-$G52,$C$12)/$C$12,$E52*$C$5*INDEX($C$6:$C$9,MIN(O$45-$G52,3)+1)))*(1-$C$14)*IF(AND($C52="Verified",$C$39=1),0,1) -> 14.82 | ... Y52: =IF(Y$45<$G52,0,IF($F52=1,$C$10+($C$11-$C$10)*MIN(Y$45-$G52,$C$12)/$C$12,$E52*$C$5*INDEX($C$6:$C$9,MIN(Y$45-$G52,3)+1)))*(1-$C$14)*IF(AND($C52="Verified",$C$39=1),0,1) -> 14.82
A53: =Assumptions!A62 -> 6 | B53: =Assumptions!B62 -> A | C53: =Assumptions!C62 -> Assured | D53: =Assumptions!D62 -> 12000 | E53: =Assumptions!E62 -> 24 | F53: =Assumptions!G62 -> 0 | G53: =Assumptions!F62+IF(F53=1,0,$C$15) -> 5 | H53: =IF(H$45<$G53,0,IF($F53=1,$C$10+($C$11-$C$10)*MIN(H$45-$G53,$C$12)/$C$12,$E53*$C$5*INDEX($C$6:$C$9,MIN(H$45-$G53,3)+1)))*(1-$C$14)*IF(AND($C53="Verified",$C$39=1),0,1) -> 0 | I53: =IF(I$45<$G53,0,IF($F53=1,$C$10+($C$11-$C$10)*MIN(I$45-$G53,$C$12)/$C$12,$E53*$C$5*INDEX($C$6:$C$9,MIN(I$45-$G53,3)+1)))*(1-$C$14)*IF(AND($C53="Verified",$C$39=1),0,1) -> 0 | J53: =IF(J$45<$G53,0,IF($F53=1,$C$10+($C$11-$C$10)*MIN(J$45-$G53,$C$12)/$C$12,$E53*$C$5*INDEX($C$6:$C$9,MIN(J$45-$G53,3)+1)))*(1-$C$14)*IF(AND($C53="Verified",$C$39=1),0,1) -> 0 | K53: =IF(K$45<$G53,0,IF($F53=1,$C$10+($C$11-$C$10)*MIN(K$45-$G53,$C$12)/$C$12,$E53*$C$5*INDEX($C$6:$C$9,MIN(K$45-$G53,3)+1)))*(1-$C$14)*IF(AND($C53="Verified",$C$39=1),0,1) -> 0 | L53: =IF(L$45<$G53,0,IF($F53=1,$C$10+($C$11-$C$10)*MIN(L$45-$G53,$C$12)/$C$12,$E53*$C$5*INDEX($C$6:$C$9,MIN(L$45-$G53,3)+1)))*(1-$C$14)*IF(AND($C53="Verified",$C$39=1),0,1) -> 4.446 | M53: =IF(M$45<$G53,0,IF($F53=1,$C$10+($C$11-$C$10)*MIN(M$45-$G53,$C$12)/$C$12,$E53*$C$5*INDEX($C$6:$C$9,MIN(M$45-$G53,3)+1)))*(1-$C$14)*IF(AND($C53="Verified",$C$39=1),0,1) -> 8.892 | N53: =IF(N$45<$G53,0,IF($F53=1,$C$10+($C$11-$C$10)*MIN(N$45-$G53,$C$12)/$C$12,$E53*$C$5*INDEX($C$6:$C$9,MIN(N$45-$G53,3)+1)))*(1-$C$14)*IF(AND($C53="Verified",$C$39=1),0,1) -> 12.597 | O53: =IF(O$45<$G53,0,IF($F53=1,$C$10+($C$11-$C$10)*MIN(O$45-$G53,$C$12)/$C$12,$E53*$C$5*INDEX($C$6:$C$9,MIN(O$45-$G53,3)+1)))*(1-$C$14)*IF(AND($C53="Verified",$C$39=1),0,1) -> 14.82 | ... Y53: =IF(Y$45<$G53,0,IF($F53=1,$C$10+($C$11-$C$10)*MIN(Y$45-$G53,$C$12)/$C$12,$E53*$C$5*INDEX($C$6:$C$9,MIN(Y$45-$G53,3)+1)))*(1-$C$14)*IF(AND($C53="Verified",$C$39=1),0,1) -> 14.82
A54: =Assumptions!A63 -> 7 | B54: =Assumptions!B63 -> A | C54: =Assumptions!C63 -> Assured | D54: =Assumptions!D63 -> 12000 | E54: =Assumptions!E63 -> 24 | F54: =Assumptions!G63 -> 0 | G54: =Assumptions!F63+IF(F54=1,0,$C$15) -> 6 | H54: =IF(H$45<$G54,0,IF($F54=1,$C$10+($C$11-$C$10)*MIN(H$45-$G54,$C$12)/$C$12,$E54*$C$5*INDEX($C$6:$C$9,MIN(H$45-$G54,3)+1)))*(1-$C$14)*IF(AND($C54="Verified",$C$39=1),0,1) -> 0 | I54: =IF(I$45<$G54,0,IF($F54=1,$C$10+($C$11-$C$10)*MIN(I$45-$G54,$C$12)/$C$12,$E54*$C$5*INDEX($C$6:$C$9,MIN(I$45-$G54,3)+1)))*(1-$C$14)*IF(AND($C54="Verified",$C$39=1),0,1) -> 0 | J54: =IF(J$45<$G54,0,IF($F54=1,$C$10+($C$11-$C$10)*MIN(J$45-$G54,$C$12)/$C$12,$E54*$C$5*INDEX($C$6:$C$9,MIN(J$45-$G54,3)+1)))*(1-$C$14)*IF(AND($C54="Verified",$C$39=1),0,1) -> 0 | K54: =IF(K$45<$G54,0,IF($F54=1,$C$10+($C$11-$C$10)*MIN(K$45-$G54,$C$12)/$C$12,$E54*$C$5*INDEX($C$6:$C$9,MIN(K$45-$G54,3)+1)))*(1-$C$14)*IF(AND($C54="Verified",$C$39=1),0,1) -> 0 | L54: =IF(L$45<$G54,0,IF($F54=1,$C$10+($C$11-$C$10)*MIN(L$45-$G54,$C$12)/$C$12,$E54*$C$5*INDEX($C$6:$C$9,MIN(L$45-$G54,3)+1)))*(1-$C$14)*IF(AND($C54="Verified",$C$39=1),0,1) -> 0 | M54: =IF(M$45<$G54,0,IF($F54=1,$C$10+($C$11-$C$10)*MIN(M$45-$G54,$C$12)/$C$12,$E54*$C$5*INDEX($C$6:$C$9,MIN(M$45-$G54,3)+1)))*(1-$C$14)*IF(AND($C54="Verified",$C$39=1),0,1) -> 4.446 | N54: =IF(N$45<$G54,0,IF($F54=1,$C$10+($C$11-$C$10)*MIN(N$45-$G54,$C$12)/$C$12,$E54*$C$5*INDEX($C$6:$C$9,MIN(N$45-$G54,3)+1)))*(1-$C$14)*IF(AND($C54="Verified",$C$39=1),0,1) -> 8.892 | O54: =IF(O$45<$G54,0,IF($F54=1,$C$10+($C$11-$C$10)*MIN(O$45-$G54,$C$12)/$C$12,$E54*$C$5*INDEX($C$6:$C$9,MIN(O$45-$G54,3)+1)))*(1-$C$14)*IF(AND($C54="Verified",$C$39=1),0,1) -> 12.597 | ... Y54: =IF(Y$45<$G54,0,IF($F54=1,$C$10+($C$11-$C$10)*MIN(Y$45-$G54,$C$12)/$C$12,$E54*$C$5*INDEX($C$6:$C$9,MIN(Y$45-$G54,3)+1)))*(1-$C$14)*IF(AND($C54="Verified",$C$39=1),0,1) -> 14.82
A55: =Assumptions!A64 -> 8 | B55: =Assumptions!B64 -> A | C55: =Assumptions!C64 -> Assured | D55: =Assumptions!D64 -> 12000 | E55: =Assumptions!E64 -> 24 | F55: =Assumptions!G64 -> 0 | G55: =Assumptions!F64+IF(F55=1,0,$C$15) -> 6 | H55: =IF(H$45<$G55,0,IF($F55=1,$C$10+($C$11-$C$10)*MIN(H$45-$G55,$C$12)/$C$12,$E55*$C$5*INDEX($C$6:$C$9,MIN(H$45-$G55,3)+1)))*(1-$C$14)*IF(AND($C55="Verified",$C$39=1),0,1) -> 0 | I55: =IF(I$45<$G55,0,IF($F55=1,$C$10+($C$11-$C$10)*MIN(I$45-$G55,$C$12)/$C$12,$E55*$C$5*INDEX($C$6:$C$9,MIN(I$45-$G55,3)+1)))*(1-$C$14)*IF(AND($C55="Verified",$C$39=1),0,1) -> 0 | J55: =IF(J$45<$G55,0,IF($F55=1,$C$10+($C$11-$C$10)*MIN(J$45-$G55,$C$12)/$C$12,$E55*$C$5*INDEX($C$6:$C$9,MIN(J$45-$G55,3)+1)))*(1-$C$14)*IF(AND($C55="Verified",$C$39=1),0,1) -> 0 | K55: =IF(K$45<$G55,0,IF($F55=1,$C$10+($C$11-$C$10)*MIN(K$45-$G55,$C$12)/$C$12,$E55*$C$5*INDEX($C$6:$C$9,MIN(K$45-$G55,3)+1)))*(1-$C$14)*IF(AND($C55="Verified",$C$39=1),0,1) -> 0 | L55: =IF(L$45<$G55,0,IF($F55=1,$C$10+($C$11-$C$10)*MIN(L$45-$G55,$C$12)/$C$12,$E55*$C$5*INDEX($C$6:$C$9,MIN(L$45-$G55,3)+1)))*(1-$C$14)*IF(AND($C55="Verified",$C$39=1),0,1) -> 0 | M55: =IF(M$45<$G55,0,IF($F55=1,$C$10+($C$11-$C$10)*MIN(M$45-$G55,$C$12)/$C$12,$E55*$C$5*INDEX($C$6:$C$9,MIN(M$45-$G55,3)+1)))*(1-$C$14)*IF(AND($C55="Verified",$C$39=1),0,1) -> 4.446 | N55: =IF(N$45<$G55,0,IF($F55=1,$C$10+($C$11-$C$10)*MIN(N$45-$G55,$C$12)/$C$12,$E55*$C$5*INDEX($C$6:$C$9,MIN(N$45-$G55,3)+1)))*(1-$C$14)*IF(AND($C55="Verified",$C$39=1),0,1) -> 8.892 | O55: =IF(O$45<$G55,0,IF($F55=1,$C$10+($C$11-$C$10)*MIN(O$45-$G55,$C$12)/$C$12,$E55*$C$5*INDEX($C$6:$C$9,MIN(O$45-$G55,3)+1)))*(1-$C$14)*IF(AND($C55="Verified",$C$39=1),0,1) -> 12.597 | ... Y55: =IF(Y$45<$G55,0,IF($F55=1,$C$10+($C$11-$C$10)*MIN(Y$45-$G55,$C$12)/$C$12,$E55*$C$5*INDEX($C$6:$C$9,MIN(Y$45-$G55,3)+1)))*(1-$C$14)*IF(AND($C55="Verified",$C$39=1),0,1) -> 14.82
A56: =Assumptions!A65 -> 9 | B56: =Assumptions!B65 -> A | C56: =Assumptions!C65 -> Assured | D56: =Assumptions!D65 -> 12000 | E56: =Assumptions!E65 -> 24 | F56: =Assumptions!G65 -> 0 | G56: =Assumptions!F65+IF(F56=1,0,$C$15) -> 7 | H56: =IF(H$45<$G56,0,IF($F56=1,$C$10+($C$11-$C$10)*MIN(H$45-$G56,$C$12)/$C$12,$E56*$C$5*INDEX($C$6:$C$9,MIN(H$45-$G56,3)+1)))*(1-$C$14)*IF(AND($C56="Verified",$C$39=1),0,1) -> 0 | I56: =IF(I$45<$G56,0,IF($F56=1,$C$10+($C$11-$C$10)*MIN(I$45-$G56,$C$12)/$C$12,$E56*$C$5*INDEX($C$6:$C$9,MIN(I$45-$G56,3)+1)))*(1-$C$14)*IF(AND($C56="Verified",$C$39=1),0,1) -> 0 | J56: =IF(J$45<$G56,0,IF($F56=1,$C$10+($C$11-$C$10)*MIN(J$45-$G56,$C$12)/$C$12,$E56*$C$5*INDEX($C$6:$C$9,MIN(J$45-$G56,3)+1)))*(1-$C$14)*IF(AND($C56="Verified",$C$39=1),0,1) -> 0 | K56: =IF(K$45<$G56,0,IF($F56=1,$C$10+($C$11-$C$10)*MIN(K$45-$G56,$C$12)/$C$12,$E56*$C$5*INDEX($C$6:$C$9,MIN(K$45-$G56,3)+1)))*(1-$C$14)*IF(AND($C56="Verified",$C$39=1),0,1) -> 0 | L56: =IF(L$45<$G56,0,IF($F56=1,$C$10+($C$11-$C$10)*MIN(L$45-$G56,$C$12)/$C$12,$E56*$C$5*INDEX($C$6:$C$9,MIN(L$45-$G56,3)+1)))*(1-$C$14)*IF(AND($C56="Verified",$C$39=1),0,1) -> 0 | M56: =IF(M$45<$G56,0,IF($F56=1,$C$10+($C$11-$C$10)*MIN(M$45-$G56,$C$12)/$C$12,$E56*$C$5*INDEX($C$6:$C$9,MIN(M$45-$G56,3)+1)))*(1-$C$14)*IF(AND($C56="Verified",$C$39=1),0,1) -> 0 | N56: =IF(N$45<$G56,0,IF($F56=1,$C$10+($C$11-$C$10)*MIN(N$45-$G56,$C$12)/$C$12,$E56*$C$5*INDEX($C$6:$C$9,MIN(N$45-$G56,3)+1)))*(1-$C$14)*IF(AND($C56="Verified",$C$39=1),0,1) -> 4.446 | O56: =IF(O$45<$G56,0,IF($F56=1,$C$10+($C$11-$C$10)*MIN(O$45-$G56,$C$12)/$C$12,$E56*$C$5*INDEX($C$6:$C$9,MIN(O$45-$G56,3)+1)))*(1-$C$14)*IF(AND($C56="Verified",$C$39=1),0,1) -> 8.892 | ... Y56: =IF(Y$45<$G56,0,IF($F56=1,$C$10+($C$11-$C$10)*MIN(Y$45-$G56,$C$12)/$C$12,$E56*$C$5*INDEX($C$6:$C$9,MIN(Y$45-$G56,3)+1)))*(1-$C$14)*IF(AND($C56="Verified",$C$39=1),0,1) -> 14.82
A57: =Assumptions!A66 -> 10 | B57: =Assumptions!B66 -> C | C57: =Assumptions!C66 -> Assured | D57: =Assumptions!D66 -> 8000 | E57: =Assumptions!E66 -> 26 | F57: =Assumptions!G66 -> 0 | G57: =Assumptions!F66+IF(F57=1,0,$C$15) -> 8 | H57: =IF(H$45<$G57,0,IF($F57=1,$C$10+($C$11-$C$10)*MIN(H$45-$G57,$C$12)/$C$12,$E57*$C$5*INDEX($C$6:$C$9,MIN(H$45-$G57,3)+1)))*(1-$C$14)*IF(AND($C57="Verified",$C$39=1),0,1) -> 0 | I57: =IF(I$45<$G57,0,IF($F57=1,$C$10+($C$11-$C$10)*MIN(I$45-$G57,$C$12)/$C$12,$E57*$C$5*INDEX($C$6:$C$9,MIN(I$45-$G57,3)+1)))*(1-$C$14)*IF(AND($C57="Verified",$C$39=1),0,1) -> 0 | J57: =IF(J$45<$G57,0,IF($F57=1,$C$10+($C$11-$C$10)*MIN(J$45-$G57,$C$12)/$C$12,$E57*$C$5*INDEX($C$6:$C$9,MIN(J$45-$G57,3)+1)))*(1-$C$14)*IF(AND($C57="Verified",$C$39=1),0,1) -> 0 | K57: =IF(K$45<$G57,0,IF($F57=1,$C$10+($C$11-$C$10)*MIN(K$45-$G57,$C$12)/$C$12,$E57*$C$5*INDEX($C$6:$C$9,MIN(K$45-$G57,3)+1)))*(1-$C$14)*IF(AND($C57="Verified",$C$39=1),0,1) -> 0 | L57: =IF(L$45<$G57,0,IF($F57=1,$C$10+($C$11-$C$10)*MIN(L$45-$G57,$C$12)/$C$12,$E57*$C$5*INDEX($C$6:$C$9,MIN(L$45-$G57,3)+1)))*(1-$C$14)*IF(AND($C57="Verified",$C$39=1),0,1) -> 0 | M57: =IF(M$45<$G57,0,IF($F57=1,$C$10+($C$11-$C$10)*MIN(M$45-$G57,$C$12)/$C$12,$E57*$C$5*INDEX($C$6:$C$9,MIN(M$45-$G57,3)+1)))*(1-$C$14)*IF(AND($C57="Verified",$C$39=1),0,1) -> 0 | N57: =IF(N$45<$G57,0,IF($F57=1,$C$10+($C$11-$C$10)*MIN(N$45-$G57,$C$12)/$C$12,$E57*$C$5*INDEX($C$6:$C$9,MIN(N$45-$G57,3)+1)))*(1-$C$14)*IF(AND($C57="Verified",$C$39=1),0,1) -> 0 | O57: =IF(O$45<$G57,0,IF($F57=1,$C$10+($C$11-$C$10)*MIN(O$45-$G57,$C$12)/$C$12,$E57*$C$5*INDEX($C$6:$C$9,MIN(O$45-$G57,3)+1)))*(1-$C$14)*IF(AND($C57="Verified",$C$39=1),0,1) -> 4.8165 | ... Y57: =IF(Y$45<$G57,0,IF($F57=1,$C$10+($C$11-$C$10)*MIN(Y$45-$G57,$C$12)/$C$12,$E57*$C$5*INDEX($C$6:$C$9,MIN(Y$45-$G57,3)+1)))*(1-$C$14)*IF(AND($C57="Verified",$C$39=1),0,1) -> 16.055
A58: =Assumptions!A67 -> 11 | B58: =Assumptions!B67 -> C | C58: =Assumptions!C67 -> Assured | D58: =Assumptions!D67 -> 8000 | E58: =Assumptions!E67 -> 26 | F58: =Assumptions!G67 -> 0 | G58: =Assumptions!F67+IF(F58=1,0,$C$15) -> 9 | H58: =IF(H$45<$G58,0,IF($F58=1,$C$10+($C$11-$C$10)*MIN(H$45-$G58,$C$12)/$C$12,$E58*$C$5*INDEX($C$6:$C$9,MIN(H$45-$G58,3)+1)))*(1-$C$14)*IF(AND($C58="Verified",$C$39=1),0,1) -> 0 | I58: =IF(I$45<$G58,0,IF($F58=1,$C$10+($C$11-$C$10)*MIN(I$45-$G58,$C$12)/$C$12,$E58*$C$5*INDEX($C$6:$C$9,MIN(I$45-$G58,3)+1)))*(1-$C$14)*IF(AND($C58="Verified",$C$39=1),0,1) -> 0 | J58: =IF(J$45<$G58,0,IF($F58=1,$C$10+($C$11-$C$10)*MIN(J$45-$G58,$C$12)/$C$12,$E58*$C$5*INDEX($C$6:$C$9,MIN(J$45-$G58,3)+1)))*(1-$C$14)*IF(AND($C58="Verified",$C$39=1),0,1) -> 0 | K58: =IF(K$45<$G58,0,IF($F58=1,$C$10+($C$11-$C$10)*MIN(K$45-$G58,$C$12)/$C$12,$E58*$C$5*INDEX($C$6:$C$9,MIN(K$45-$G58,3)+1)))*(1-$C$14)*IF(AND($C58="Verified",$C$39=1),0,1) -> 0 | L58: =IF(L$45<$G58,0,IF($F58=1,$C$10+($C$11-$C$10)*MIN(L$45-$G58,$C$12)/$C$12,$E58*$C$5*INDEX($C$6:$C$9,MIN(L$45-$G58,3)+1)))*(1-$C$14)*IF(AND($C58="Verified",$C$39=1),0,1) -> 0 | M58: =IF(M$45<$G58,0,IF($F58=1,$C$10+($C$11-$C$10)*MIN(M$45-$G58,$C$12)/$C$12,$E58*$C$5*INDEX($C$6:$C$9,MIN(M$45-$G58,3)+1)))*(1-$C$14)*IF(AND($C58="Verified",$C$39=1),0,1) -> 0 | N58: =IF(N$45<$G58,0,IF($F58=1,$C$10+($C$11-$C$10)*MIN(N$45-$G58,$C$12)/$C$12,$E58*$C$5*INDEX($C$6:$C$9,MIN(N$45-$G58,3)+1)))*(1-$C$14)*IF(AND($C58="Verified",$C$39=1),0,1) -> 0 | O58: =IF(O$45<$G58,0,IF($F58=1,$C$10+($C$11-$C$10)*MIN(O$45-$G58,$C$12)/$C$12,$E58*$C$5*INDEX($C$6:$C$9,MIN(O$45-$G58,3)+1)))*(1-$C$14)*IF(AND($C58="Verified",$C$39=1),0,1) -> 0 | ... Y58: =IF(Y$45<$G58,0,IF($F58=1,$C$10+($C$11-$C$10)*MIN(Y$45-$G58,$C$12)/$C$12,$E58*$C$5*INDEX($C$6:$C$9,MIN(Y$45-$G58,3)+1)))*(1-$C$14)*IF(AND($C58="Verified",$C$39=1),0,1) -> 16.055
A59: =Assumptions!A68 -> 12 | B59: =Assumptions!B68 -> C | C59: =Assumptions!C68 -> Assured | D59: =Assumptions!D68 -> 8000 | E59: =Assumptions!E68 -> 26 | F59: =Assumptions!G68 -> 0 | G59: =Assumptions!F68+IF(F59=1,0,$C$15) -> 9 | H59: =IF(H$45<$G59,0,IF($F59=1,$C$10+($C$11-$C$10)*MIN(H$45-$G59,$C$12)/$C$12,$E59*$C$5*INDEX($C$6:$C$9,MIN(H$45-$G59,3)+1)))*(1-$C$14)*IF(AND($C59="Verified",$C$39=1),0,1) -> 0 | I59: =IF(I$45<$G59,0,IF($F59=1,$C$10+($C$11-$C$10)*MIN(I$45-$G59,$C$12)/$C$12,$E59*$C$5*INDEX($C$6:$C$9,MIN(I$45-$G59,3)+1)))*(1-$C$14)*IF(AND($C59="Verified",$C$39=1),0,1) -> 0 | J59: =IF(J$45<$G59,0,IF($F59=1,$C$10+($C$11-$C$10)*MIN(J$45-$G59,$C$12)/$C$12,$E59*$C$5*INDEX($C$6:$C$9,MIN(J$45-$G59,3)+1)))*(1-$C$14)*IF(AND($C59="Verified",$C$39=1),0,1) -> 0 | K59: =IF(K$45<$G59,0,IF($F59=1,$C$10+($C$11-$C$10)*MIN(K$45-$G59,$C$12)/$C$12,$E59*$C$5*INDEX($C$6:$C$9,MIN(K$45-$G59,3)+1)))*(1-$C$14)*IF(AND($C59="Verified",$C$39=1),0,1) -> 0 | L59: =IF(L$45<$G59,0,IF($F59=1,$C$10+($C$11-$C$10)*MIN(L$45-$G59,$C$12)/$C$12,$E59*$C$5*INDEX($C$6:$C$9,MIN(L$45-$G59,3)+1)))*(1-$C$14)*IF(AND($C59="Verified",$C$39=1),0,1) -> 0 | M59: =IF(M$45<$G59,0,IF($F59=1,$C$10+($C$11-$C$10)*MIN(M$45-$G59,$C$12)/$C$12,$E59*$C$5*INDEX($C$6:$C$9,MIN(M$45-$G59,3)+1)))*(1-$C$14)*IF(AND($C59="Verified",$C$39=1),0,1) -> 0 | N59: =IF(N$45<$G59,0,IF($F59=1,$C$10+($C$11-$C$10)*MIN(N$45-$G59,$C$12)/$C$12,$E59*$C$5*INDEX($C$6:$C$9,MIN(N$45-$G59,3)+1)))*(1-$C$14)*IF(AND($C59="Verified",$C$39=1),0,1) -> 0 | O59: =IF(O$45<$G59,0,IF($F59=1,$C$10+($C$11-$C$10)*MIN(O$45-$G59,$C$12)/$C$12,$E59*$C$5*INDEX($C$6:$C$9,MIN(O$45-$G59,3)+1)))*(1-$C$14)*IF(AND($C59="Verified",$C$39=1),0,1) -> 0 | ... Y59: =IF(Y$45<$G59,0,IF($F59=1,$C$10+($C$11-$C$10)*MIN(Y$45-$G59,$C$12)/$C$12,$E59*$C$5*INDEX($C$6:$C$9,MIN(Y$45-$G59,3)+1)))*(1-$C$14)*IF(AND($C59="Verified",$C$39=1),0,1) -> 16.055
... A67: =Assumptions!A76 -> 20 | B67: =Assumptions!B76 -> B | C67: =Assumptions!C76 -> Verified | D67: =Assumptions!D76 -> 6500 | E67: =Assumptions!E76 -> 30 | F67: =Assumptions!G76 -> 0 | G67: =Assumptions!F76+IF(F67=1,0,$C$15) -> 16 | H67: =IF(H$45<$G67,0,IF($F67=1,$C$10+($C$11-$C$10)*MIN(H$45-$G67,$C$12)/$C$12,$E67*$C$5*INDEX($C$6:$C$9,MIN(H$45-$G67,3)+1)))*(1-$C$14)*IF(AND($C67="Verified",$C$39=1),0,1) -> 0 | I67: =IF(I$45<$G67,0,IF($F67=1,$C$10+($C$11-$C$10)*MIN(I$45-$G67,$C$12)/$C$12,$E67*$C$5*INDEX($C$6:$C$9,MIN(I$45-$G67,3)+1)))*(1-$C$14)*IF(AND($C67="Verified",$C$39=1),0,1) -> 0 | J67: =IF(J$45<$G67,0,IF($F67=1,$C$10+($C$11-$C$10)*MIN(J$45-$G67,$C$12)/$C$12,$E67*$C$5*INDEX($C$6:$C$9,MIN(J$45-$G67,3)+1)))*(1-$C$14)*IF(AND($C67="Verified",$C$39=1),0,1) -> 0 | K67: =IF(K$45<$G67,0,IF($F67=1,$C$10+($C$11-$C$10)*MIN(K$45-$G67,$C$12)/$C$12,$E67*$C$5*INDEX($C$6:$C$9,MIN(K$45-$G67,3)+1)))*(1-$C$14)*IF(AND($C67="Verified",$C$39=1),0,1) -> 0 | L67: =IF(L$45<$G67,0,IF($F67=1,$C$10+($C$11-$C$10)*MIN(L$45-$G67,$C$12)/$C$12,$E67*$C$5*INDEX($C$6:$C$9,MIN(L$45-$G67,3)+1)))*(1-$C$14)*IF(AND($C67="Verified",$C$39=1),0,1) -> 0 | M67: =IF(M$45<$G67,0,IF($F67=1,$C$10+($C$11-$C$10)*MIN(M$45-$G67,$C$12)/$C$12,$E67*$C$5*INDEX($C$6:$C$9,MIN(M$45-$G67,3)+1)))*(1-$C$14)*IF(AND($C67="Verified",$C$39=1),0,1) -> 0 | N67: =IF(N$45<$G67,0,IF($F67=1,$C$10+($C$11-$C$10)*MIN(N$45-$G67,$C$12)/$C$12,$E67*$C$5*INDEX($C$6:$C$9,MIN(N$45-$G67,3)+1)))*(1-$C$14)*IF(AND($C67="Verified",$C$39=1),0,1) -> 0 | O67: =IF(O$45<$G67,0,IF($F67=1,$C$10+($C$11-$C$10)*MIN(O$45-$G67,$C$12)/$C$12,$E67*$C$5*INDEX($C$6:$C$9,MIN(O$45-$G67,3)+1)))*(1-$C$14)*IF(AND($C67="Verified",$C$39=1),0,1) -> 0 | ... Y67: =IF(Y$45<$G67,0,IF($F67=1,$C$10+($C$11-$C$10)*MIN(Y$45-$G67,$C$12)/$C$12,$E67*$C$5*INDEX($C$6:$C$9,MIN(Y$45-$G67,3)+1)))*(1-$C$14)*IF(AND($C67="Verified",$C$39=1),0,1) -> 15.74625
A69: OpenBench revenue per host (₹)
A70: =A48 -> 1 | B70: =B48 -> Pilot | C70: =C48 -> Assured | H70: =H48*$D48*$C$13*INDEX(Assumptions!$B$44:$B$46,MATCH($C48,Assumptions!$A$44:$A$46,0))+IF(H$45>=$G48,INDEX(Assumptions!$C$44:$C$46,MATCH($C48,Assumptions!$A$44:$A$46,0)),0)+IF($C48="Assured",H48*$D48*$C$13*$C$26*$C$27*$C$28,0) -> 40380.047 | I70: =I48*$D48*$C$13*INDEX(Assumptions!$B$44:$B$46,MATCH($C48,Assumptions!$A$44:$A$46,0))+IF(I$45>=$G48,INDEX(Assumptions!$C$44:$C$46,MATCH($C48,Assumptions!$A$44:$A$46,0)),0)+IF($C48="Assured",I48*$D48*$C$13*$C$26*$C$27*$C$28,0) -> 42302.906 | J70: =J48*$D48*$C$13*INDEX(Assumptions!$B$44:$B$46,MATCH($C48,Assumptions!$A$44:$A$46,0))+IF(J$45>=$G48,INDEX(Assumptions!$C$44:$C$46,MATCH($C48,Assumptions!$A$44:$A$46,0)),0)+IF($C48="Assured",J48*$D48*$C$13*$C$26*$C$27*$C$28,0) -> 44225.766 | K70: =K48*$D48*$C$13*INDEX(Assumptions!$B$44:$B$46,MATCH($C48,Assumptions!$A$44:$A$46,0))+IF(K$45>=$G48,INDEX(Assumptions!$C$44:$C$46,MATCH($C48,Assumptions!$A$44:$A$46,0)),0)+IF($C48="Assured",K48*$D48*$C$13*$C$26*$C$27*$C$28,0) -> 46148.625 | L70: =L48*$D48*$C$13*INDEX(Assumptions!$B$44:$B$46,MATCH($C48,Assumptions!$A$44:$A$46,0))+IF(L$45>=$G48,INDEX(Assumptions!$C$44:$C$46,MATCH($C48,Assumptions!$A$44:$A$46,0)),0)+IF($C48="Assured",L48*$D48*$C$13*$C$26*$C$27*$C$28,0) -> 46148.625 | M70: =M48*$D48*$C$13*INDEX(Assumptions!$B$44:$B$46,MATCH($C48,Assumptions!$A$44:$A$46,0))+IF(M$45>=$G48,INDEX(Assumptions!$C$44:$C$46,MATCH($C48,Assumptions!$A$44:$A$46,0)),0)+IF($C48="Assured",M48*$D48*$C$13*$C$26*$C$27*$C$28,0) -> 46148.625 | N70: =N48*$D48*$C$13*INDEX(Assumptions!$B$44:$B$46,MATCH($C48,Assumptions!$A$44:$A$46,0))+IF(N$45>=$G48,INDEX(Assumptions!$C$44:$C$46,MATCH($C48,Assumptions!$A$44:$A$46,0)),0)+IF($C48="Assured",N48*$D48*$C$13*$C$26*$C$27*$C$28,0) -> 46148.625 | O70: =O48*$D48*$C$13*INDEX(Assumptions!$B$44:$B$46,MATCH($C48,Assumptions!$A$44:$A$46,0))+IF(O$45>=$G48,INDEX(Assumptions!$C$44:$C$46,MATCH($C48,Assumptions!$A$44:$A$46,0)),0)+IF($C48="Assured",O48*$D48*$C$13*$C$26*$C$27*$C$28,0) -> 46148.625 | ... Y70: =Y48*$D48*$C$13*INDEX(Assumptions!$B$44:$B$46,MATCH($C48,Assumptions!$A$44:$A$46,0))+IF(Y$45>=$G48,INDEX(Assumptions!$C$44:$C$46,MATCH($C48,Assumptions!$A$44:$A$46,0)),0)+IF($C48="Assured",Y48*$D48*$C$13*$C$26*$C$27*$C$28,0) -> 46148.625
A71: =A49 -> 2 | B71: =B49 -> Pilot | C71: =C49 -> Assured | H71: =H49*$D49*$C$13*INDEX(Assumptions!$B$44:$B$46,MATCH($C49,Assumptions!$A$44:$A$46,0))+IF(H$45>=$G49,INDEX(Assumptions!$C$44:$C$46,MATCH($C49,Assumptions!$A$44:$A$46,0)),0)+IF($C49="Assured",H49*$D49*$C$13*$C$26*$C$27*$C$28,0) -> 40380.047 | I71: =I49*$D49*$C$13*INDEX(Assumptions!$B$44:$B$46,MATCH($C49,Assumptions!$A$44:$A$46,0))+IF(I$45>=$G49,INDEX(Assumptions!$C$44:$C$46,MATCH($C49,Assumptions!$A$44:$A$46,0)),0)+IF($C49="Assured",I49*$D49*$C$13*$C$26*$C$27*$C$28,0) -> 42302.906 | J71: =J49*$D49*$C$13*INDEX(Assumptions!$B$44:$B$46,MATCH($C49,Assumptions!$A$44:$A$46,0))+IF(J$45>=$G49,INDEX(Assumptions!$C$44:$C$46,MATCH($C49,Assumptions!$A$44:$A$46,0)),0)+IF($C49="Assured",J49*$D49*$C$13*$C$26*$C$27*$C$28,0) -> 44225.766 | K71: =K49*$D49*$C$13*INDEX(Assumptions!$B$44:$B$46,MATCH($C49,Assumptions!$A$44:$A$46,0))+IF(K$45>=$G49,INDEX(Assumptions!$C$44:$C$46,MATCH($C49,Assumptions!$A$44:$A$46,0)),0)+IF($C49="Assured",K49*$D49*$C$13*$C$26*$C$27*$C$28,0) -> 46148.625 | L71: =L49*$D49*$C$13*INDEX(Assumptions!$B$44:$B$46,MATCH($C49,Assumptions!$A$44:$A$46,0))+IF(L$45>=$G49,INDEX(Assumptions!$C$44:$C$46,MATCH($C49,Assumptions!$A$44:$A$46,0)),0)+IF($C49="Assured",L49*$D49*$C$13*$C$26*$C$27*$C$28,0) -> 46148.625 | M71: =M49*$D49*$C$13*INDEX(Assumptions!$B$44:$B$46,MATCH($C49,Assumptions!$A$44:$A$46,0))+IF(M$45>=$G49,INDEX(Assumptions!$C$44:$C$46,MATCH($C49,Assumptions!$A$44:$A$46,0)),0)+IF($C49="Assured",M49*$D49*$C$13*$C$26*$C$27*$C$28,0) -> 46148.625 | N71: =N49*$D49*$C$13*INDEX(Assumptions!$B$44:$B$46,MATCH($C49,Assumptions!$A$44:$A$46,0))+IF(N$45>=$G49,INDEX(Assumptions!$C$44:$C$46,MATCH($C49,Assumptions!$A$44:$A$46,0)),0)+IF($C49="Assured",N49*$D49*$C$13*$C$26*$C$27*$C$28,0) -> 46148.625 | O71: =O49*$D49*$C$13*INDEX(Assumptions!$B$44:$B$46,MATCH($C49,Assumptions!$A$44:$A$46,0))+IF(O$45>=$G49,INDEX(Assumptions!$C$44:$C$46,MATCH($C49,Assumptions!$A$44:$A$46,0)),0)+IF($C49="Assured",O49*$D49*$C$13*$C$26*$C$27*$C$28,0) -> 46148.625 | ... Y71: =Y49*$D49*$C$13*INDEX(Assumptions!$B$44:$B$46,MATCH($C49,Assumptions!$A$44:$A$46,0))+IF(Y$45>=$G49,INDEX(Assumptions!$C$44:$C$46,MATCH($C49,Assumptions!$A$44:$A$46,0)),0)+IF($C49="Assured",Y49*$D49*$C$13*$C$26*$C$27*$C$28,0) -> 46148.625
A72: =A50 -> 3 | B72: =B50 -> Pilot | C72: =C50 -> Assured | H72: =H50*$D50*$C$13*INDEX(Assumptions!$B$44:$B$46,MATCH($C50,Assumptions!$A$44:$A$46,0))+IF(H$45>=$G50,INDEX(Assumptions!$C$44:$C$46,MATCH($C50,Assumptions!$A$44:$A$46,0)),0)+IF($C50="Assured",H50*$D50*$C$13*$C$26*$C$27*$C$28,0) -> 40380.047 | I72: =I50*$D50*$C$13*INDEX(Assumptions!$B$44:$B$46,MATCH($C50,Assumptions!$A$44:$A$46,0))+IF(I$45>=$G50,INDEX(Assumptions!$C$44:$C$46,MATCH($C50,Assumptions!$A$44:$A$46,0)),0)+IF($C50="Assured",I50*$D50*$C$13*$C$26*$C$27*$C$28,0) -> 42302.906 | J72: =J50*$D50*$C$13*INDEX(Assumptions!$B$44:$B$46,MATCH($C50,Assumptions!$A$44:$A$46,0))+IF(J$45>=$G50,INDEX(Assumptions!$C$44:$C$46,MATCH($C50,Assumptions!$A$44:$A$46,0)),0)+IF($C50="Assured",J50*$D50*$C$13*$C$26*$C$27*$C$28,0) -> 44225.766 | K72: =K50*$D50*$C$13*INDEX(Assumptions!$B$44:$B$46,MATCH($C50,Assumptions!$A$44:$A$46,0))+IF(K$45>=$G50,INDEX(Assumptions!$C$44:$C$46,MATCH($C50,Assumptions!$A$44:$A$46,0)),0)+IF($C50="Assured",K50*$D50*$C$13*$C$26*$C$27*$C$28,0) -> 46148.625 | L72: =L50*$D50*$C$13*INDEX(Assumptions!$B$44:$B$46,MATCH($C50,Assumptions!$A$44:$A$46,0))+IF(L$45>=$G50,INDEX(Assumptions!$C$44:$C$46,MATCH($C50,Assumptions!$A$44:$A$46,0)),0)+IF($C50="Assured",L50*$D50*$C$13*$C$26*$C$27*$C$28,0) -> 46148.625 | M72: =M50*$D50*$C$13*INDEX(Assumptions!$B$44:$B$46,MATCH($C50,Assumptions!$A$44:$A$46,0))+IF(M$45>=$G50,INDEX(Assumptions!$C$44:$C$46,MATCH($C50,Assumptions!$A$44:$A$46,0)),0)+IF($C50="Assured",M50*$D50*$C$13*$C$26*$C$27*$C$28,0) -> 46148.625 | N72: =N50*$D50*$C$13*INDEX(Assumptions!$B$44:$B$46,MATCH($C50,Assumptions!$A$44:$A$46,0))+IF(N$45>=$G50,INDEX(Assumptions!$C$44:$C$46,MATCH($C50,Assumptions!$A$44:$A$46,0)),0)+IF($C50="Assured",N50*$D50*$C$13*$C$26*$C$27*$C$28,0) -> 46148.625 | O72: =O50*$D50*$C$13*INDEX(Assumptions!$B$44:$B$46,MATCH($C50,Assumptions!$A$44:$A$46,0))+IF(O$45>=$G50,INDEX(Assumptions!$C$44:$C$46,MATCH($C50,Assumptions!$A$44:$A$46,0)),0)+IF($C50="Assured",O50*$D50*$C$13*$C$26*$C$27*$C$28,0) -> 46148.625 | ... Y72: =Y50*$D50*$C$13*INDEX(Assumptions!$B$44:$B$46,MATCH($C50,Assumptions!$A$44:$A$46,0))+IF(Y$45>=$G50,INDEX(Assumptions!$C$44:$C$46,MATCH($C50,Assumptions!$A$44:$A$46,0)),0)+IF($C50="Assured",Y50*$D50*$C$13*$C$26*$C$27*$C$28,0) -> 46148.625
A73: =A51 -> 4 | B73: =B51 -> Pilot | C73: =C51 -> Assured | H73: =H51*$D51*$C$13*INDEX(Assumptions!$B$44:$B$46,MATCH($C51,Assumptions!$A$44:$A$46,0))+IF(H$45>=$G51,INDEX(Assumptions!$C$44:$C$46,MATCH($C51,Assumptions!$A$44:$A$46,0)),0)+IF($C51="Assured",H51*$D51*$C$13*$C$26*$C$27*$C$28,0) -> 40380.047 | I73: =I51*$D51*$C$13*INDEX(Assumptions!$B$44:$B$46,MATCH($C51,Assumptions!$A$44:$A$46,0))+IF(I$45>=$G51,INDEX(Assumptions!$C$44:$C$46,MATCH($C51,Assumptions!$A$44:$A$46,0)),0)+IF($C51="Assured",I51*$D51*$C$13*$C$26*$C$27*$C$28,0) -> 42302.906 | J73: =J51*$D51*$C$13*INDEX(Assumptions!$B$44:$B$46,MATCH($C51,Assumptions!$A$44:$A$46,0))+IF(J$45>=$G51,INDEX(Assumptions!$C$44:$C$46,MATCH($C51,Assumptions!$A$44:$A$46,0)),0)+IF($C51="Assured",J51*$D51*$C$13*$C$26*$C$27*$C$28,0) -> 44225.766 | K73: =K51*$D51*$C$13*INDEX(Assumptions!$B$44:$B$46,MATCH($C51,Assumptions!$A$44:$A$46,0))+IF(K$45>=$G51,INDEX(Assumptions!$C$44:$C$46,MATCH($C51,Assumptions!$A$44:$A$46,0)),0)+IF($C51="Assured",K51*$D51*$C$13*$C$26*$C$27*$C$28,0) -> 46148.625 | L73: =L51*$D51*$C$13*INDEX(Assumptions!$B$44:$B$46,MATCH($C51,Assumptions!$A$44:$A$46,0))+IF(L$45>=$G51,INDEX(Assumptions!$C$44:$C$46,MATCH($C51,Assumptions!$A$44:$A$46,0)),0)+IF($C51="Assured",L51*$D51*$C$13*$C$26*$C$27*$C$28,0) -> 46148.625 | M73: =M51*$D51*$C$13*INDEX(Assumptions!$B$44:$B$46,MATCH($C51,Assumptions!$A$44:$A$46,0))+IF(M$45>=$G51,INDEX(Assumptions!$C$44:$C$46,MATCH($C51,Assumptions!$A$44:$A$46,0)),0)+IF($C51="Assured",M51*$D51*$C$13*$C$26*$C$27*$C$28,0) -> 46148.625 | N73: =N51*$D51*$C$13*INDEX(Assumptions!$B$44:$B$46,MATCH($C51,Assumptions!$A$44:$A$46,0))+IF(N$45>=$G51,INDEX(Assumptions!$C$44:$C$46,MATCH($C51,Assumptions!$A$44:$A$46,0)),0)+IF($C51="Assured",N51*$D51*$C$13*$C$26*$C$27*$C$28,0) -> 46148.625 | O73: =O51*$D51*$C$13*INDEX(Assumptions!$B$44:$B$46,MATCH($C51,Assumptions!$A$44:$A$46,0))+IF(O$45>=$G51,INDEX(Assumptions!$C$44:$C$46,MATCH($C51,Assumptions!$A$44:$A$46,0)),0)+IF($C51="Assured",O51*$D51*$C$13*$C$26*$C$27*$C$28,0) -> 46148.625 | ... Y73: =Y51*$D51*$C$13*INDEX(Assumptions!$B$44:$B$46,MATCH($C51,Assumptions!$A$44:$A$46,0))+IF(Y$45>=$G51,INDEX(Assumptions!$C$44:$C$46,MATCH($C51,Assumptions!$A$44:$A$46,0)),0)+IF($C51="Assured",Y51*$D51*$C$13*$C$26*$C$27*$C$28,0) -> 46148.625
A74: =A52 -> 5 | B74: =B52 -> A | C74: =C52 -> Assured | H74: =H52*$D52*$C$13*INDEX(Assumptions!$B$44:$B$46,MATCH($C52,Assumptions!$A$44:$A$46,0))+IF(H$45>=$G52,INDEX(Assumptions!$C$44:$C$46,MATCH($C52,Assumptions!$A$44:$A$46,0)),0)+IF($C52="Assured",H52*$D52*$C$13*$C$26*$C$27*$C$28,0) -> 0 | I74: =I52*$D52*$C$13*INDEX(Assumptions!$B$44:$B$46,MATCH($C52,Assumptions!$A$44:$A$46,0))+IF(I$45>=$G52,INDEX(Assumptions!$C$44:$C$46,MATCH($C52,Assumptions!$A$44:$A$46,0)),0)+IF($C52="Assured",I52*$D52*$C$13*$C$26*$C$27*$C$28,0) -> 0 | J74: =J52*$D52*$C$13*INDEX(Assumptions!$B$44:$B$46,MATCH($C52,Assumptions!$A$44:$A$46,0))+IF(J$45>=$G52,INDEX(Assumptions!$C$44:$C$46,MATCH($C52,Assumptions!$A$44:$A$46,0)),0)+IF($C52="Assured",J52*$D52*$C$13*$C$26*$C$27*$C$28,0) -> 0 | K74: =K52*$D52*$C$13*INDEX(Assumptions!$B$44:$B$46,MATCH($C52,Assumptions!$A$44:$A$46,0))+IF(K$45>=$G52,INDEX(Assumptions!$C$44:$C$46,MATCH($C52,Assumptions!$A$44:$A$46,0)),0)+IF($C52="Assured",K52*$D52*$C$13*$C$26*$C$27*$C$28,0) -> 0 | L74: =L52*$D52*$C$13*INDEX(Assumptions!$B$44:$B$46,MATCH($C52,Assumptions!$A$44:$A$46,0))+IF(L$45>=$G52,INDEX(Assumptions!$C$44:$C$46,MATCH($C52,Assumptions!$A$44:$A$46,0)),0)+IF($C52="Assured",L52*$D52*$C$13*$C$26*$C$27*$C$28,0) -> 15245.334 | M74: =M52*$D52*$C$13*INDEX(Assumptions!$B$44:$B$46,MATCH($C52,Assumptions!$A$44:$A$46,0))+IF(M$45>=$G52,INDEX(Assumptions!$C$44:$C$46,MATCH($C52,Assumptions!$A$44:$A$46,0)),0)+IF($C52="Assured",M52*$D52*$C$13*$C$26*$C$27*$C$28,0) -> 30490.668 | N74: =N52*$D52*$C$13*INDEX(Assumptions!$B$44:$B$46,MATCH($C52,Assumptions!$A$44:$A$46,0))+IF(N$45>=$G52,INDEX(Assumptions!$C$44:$C$46,MATCH($C52,Assumptions!$A$44:$A$46,0)),0)+IF($C52="Assured",N52*$D52*$C$13*$C$26*$C$27*$C$28,0) -> 43195.113 | O74: =O52*$D52*$C$13*INDEX(Assumptions!$B$44:$B$46,MATCH($C52,Assumptions!$A$44:$A$46,0))+IF(O$45>=$G52,INDEX(Assumptions!$C$44:$C$46,MATCH($C52,Assumptions!$A$44:$A$46,0)),0)+IF($C52="Assured",O52*$D52*$C$13*$C$26*$C$27*$C$28,0) -> 50817.78 | ... Y74: =Y52*$D52*$C$13*INDEX(Assumptions!$B$44:$B$46,MATCH($C52,Assumptions!$A$44:$A$46,0))+IF(Y$45>=$G52,INDEX(Assumptions!$C$44:$C$46,MATCH($C52,Assumptions!$A$44:$A$46,0)),0)+IF($C52="Assured",Y52*$D52*$C$13*$C$26*$C$27*$C$28,0) -> 50817.78
A75: =A53 -> 6 | B75: =B53 -> A | C75: =C53 -> Assured | H75: =H53*$D53*$C$13*INDEX(Assumptions!$B$44:$B$46,MATCH($C53,Assumptions!$A$44:$A$46,0))+IF(H$45>=$G53,INDEX(Assumptions!$C$44:$C$46,MATCH($C53,Assumptions!$A$44:$A$46,0)),0)+IF($C53="Assured",H53*$D53*$C$13*$C$26*$C$27*$C$28,0) -> 0 | I75: =I53*$D53*$C$13*INDEX(Assumptions!$B$44:$B$46,MATCH($C53,Assumptions!$A$44:$A$46,0))+IF(I$45>=$G53,INDEX(Assumptions!$C$44:$C$46,MATCH($C53,Assumptions!$A$44:$A$46,0)),0)+IF($C53="Assured",I53*$D53*$C$13*$C$26*$C$27*$C$28,0) -> 0 | J75: =J53*$D53*$C$13*INDEX(Assumptions!$B$44:$B$46,MATCH($C53,Assumptions!$A$44:$A$46,0))+IF(J$45>=$G53,INDEX(Assumptions!$C$44:$C$46,MATCH($C53,Assumptions!$A$44:$A$46,0)),0)+IF($C53="Assured",J53*$D53*$C$13*$C$26*$C$27*$C$28,0) -> 0 | K75: =K53*$D53*$C$13*INDEX(Assumptions!$B$44:$B$46,MATCH($C53,Assumptions!$A$44:$A$46,0))+IF(K$45>=$G53,INDEX(Assumptions!$C$44:$C$46,MATCH($C53,Assumptions!$A$44:$A$46,0)),0)+IF($C53="Assured",K53*$D53*$C$13*$C$26*$C$27*$C$28,0) -> 0 | L75: =L53*$D53*$C$13*INDEX(Assumptions!$B$44:$B$46,MATCH($C53,Assumptions!$A$44:$A$46,0))+IF(L$45>=$G53,INDEX(Assumptions!$C$44:$C$46,MATCH($C53,Assumptions!$A$44:$A$46,0)),0)+IF($C53="Assured",L53*$D53*$C$13*$C$26*$C$27*$C$28,0) -> 15245.334 | M75: =M53*$D53*$C$13*INDEX(Assumptions!$B$44:$B$46,MATCH($C53,Assumptions!$A$44:$A$46,0))+IF(M$45>=$G53,INDEX(Assumptions!$C$44:$C$46,MATCH($C53,Assumptions!$A$44:$A$46,0)),0)+IF($C53="Assured",M53*$D53*$C$13*$C$26*$C$27*$C$28,0) -> 30490.668 | N75: =N53*$D53*$C$13*INDEX(Assumptions!$B$44:$B$46,MATCH($C53,Assumptions!$A$44:$A$46,0))+IF(N$45>=$G53,INDEX(Assumptions!$C$44:$C$46,MATCH($C53,Assumptions!$A$44:$A$46,0)),0)+IF($C53="Assured",N53*$D53*$C$13*$C$26*$C$27*$C$28,0) -> 43195.113 | O75: =O53*$D53*$C$13*INDEX(Assumptions!$B$44:$B$46,MATCH($C53,Assumptions!$A$44:$A$46,0))+IF(O$45>=$G53,INDEX(Assumptions!$C$44:$C$46,MATCH($C53,Assumptions!$A$44:$A$46,0)),0)+IF($C53="Assured",O53*$D53*$C$13*$C$26*$C$27*$C$28,0) -> 50817.78 | ... Y75: =Y53*$D53*$C$13*INDEX(Assumptions!$B$44:$B$46,MATCH($C53,Assumptions!$A$44:$A$46,0))+IF(Y$45>=$G53,INDEX(Assumptions!$C$44:$C$46,MATCH($C53,Assumptions!$A$44:$A$46,0)),0)+IF($C53="Assured",Y53*$D53*$C$13*$C$26*$C$27*$C$28,0) -> 50817.78
A76: =A54 -> 7 | B76: =B54 -> A | C76: =C54 -> Assured | H76: =H54*$D54*$C$13*INDEX(Assumptions!$B$44:$B$46,MATCH($C54,Assumptions!$A$44:$A$46,0))+IF(H$45>=$G54,INDEX(Assumptions!$C$44:$C$46,MATCH($C54,Assumptions!$A$44:$A$46,0)),0)+IF($C54="Assured",H54*$D54*$C$13*$C$26*$C$27*$C$28,0) -> 0 | I76: =I54*$D54*$C$13*INDEX(Assumptions!$B$44:$B$46,MATCH($C54,Assumptions!$A$44:$A$46,0))+IF(I$45>=$G54,INDEX(Assumptions!$C$44:$C$46,MATCH($C54,Assumptions!$A$44:$A$46,0)),0)+IF($C54="Assured",I54*$D54*$C$13*$C$26*$C$27*$C$28,0) -> 0 | J76: =J54*$D54*$C$13*INDEX(Assumptions!$B$44:$B$46,MATCH($C54,Assumptions!$A$44:$A$46,0))+IF(J$45>=$G54,INDEX(Assumptions!$C$44:$C$46,MATCH($C54,Assumptions!$A$44:$A$46,0)),0)+IF($C54="Assured",J54*$D54*$C$13*$C$26*$C$27*$C$28,0) -> 0 | K76: =K54*$D54*$C$13*INDEX(Assumptions!$B$44:$B$46,MATCH($C54,Assumptions!$A$44:$A$46,0))+IF(K$45>=$G54,INDEX(Assumptions!$C$44:$C$46,MATCH($C54,Assumptions!$A$44:$A$46,0)),0)+IF($C54="Assured",K54*$D54*$C$13*$C$26*$C$27*$C$28,0) -> 0 | L76: =L54*$D54*$C$13*INDEX(Assumptions!$B$44:$B$46,MATCH($C54,Assumptions!$A$44:$A$46,0))+IF(L$45>=$G54,INDEX(Assumptions!$C$44:$C$46,MATCH($C54,Assumptions!$A$44:$A$46,0)),0)+IF($C54="Assured",L54*$D54*$C$13*$C$26*$C$27*$C$28,0) -> 0 | M76: =M54*$D54*$C$13*INDEX(Assumptions!$B$44:$B$46,MATCH($C54,Assumptions!$A$44:$A$46,0))+IF(M$45>=$G54,INDEX(Assumptions!$C$44:$C$46,MATCH($C54,Assumptions!$A$44:$A$46,0)),0)+IF($C54="Assured",M54*$D54*$C$13*$C$26*$C$27*$C$28,0) -> 15245.334 | N76: =N54*$D54*$C$13*INDEX(Assumptions!$B$44:$B$46,MATCH($C54,Assumptions!$A$44:$A$46,0))+IF(N$45>=$G54,INDEX(Assumptions!$C$44:$C$46,MATCH($C54,Assumptions!$A$44:$A$46,0)),0)+IF($C54="Assured",N54*$D54*$C$13*$C$26*$C$27*$C$28,0) -> 30490.668 | O76: =O54*$D54*$C$13*INDEX(Assumptions!$B$44:$B$46,MATCH($C54,Assumptions!$A$44:$A$46,0))+IF(O$45>=$G54,INDEX(Assumptions!$C$44:$C$46,MATCH($C54,Assumptions!$A$44:$A$46,0)),0)+IF($C54="Assured",O54*$D54*$C$13*$C$26*$C$27*$C$28,0) -> 43195.113 | ... Y76: =Y54*$D54*$C$13*INDEX(Assumptions!$B$44:$B$46,MATCH($C54,Assumptions!$A$44:$A$46,0))+IF(Y$45>=$G54,INDEX(Assumptions!$C$44:$C$46,MATCH($C54,Assumptions!$A$44:$A$46,0)),0)+IF($C54="Assured",Y54*$D54*$C$13*$C$26*$C$27*$C$28,0) -> 50817.78
A77: =A55 -> 8 | B77: =B55 -> A | C77: =C55 -> Assured | H77: =H55*$D55*$C$13*INDEX(Assumptions!$B$44:$B$46,MATCH($C55,Assumptions!$A$44:$A$46,0))+IF(H$45>=$G55,INDEX(Assumptions!$C$44:$C$46,MATCH($C55,Assumptions!$A$44:$A$46,0)),0)+IF($C55="Assured",H55*$D55*$C$13*$C$26*$C$27*$C$28,0) -> 0 | I77: =I55*$D55*$C$13*INDEX(Assumptions!$B$44:$B$46,MATCH($C55,Assumptions!$A$44:$A$46,0))+IF(I$45>=$G55,INDEX(Assumptions!$C$44:$C$46,MATCH($C55,Assumptions!$A$44:$A$46,0)),0)+IF($C55="Assured",I55*$D55*$C$13*$C$26*$C$27*$C$28,0) -> 0 | J77: =J55*$D55*$C$13*INDEX(Assumptions!$B$44:$B$46,MATCH($C55,Assumptions!$A$44:$A$46,0))+IF(J$45>=$G55,INDEX(Assumptions!$C$44:$C$46,MATCH($C55,Assumptions!$A$44:$A$46,0)),0)+IF($C55="Assured",J55*$D55*$C$13*$C$26*$C$27*$C$28,0) -> 0 | K77: =K55*$D55*$C$13*INDEX(Assumptions!$B$44:$B$46,MATCH($C55,Assumptions!$A$44:$A$46,0))+IF(K$45>=$G55,INDEX(Assumptions!$C$44:$C$46,MATCH($C55,Assumptions!$A$44:$A$46,0)),0)+IF($C55="Assured",K55*$D55*$C$13*$C$26*$C$27*$C$28,0) -> 0 | L77: =L55*$D55*$C$13*INDEX(Assumptions!$B$44:$B$46,MATCH($C55,Assumptions!$A$44:$A$46,0))+IF(L$45>=$G55,INDEX(Assumptions!$C$44:$C$46,MATCH($C55,Assumptions!$A$44:$A$46,0)),0)+IF($C55="Assured",L55*$D55*$C$13*$C$26*$C$27*$C$28,0) -> 0 | M77: =M55*$D55*$C$13*INDEX(Assumptions!$B$44:$B$46,MATCH($C55,Assumptions!$A$44:$A$46,0))+IF(M$45>=$G55,INDEX(Assumptions!$C$44:$C$46,MATCH($C55,Assumptions!$A$44:$A$46,0)),0)+IF($C55="Assured",M55*$D55*$C$13*$C$26*$C$27*$C$28,0) -> 15245.334 | N77: =N55*$D55*$C$13*INDEX(Assumptions!$B$44:$B$46,MATCH($C55,Assumptions!$A$44:$A$46,0))+IF(N$45>=$G55,INDEX(Assumptions!$C$44:$C$46,MATCH($C55,Assumptions!$A$44:$A$46,0)),0)+IF($C55="Assured",N55*$D55*$C$13*$C$26*$C$27*$C$28,0) -> 30490.668 | O77: =O55*$D55*$C$13*INDEX(Assumptions!$B$44:$B$46,MATCH($C55,Assumptions!$A$44:$A$46,0))+IF(O$45>=$G55,INDEX(Assumptions!$C$44:$C$46,MATCH($C55,Assumptions!$A$44:$A$46,0)),0)+IF($C55="Assured",O55*$D55*$C$13*$C$26*$C$27*$C$28,0) -> 43195.113 | ... Y77: =Y55*$D55*$C$13*INDEX(Assumptions!$B$44:$B$46,MATCH($C55,Assumptions!$A$44:$A$46,0))+IF(Y$45>=$G55,INDEX(Assumptions!$C$44:$C$46,MATCH($C55,Assumptions!$A$44:$A$46,0)),0)+IF($C55="Assured",Y55*$D55*$C$13*$C$26*$C$27*$C$28,0) -> 50817.78
A78: =A56 -> 9 | B78: =B56 -> A | C78: =C56 -> Assured | H78: =H56*$D56*$C$13*INDEX(Assumptions!$B$44:$B$46,MATCH($C56,Assumptions!$A$44:$A$46,0))+IF(H$45>=$G56,INDEX(Assumptions!$C$44:$C$46,MATCH($C56,Assumptions!$A$44:$A$46,0)),0)+IF($C56="Assured",H56*$D56*$C$13*$C$26*$C$27*$C$28,0) -> 0 | I78: =I56*$D56*$C$13*INDEX(Assumptions!$B$44:$B$46,MATCH($C56,Assumptions!$A$44:$A$46,0))+IF(I$45>=$G56,INDEX(Assumptions!$C$44:$C$46,MATCH($C56,Assumptions!$A$44:$A$46,0)),0)+IF($C56="Assured",I56*$D56*$C$13*$C$26*$C$27*$C$28,0) -> 0 | J78: =J56*$D56*$C$13*INDEX(Assumptions!$B$44:$B$46,MATCH($C56,Assumptions!$A$44:$A$46,0))+IF(J$45>=$G56,INDEX(Assumptions!$C$44:$C$46,MATCH($C56,Assumptions!$A$44:$A$46,0)),0)+IF($C56="Assured",J56*$D56*$C$13*$C$26*$C$27*$C$28,0) -> 0 | K78: =K56*$D56*$C$13*INDEX(Assumptions!$B$44:$B$46,MATCH($C56,Assumptions!$A$44:$A$46,0))+IF(K$45>=$G56,INDEX(Assumptions!$C$44:$C$46,MATCH($C56,Assumptions!$A$44:$A$46,0)),0)+IF($C56="Assured",K56*$D56*$C$13*$C$26*$C$27*$C$28,0) -> 0 | L78: =L56*$D56*$C$13*INDEX(Assumptions!$B$44:$B$46,MATCH($C56,Assumptions!$A$44:$A$46,0))+IF(L$45>=$G56,INDEX(Assumptions!$C$44:$C$46,MATCH($C56,Assumptions!$A$44:$A$46,0)),0)+IF($C56="Assured",L56*$D56*$C$13*$C$26*$C$27*$C$28,0) -> 0 | M78: =M56*$D56*$C$13*INDEX(Assumptions!$B$44:$B$46,MATCH($C56,Assumptions!$A$44:$A$46,0))+IF(M$45>=$G56,INDEX(Assumptions!$C$44:$C$46,MATCH($C56,Assumptions!$A$44:$A$46,0)),0)+IF($C56="Assured",M56*$D56*$C$13*$C$26*$C$27*$C$28,0) -> 0 | N78: =N56*$D56*$C$13*INDEX(Assumptions!$B$44:$B$46,MATCH($C56,Assumptions!$A$44:$A$46,0))+IF(N$45>=$G56,INDEX(Assumptions!$C$44:$C$46,MATCH($C56,Assumptions!$A$44:$A$46,0)),0)+IF($C56="Assured",N56*$D56*$C$13*$C$26*$C$27*$C$28,0) -> 15245.334 | O78: =O56*$D56*$C$13*INDEX(Assumptions!$B$44:$B$46,MATCH($C56,Assumptions!$A$44:$A$46,0))+IF(O$45>=$G56,INDEX(Assumptions!$C$44:$C$46,MATCH($C56,Assumptions!$A$44:$A$46,0)),0)+IF($C56="Assured",O56*$D56*$C$13*$C$26*$C$27*$C$28,0) -> 30490.668 | ... Y78: =Y56*$D56*$C$13*INDEX(Assumptions!$B$44:$B$46,MATCH($C56,Assumptions!$A$44:$A$46,0))+IF(Y$45>=$G56,INDEX(Assumptions!$C$44:$C$46,MATCH($C56,Assumptions!$A$44:$A$46,0)),0)+IF($C56="Assured",Y56*$D56*$C$13*$C$26*$C$27*$C$28,0) -> 50817.78
A79: =A57 -> 10 | B79: =B57 -> C | C79: =C57 -> Assured | H79: =H57*$D57*$C$13*INDEX(Assumptions!$B$44:$B$46,MATCH($C57,Assumptions!$A$44:$A$46,0))+IF(H$45>=$G57,INDEX(Assumptions!$C$44:$C$46,MATCH($C57,Assumptions!$A$44:$A$46,0)),0)+IF($C57="Assured",H57*$D57*$C$13*$C$26*$C$27*$C$28,0) -> 0 | I79: =I57*$D57*$C$13*INDEX(Assumptions!$B$44:$B$46,MATCH($C57,Assumptions!$A$44:$A$46,0))+IF(I$45>=$G57,INDEX(Assumptions!$C$44:$C$46,MATCH($C57,Assumptions!$A$44:$A$46,0)),0)+IF($C57="Assured",I57*$D57*$C$13*$C$26*$C$27*$C$28,0) -> 0 | J79: =J57*$D57*$C$13*INDEX(Assumptions!$B$44:$B$46,MATCH($C57,Assumptions!$A$44:$A$46,0))+IF(J$45>=$G57,INDEX(Assumptions!$C$44:$C$46,MATCH($C57,Assumptions!$A$44:$A$46,0)),0)+IF($C57="Assured",J57*$D57*$C$13*$C$26*$C$27*$C$28,0) -> 0 | K79: =K57*$D57*$C$13*INDEX(Assumptions!$B$44:$B$46,MATCH($C57,Assumptions!$A$44:$A$46,0))+IF(K$45>=$G57,INDEX(Assumptions!$C$44:$C$46,MATCH($C57,Assumptions!$A$44:$A$46,0)),0)+IF($C57="Assured",K57*$D57*$C$13*$C$26*$C$27*$C$28,0) -> 0 | L79: =L57*$D57*$C$13*INDEX(Assumptions!$B$44:$B$46,MATCH($C57,Assumptions!$A$44:$A$46,0))+IF(L$45>=$G57,INDEX(Assumptions!$C$44:$C$46,MATCH($C57,Assumptions!$A$44:$A$46,0)),0)+IF($C57="Assured",L57*$D57*$C$13*$C$26*$C$27*$C$28,0) -> 0 | M79: =M57*$D57*$C$13*INDEX(Assumptions!$B$44:$B$46,MATCH($C57,Assumptions!$A$44:$A$46,0))+IF(M$45>=$G57,INDEX(Assumptions!$C$44:$C$46,MATCH($C57,Assumptions!$A$44:$A$46,0)),0)+IF($C57="Assured",M57*$D57*$C$13*$C$26*$C$27*$C$28,0) -> 0 | N79: =N57*$D57*$C$13*INDEX(Assumptions!$B$44:$B$46,MATCH($C57,Assumptions!$A$44:$A$46,0))+IF(N$45>=$G57,INDEX(Assumptions!$C$44:$C$46,MATCH($C57,Assumptions!$A$44:$A$46,0)),0)+IF($C57="Assured",N57*$D57*$C$13*$C$26*$C$27*$C$28,0) -> 0 | O79: =O57*$D57*$C$13*INDEX(Assumptions!$B$44:$B$46,MATCH($C57,Assumptions!$A$44:$A$46,0))+IF(O$45>=$G57,INDEX(Assumptions!$C$44:$C$46,MATCH($C57,Assumptions!$A$44:$A$46,0)),0)+IF($C57="Assured",O57*$D57*$C$13*$C$26*$C$27*$C$28,0) -> 11010.519 | ... Y79: =Y57*$D57*$C$13*INDEX(Assumptions!$B$44:$B$46,MATCH($C57,Assumptions!$A$44:$A$46,0))+IF(Y$45>=$G57,INDEX(Assumptions!$C$44:$C$46,MATCH($C57,Assumptions!$A$44:$A$46,0)),0)+IF($C57="Assured",Y57*$D57*$C$13*$C$26*$C$27*$C$28,0) -> 36701.73
A80: =A58 -> 11 | B80: =B58 -> C | C80: =C58 -> Assured | H80: =H58*$D58*$C$13*INDEX(Assumptions!$B$44:$B$46,MATCH($C58,Assumptions!$A$44:$A$46,0))+IF(H$45>=$G58,INDEX(Assumptions!$C$44:$C$46,MATCH($C58,Assumptions!$A$44:$A$46,0)),0)+IF($C58="Assured",H58*$D58*$C$13*$C$26*$C$27*$C$28,0) -> 0 | I80: =I58*$D58*$C$13*INDEX(Assumptions!$B$44:$B$46,MATCH($C58,Assumptions!$A$44:$A$46,0))+IF(I$45>=$G58,INDEX(Assumptions!$C$44:$C$46,MATCH($C58,Assumptions!$A$44:$A$46,0)),0)+IF($C58="Assured",I58*$D58*$C$13*$C$26*$C$27*$C$28,0) -> 0 | J80: =J58*$D58*$C$13*INDEX(Assumptions!$B$44:$B$46,MATCH($C58,Assumptions!$A$44:$A$46,0))+IF(J$45>=$G58,INDEX(Assumptions!$C$44:$C$46,MATCH($C58,Assumptions!$A$44:$A$46,0)),0)+IF($C58="Assured",J58*$D58*$C$13*$C$26*$C$27*$C$28,0) -> 0 | K80: =K58*$D58*$C$13*INDEX(Assumptions!$B$44:$B$46,MATCH($C58,Assumptions!$A$44:$A$46,0))+IF(K$45>=$G58,INDEX(Assumptions!$C$44:$C$46,MATCH($C58,Assumptions!$A$44:$A$46,0)),0)+IF($C58="Assured",K58*$D58*$C$13*$C$26*$C$27*$C$28,0) -> 0 | L80: =L58*$D58*$C$13*INDEX(Assumptions!$B$44:$B$46,MATCH($C58,Assumptions!$A$44:$A$46,0))+IF(L$45>=$G58,INDEX(Assumptions!$C$44:$C$46,MATCH($C58,Assumptions!$A$44:$A$46,0)),0)+IF($C58="Assured",L58*$D58*$C$13*$C$26*$C$27*$C$28,0) -> 0 | M80: =M58*$D58*$C$13*INDEX(Assumptions!$B$44:$B$46,MATCH($C58,Assumptions!$A$44:$A$46,0))+IF(M$45>=$G58,INDEX(Assumptions!$C$44:$C$46,MATCH($C58,Assumptions!$A$44:$A$46,0)),0)+IF($C58="Assured",M58*$D58*$C$13*$C$26*$C$27*$C$28,0) -> 0 | N80: =N58*$D58*$C$13*INDEX(Assumptions!$B$44:$B$46,MATCH($C58,Assumptions!$A$44:$A$46,0))+IF(N$45>=$G58,INDEX(Assumptions!$C$44:$C$46,MATCH($C58,Assumptions!$A$44:$A$46,0)),0)+IF($C58="Assured",N58*$D58*$C$13*$C$26*$C$27*$C$28,0) -> 0 | O80: =O58*$D58*$C$13*INDEX(Assumptions!$B$44:$B$46,MATCH($C58,Assumptions!$A$44:$A$46,0))+IF(O$45>=$G58,INDEX(Assumptions!$C$44:$C$46,MATCH($C58,Assumptions!$A$44:$A$46,0)),0)+IF($C58="Assured",O58*$D58*$C$13*$C$26*$C$27*$C$28,0) -> 0 | ... Y80: =Y58*$D58*$C$13*INDEX(Assumptions!$B$44:$B$46,MATCH($C58,Assumptions!$A$44:$A$46,0))+IF(Y$45>=$G58,INDEX(Assumptions!$C$44:$C$46,MATCH($C58,Assumptions!$A$44:$A$46,0)),0)+IF($C58="Assured",Y58*$D58*$C$13*$C$26*$C$27*$C$28,0) -> 36701.73
A81: =A59 -> 12 | B81: =B59 -> C | C81: =C59 -> Assured | H81: =H59*$D59*$C$13*INDEX(Assumptions!$B$44:$B$46,MATCH($C59,Assumptions!$A$44:$A$46,0))+IF(H$45>=$G59,INDEX(Assumptions!$C$44:$C$46,MATCH($C59,Assumptions!$A$44:$A$46,0)),0)+IF($C59="Assured",H59*$D59*$C$13*$C$26*$C$27*$C$28,0) -> 0 | I81: =I59*$D59*$C$13*INDEX(Assumptions!$B$44:$B$46,MATCH($C59,Assumptions!$A$44:$A$46,0))+IF(I$45>=$G59,INDEX(Assumptions!$C$44:$C$46,MATCH($C59,Assumptions!$A$44:$A$46,0)),0)+IF($C59="Assured",I59*$D59*$C$13*$C$26*$C$27*$C$28,0) -> 0 | J81: =J59*$D59*$C$13*INDEX(Assumptions!$B$44:$B$46,MATCH($C59,Assumptions!$A$44:$A$46,0))+IF(J$45>=$G59,INDEX(Assumptions!$C$44:$C$46,MATCH($C59,Assumptions!$A$44:$A$46,0)),0)+IF($C59="Assured",J59*$D59*$C$13*$C$26*$C$27*$C$28,0) -> 0 | K81: =K59*$D59*$C$13*INDEX(Assumptions!$B$44:$B$46,MATCH($C59,Assumptions!$A$44:$A$46,0))+IF(K$45>=$G59,INDEX(Assumptions!$C$44:$C$46,MATCH($C59,Assumptions!$A$44:$A$46,0)),0)+IF($C59="Assured",K59*$D59*$C$13*$C$26*$C$27*$C$28,0) -> 0 | L81: =L59*$D59*$C$13*INDEX(Assumptions!$B$44:$B$46,MATCH($C59,Assumptions!$A$44:$A$46,0))+IF(L$45>=$G59,INDEX(Assumptions!$C$44:$C$46,MATCH($C59,Assumptions!$A$44:$A$46,0)),0)+IF($C59="Assured",L59*$D59*$C$13*$C$26*$C$27*$C$28,0) -> 0 | M81: =M59*$D59*$C$13*INDEX(Assumptions!$B$44:$B$46,MATCH($C59,Assumptions!$A$44:$A$46,0))+IF(M$45>=$G59,INDEX(Assumptions!$C$44:$C$46,MATCH($C59,Assumptions!$A$44:$A$46,0)),0)+IF($C59="Assured",M59*$D59*$C$13*$C$26*$C$27*$C$28,0) -> 0 | N81: =N59*$D59*$C$13*INDEX(Assumptions!$B$44:$B$46,MATCH($C59,Assumptions!$A$44:$A$46,0))+IF(N$45>=$G59,INDEX(Assumptions!$C$44:$C$46,MATCH($C59,Assumptions!$A$44:$A$46,0)),0)+IF($C59="Assured",N59*$D59*$C$13*$C$26*$C$27*$C$28,0) -> 0 | O81: =O59*$D59*$C$13*INDEX(Assumptions!$B$44:$B$46,MATCH($C59,Assumptions!$A$44:$A$46,0))+IF(O$45>=$G59,INDEX(Assumptions!$C$44:$C$46,MATCH($C59,Assumptions!$A$44:$A$46,0)),0)+IF($C59="Assured",O59*$D59*$C$13*$C$26*$C$27*$C$28,0) -> 0 | ... Y81: =Y59*$D59*$C$13*INDEX(Assumptions!$B$44:$B$46,MATCH($C59,Assumptions!$A$44:$A$46,0))+IF(Y$45>=$G59,INDEX(Assumptions!$C$44:$C$46,MATCH($C59,Assumptions!$A$44:$A$46,0)),0)+IF($C59="Assured",Y59*$D59*$C$13*$C$26*$C$27*$C$28,0) -> 36701.73
... A89: =A67 -> 20 | B89: =B67 -> B | C89: =C67 -> Verified | H89: =H67*$D67*$C$13*INDEX(Assumptions!$B$44:$B$46,MATCH($C67,Assumptions!$A$44:$A$46,0))+IF(H$45>=$G67,INDEX(Assumptions!$C$44:$C$46,MATCH($C67,Assumptions!$A$44:$A$46,0)),0)+IF($C67="Assured",H67*$D67*$C$13*$C$26*$C$27*$C$28,0) -> 0 | I89: =I67*$D67*$C$13*INDEX(Assumptions!$B$44:$B$46,MATCH($C67,Assumptions!$A$44:$A$46,0))+IF(I$45>=$G67,INDEX(Assumptions!$C$44:$C$46,MATCH($C67,Assumptions!$A$44:$A$46,0)),0)+IF($C67="Assured",I67*$D67*$C$13*$C$26*$C$27*$C$28,0) -> 0 | J89: =J67*$D67*$C$13*INDEX(Assumptions!$B$44:$B$46,MATCH($C67,Assumptions!$A$44:$A$46,0))+IF(J$45>=$G67,INDEX(Assumptions!$C$44:$C$46,MATCH($C67,Assumptions!$A$44:$A$46,0)),0)+IF($C67="Assured",J67*$D67*$C$13*$C$26*$C$27*$C$28,0) -> 0 | K89: =K67*$D67*$C$13*INDEX(Assumptions!$B$44:$B$46,MATCH($C67,Assumptions!$A$44:$A$46,0))+IF(K$45>=$G67,INDEX(Assumptions!$C$44:$C$46,MATCH($C67,Assumptions!$A$44:$A$46,0)),0)+IF($C67="Assured",K67*$D67*$C$13*$C$26*$C$27*$C$28,0) -> 0 | L89: =L67*$D67*$C$13*INDEX(Assumptions!$B$44:$B$46,MATCH($C67,Assumptions!$A$44:$A$46,0))+IF(L$45>=$G67,INDEX(Assumptions!$C$44:$C$46,MATCH($C67,Assumptions!$A$44:$A$46,0)),0)+IF($C67="Assured",L67*$D67*$C$13*$C$26*$C$27*$C$28,0) -> 0 | M89: =M67*$D67*$C$13*INDEX(Assumptions!$B$44:$B$46,MATCH($C67,Assumptions!$A$44:$A$46,0))+IF(M$45>=$G67,INDEX(Assumptions!$C$44:$C$46,MATCH($C67,Assumptions!$A$44:$A$46,0)),0)+IF($C67="Assured",M67*$D67*$C$13*$C$26*$C$27*$C$28,0) -> 0 | N89: =N67*$D67*$C$13*INDEX(Assumptions!$B$44:$B$46,MATCH($C67,Assumptions!$A$44:$A$46,0))+IF(N$45>=$G67,INDEX(Assumptions!$C$44:$C$46,MATCH($C67,Assumptions!$A$44:$A$46,0)),0)+IF($C67="Assured",N67*$D67*$C$13*$C$26*$C$27*$C$28,0) -> 0 | O89: =O67*$D67*$C$13*INDEX(Assumptions!$B$44:$B$46,MATCH($C67,Assumptions!$A$44:$A$46,0))+IF(O$45>=$G67,INDEX(Assumptions!$C$44:$C$46,MATCH($C67,Assumptions!$A$44:$A$46,0)),0)+IF($C67="Assured",O67*$D67*$C$13*$C$26*$C$27*$C$28,0) -> 0 | ... Y89: =Y67*$D67*$C$13*INDEX(Assumptions!$B$44:$B$46,MATCH($C67,Assumptions!$A$44:$A$46,0))+IF(Y$45>=$G67,INDEX(Assumptions!$C$44:$C$46,MATCH($C67,Assumptions!$A$44:$A$46,0)),0)+IF($C67="Assured",Y67*$D67*$C$13*$C$26*$C$27*$C$28,0) -> 16580.801
A91: Variable cost per host (₹)
A92: =A48 -> 1 | B92: =B48 -> Pilot | C92: =C48 -> Assured | H92: =H48*IF(AND($C48="Assured",H$45>=$C$25),$C$24,INDEX(Assumptions!$D$44:$D$46,MATCH($C48,Assumptions!$A$44:$A$46,0))) -> 22443.75 | I92: =I48*IF(AND($C48="Assured",I$45>=$C$25),$C$24,INDEX(Assumptions!$D$44:$D$46,MATCH($C48,Assumptions!$A$44:$A$46,0))) -> 23512.5 | J92: =J48*IF(AND($C48="Assured",J$45>=$C$25),$C$24,INDEX(Assumptions!$D$44:$D$46,MATCH($C48,Assumptions!$A$44:$A$46,0))) -> 24581.25 | K92: =K48*IF(AND($C48="Assured",K$45>=$C$25),$C$24,INDEX(Assumptions!$D$44:$D$46,MATCH($C48,Assumptions!$A$44:$A$46,0))) -> 25650 | L92: =L48*IF(AND($C48="Assured",L$45>=$C$25),$C$24,INDEX(Assumptions!$D$44:$D$46,MATCH($C48,Assumptions!$A$44:$A$46,0))) -> 25650 | M92: =M48*IF(AND($C48="Assured",M$45>=$C$25),$C$24,INDEX(Assumptions!$D$44:$D$46,MATCH($C48,Assumptions!$A$44:$A$46,0))) -> 25650 | N92: =N48*IF(AND($C48="Assured",N$45>=$C$25),$C$24,INDEX(Assumptions!$D$44:$D$46,MATCH($C48,Assumptions!$A$44:$A$46,0))) -> 25650 | O92: =O48*IF(AND($C48="Assured",O$45>=$C$25),$C$24,INDEX(Assumptions!$D$44:$D$46,MATCH($C48,Assumptions!$A$44:$A$46,0))) -> 25650 | ... Y92: =Y48*IF(AND($C48="Assured",Y$45>=$C$25),$C$24,INDEX(Assumptions!$D$44:$D$46,MATCH($C48,Assumptions!$A$44:$A$46,0))) -> 22800
A93: =A49 -> 2 | B93: =B49 -> Pilot | C93: =C49 -> Assured | H93: =H49*IF(AND($C49="Assured",H$45>=$C$25),$C$24,INDEX(Assumptions!$D$44:$D$46,MATCH($C49,Assumptions!$A$44:$A$46,0))) -> 22443.75 | I93: =I49*IF(AND($C49="Assured",I$45>=$C$25),$C$24,INDEX(Assumptions!$D$44:$D$46,MATCH($C49,Assumptions!$A$44:$A$46,0))) -> 23512.5 | J93: =J49*IF(AND($C49="Assured",J$45>=$C$25),$C$24,INDEX(Assumptions!$D$44:$D$46,MATCH($C49,Assumptions!$A$44:$A$46,0))) -> 24581.25 | K93: =K49*IF(AND($C49="Assured",K$45>=$C$25),$C$24,INDEX(Assumptions!$D$44:$D$46,MATCH($C49,Assumptions!$A$44:$A$46,0))) -> 25650 | L93: =L49*IF(AND($C49="Assured",L$45>=$C$25),$C$24,INDEX(Assumptions!$D$44:$D$46,MATCH($C49,Assumptions!$A$44:$A$46,0))) -> 25650 | M93: =M49*IF(AND($C49="Assured",M$45>=$C$25),$C$24,INDEX(Assumptions!$D$44:$D$46,MATCH($C49,Assumptions!$A$44:$A$46,0))) -> 25650 | N93: =N49*IF(AND($C49="Assured",N$45>=$C$25),$C$24,INDEX(Assumptions!$D$44:$D$46,MATCH($C49,Assumptions!$A$44:$A$46,0))) -> 25650 | O93: =O49*IF(AND($C49="Assured",O$45>=$C$25),$C$24,INDEX(Assumptions!$D$44:$D$46,MATCH($C49,Assumptions!$A$44:$A$46,0))) -> 25650 | ... Y93: =Y49*IF(AND($C49="Assured",Y$45>=$C$25),$C$24,INDEX(Assumptions!$D$44:$D$46,MATCH($C49,Assumptions!$A$44:$A$46,0))) -> 22800
A94: =A50 -> 3 | B94: =B50 -> Pilot | C94: =C50 -> Assured | H94: =H50*IF(AND($C50="Assured",H$45>=$C$25),$C$24,INDEX(Assumptions!$D$44:$D$46,MATCH($C50,Assumptions!$A$44:$A$46,0))) -> 22443.75 | I94: =I50*IF(AND($C50="Assured",I$45>=$C$25),$C$24,INDEX(Assumptions!$D$44:$D$46,MATCH($C50,Assumptions!$A$44:$A$46,0))) -> 23512.5 | J94: =J50*IF(AND($C50="Assured",J$45>=$C$25),$C$24,INDEX(Assumptions!$D$44:$D$46,MATCH($C50,Assumptions!$A$44:$A$46,0))) -> 24581.25 | K94: =K50*IF(AND($C50="Assured",K$45>=$C$25),$C$24,INDEX(Assumptions!$D$44:$D$46,MATCH($C50,Assumptions!$A$44:$A$46,0))) -> 25650 | L94: =L50*IF(AND($C50="Assured",L$45>=$C$25),$C$24,INDEX(Assumptions!$D$44:$D$46,MATCH($C50,Assumptions!$A$44:$A$46,0))) -> 25650 | M94: =M50*IF(AND($C50="Assured",M$45>=$C$25),$C$24,INDEX(Assumptions!$D$44:$D$46,MATCH($C50,Assumptions!$A$44:$A$46,0))) -> 25650 | N94: =N50*IF(AND($C50="Assured",N$45>=$C$25),$C$24,INDEX(Assumptions!$D$44:$D$46,MATCH($C50,Assumptions!$A$44:$A$46,0))) -> 25650 | O94: =O50*IF(AND($C50="Assured",O$45>=$C$25),$C$24,INDEX(Assumptions!$D$44:$D$46,MATCH($C50,Assumptions!$A$44:$A$46,0))) -> 25650 | ... Y94: =Y50*IF(AND($C50="Assured",Y$45>=$C$25),$C$24,INDEX(Assumptions!$D$44:$D$46,MATCH($C50,Assumptions!$A$44:$A$46,0))) -> 22800
A95: =A51 -> 4 | B95: =B51 -> Pilot | C95: =C51 -> Assured | H95: =H51*IF(AND($C51="Assured",H$45>=$C$25),$C$24,INDEX(Assumptions!$D$44:$D$46,MATCH($C51,Assumptions!$A$44:$A$46,0))) -> 22443.75 | I95: =I51*IF(AND($C51="Assured",I$45>=$C$25),$C$24,INDEX(Assumptions!$D$44:$D$46,MATCH($C51,Assumptions!$A$44:$A$46,0))) -> 23512.5 | J95: =J51*IF(AND($C51="Assured",J$45>=$C$25),$C$24,INDEX(Assumptions!$D$44:$D$46,MATCH($C51,Assumptions!$A$44:$A$46,0))) -> 24581.25 | K95: =K51*IF(AND($C51="Assured",K$45>=$C$25),$C$24,INDEX(Assumptions!$D$44:$D$46,MATCH($C51,Assumptions!$A$44:$A$46,0))) -> 25650 | L95: =L51*IF(AND($C51="Assured",L$45>=$C$25),$C$24,INDEX(Assumptions!$D$44:$D$46,MATCH($C51,Assumptions!$A$44:$A$46,0))) -> 25650 | M95: =M51*IF(AND($C51="Assured",M$45>=$C$25),$C$24,INDEX(Assumptions!$D$44:$D$46,MATCH($C51,Assumptions!$A$44:$A$46,0))) -> 25650 | N95: =N51*IF(AND($C51="Assured",N$45>=$C$25),$C$24,INDEX(Assumptions!$D$44:$D$46,MATCH($C51,Assumptions!$A$44:$A$46,0))) -> 25650 | O95: =O51*IF(AND($C51="Assured",O$45>=$C$25),$C$24,INDEX(Assumptions!$D$44:$D$46,MATCH($C51,Assumptions!$A$44:$A$46,0))) -> 25650 | ... Y95: =Y51*IF(AND($C51="Assured",Y$45>=$C$25),$C$24,INDEX(Assumptions!$D$44:$D$46,MATCH($C51,Assumptions!$A$44:$A$46,0))) -> 22800
A96: =A52 -> 5 | B96: =B52 -> A | C96: =C52 -> Assured | H96: =H52*IF(AND($C52="Assured",H$45>=$C$25),$C$24,INDEX(Assumptions!$D$44:$D$46,MATCH($C52,Assumptions!$A$44:$A$46,0))) -> 0 | I96: =I52*IF(AND($C52="Assured",I$45>=$C$25),$C$24,INDEX(Assumptions!$D$44:$D$46,MATCH($C52,Assumptions!$A$44:$A$46,0))) -> 0 | J96: =J52*IF(AND($C52="Assured",J$45>=$C$25),$C$24,INDEX(Assumptions!$D$44:$D$46,MATCH($C52,Assumptions!$A$44:$A$46,0))) -> 0 | K96: =K52*IF(AND($C52="Assured",K$45>=$C$25),$C$24,INDEX(Assumptions!$D$44:$D$46,MATCH($C52,Assumptions!$A$44:$A$46,0))) -> 0 | L96: =L52*IF(AND($C52="Assured",L$45>=$C$25),$C$24,INDEX(Assumptions!$D$44:$D$46,MATCH($C52,Assumptions!$A$44:$A$46,0))) -> 6002.1 | M96: =M52*IF(AND($C52="Assured",M$45>=$C$25),$C$24,INDEX(Assumptions!$D$44:$D$46,MATCH($C52,Assumptions!$A$44:$A$46,0))) -> 12004.2 | N96: =N52*IF(AND($C52="Assured",N$45>=$C$25),$C$24,INDEX(Assumptions!$D$44:$D$46,MATCH($C52,Assumptions!$A$44:$A$46,0))) -> 17005.95 | O96: =O52*IF(AND($C52="Assured",O$45>=$C$25),$C$24,INDEX(Assumptions!$D$44:$D$46,MATCH($C52,Assumptions!$A$44:$A$46,0))) -> 20007 | ... Y96: =Y52*IF(AND($C52="Assured",Y$45>=$C$25),$C$24,INDEX(Assumptions!$D$44:$D$46,MATCH($C52,Assumptions!$A$44:$A$46,0))) -> 17784
A97: =A53 -> 6 | B97: =B53 -> A | C97: =C53 -> Assured | H97: =H53*IF(AND($C53="Assured",H$45>=$C$25),$C$24,INDEX(Assumptions!$D$44:$D$46,MATCH($C53,Assumptions!$A$44:$A$46,0))) -> 0 | I97: =I53*IF(AND($C53="Assured",I$45>=$C$25),$C$24,INDEX(Assumptions!$D$44:$D$46,MATCH($C53,Assumptions!$A$44:$A$46,0))) -> 0 | J97: =J53*IF(AND($C53="Assured",J$45>=$C$25),$C$24,INDEX(Assumptions!$D$44:$D$46,MATCH($C53,Assumptions!$A$44:$A$46,0))) -> 0 | K97: =K53*IF(AND($C53="Assured",K$45>=$C$25),$C$24,INDEX(Assumptions!$D$44:$D$46,MATCH($C53,Assumptions!$A$44:$A$46,0))) -> 0 | L97: =L53*IF(AND($C53="Assured",L$45>=$C$25),$C$24,INDEX(Assumptions!$D$44:$D$46,MATCH($C53,Assumptions!$A$44:$A$46,0))) -> 6002.1 | M97: =M53*IF(AND($C53="Assured",M$45>=$C$25),$C$24,INDEX(Assumptions!$D$44:$D$46,MATCH($C53,Assumptions!$A$44:$A$46,0))) -> 12004.2 | N97: =N53*IF(AND($C53="Assured",N$45>=$C$25),$C$24,INDEX(Assumptions!$D$44:$D$46,MATCH($C53,Assumptions!$A$44:$A$46,0))) -> 17005.95 | O97: =O53*IF(AND($C53="Assured",O$45>=$C$25),$C$24,INDEX(Assumptions!$D$44:$D$46,MATCH($C53,Assumptions!$A$44:$A$46,0))) -> 20007 | ... Y97: =Y53*IF(AND($C53="Assured",Y$45>=$C$25),$C$24,INDEX(Assumptions!$D$44:$D$46,MATCH($C53,Assumptions!$A$44:$A$46,0))) -> 17784
A98: =A54 -> 7 | B98: =B54 -> A | C98: =C54 -> Assured | H98: =H54*IF(AND($C54="Assured",H$45>=$C$25),$C$24,INDEX(Assumptions!$D$44:$D$46,MATCH($C54,Assumptions!$A$44:$A$46,0))) -> 0 | I98: =I54*IF(AND($C54="Assured",I$45>=$C$25),$C$24,INDEX(Assumptions!$D$44:$D$46,MATCH($C54,Assumptions!$A$44:$A$46,0))) -> 0 | J98: =J54*IF(AND($C54="Assured",J$45>=$C$25),$C$24,INDEX(Assumptions!$D$44:$D$46,MATCH($C54,Assumptions!$A$44:$A$46,0))) -> 0 | K98: =K54*IF(AND($C54="Assured",K$45>=$C$25),$C$24,INDEX(Assumptions!$D$44:$D$46,MATCH($C54,Assumptions!$A$44:$A$46,0))) -> 0 | L98: =L54*IF(AND($C54="Assured",L$45>=$C$25),$C$24,INDEX(Assumptions!$D$44:$D$46,MATCH($C54,Assumptions!$A$44:$A$46,0))) -> 0 | M98: =M54*IF(AND($C54="Assured",M$45>=$C$25),$C$24,INDEX(Assumptions!$D$44:$D$46,MATCH($C54,Assumptions!$A$44:$A$46,0))) -> 6002.1 | N98: =N54*IF(AND($C54="Assured",N$45>=$C$25),$C$24,INDEX(Assumptions!$D$44:$D$46,MATCH($C54,Assumptions!$A$44:$A$46,0))) -> 12004.2 | O98: =O54*IF(AND($C54="Assured",O$45>=$C$25),$C$24,INDEX(Assumptions!$D$44:$D$46,MATCH($C54,Assumptions!$A$44:$A$46,0))) -> 17005.95 | ... Y98: =Y54*IF(AND($C54="Assured",Y$45>=$C$25),$C$24,INDEX(Assumptions!$D$44:$D$46,MATCH($C54,Assumptions!$A$44:$A$46,0))) -> 17784
A99: =A55 -> 8 | B99: =B55 -> A | C99: =C55 -> Assured | H99: =H55*IF(AND($C55="Assured",H$45>=$C$25),$C$24,INDEX(Assumptions!$D$44:$D$46,MATCH($C55,Assumptions!$A$44:$A$46,0))) -> 0 | I99: =I55*IF(AND($C55="Assured",I$45>=$C$25),$C$24,INDEX(Assumptions!$D$44:$D$46,MATCH($C55,Assumptions!$A$44:$A$46,0))) -> 0 | J99: =J55*IF(AND($C55="Assured",J$45>=$C$25),$C$24,INDEX(Assumptions!$D$44:$D$46,MATCH($C55,Assumptions!$A$44:$A$46,0))) -> 0 | K99: =K55*IF(AND($C55="Assured",K$45>=$C$25),$C$24,INDEX(Assumptions!$D$44:$D$46,MATCH($C55,Assumptions!$A$44:$A$46,0))) -> 0 | L99: =L55*IF(AND($C55="Assured",L$45>=$C$25),$C$24,INDEX(Assumptions!$D$44:$D$46,MATCH($C55,Assumptions!$A$44:$A$46,0))) -> 0 | M99: =M55*IF(AND($C55="Assured",M$45>=$C$25),$C$24,INDEX(Assumptions!$D$44:$D$46,MATCH($C55,Assumptions!$A$44:$A$46,0))) -> 6002.1 | N99: =N55*IF(AND($C55="Assured",N$45>=$C$25),$C$24,INDEX(Assumptions!$D$44:$D$46,MATCH($C55,Assumptions!$A$44:$A$46,0))) -> 12004.2 | O99: =O55*IF(AND($C55="Assured",O$45>=$C$25),$C$24,INDEX(Assumptions!$D$44:$D$46,MATCH($C55,Assumptions!$A$44:$A$46,0))) -> 17005.95 | ... Y99: =Y55*IF(AND($C55="Assured",Y$45>=$C$25),$C$24,INDEX(Assumptions!$D$44:$D$46,MATCH($C55,Assumptions!$A$44:$A$46,0))) -> 17784
